<ITEM>
  <TITEL>ズアオホオジロ</TITLE>
  <META>{{出典の明記|date=2011年11月}}{{生物分類表n|名称 = ズアオホオジロn|画像 = [[ファイル:Ortolan.jpg|250px]]n|画像キャプション = ズアオホオジロn|省略 = 鳥綱n|目 = [[スズメ目]]{{Sname||Passerine|Passeriformes}}{{Sname||Emberizidae}}{{Snamei||Emberiza}}{{Snamei|E. hortulana}}{{Snamei||Emberiza hortulana}}{{Snamei||Emberiza hortulana}}{{Sname||Passeriformes}}{{Sname||Passeri}}{{Sname||Passerida}}{{Sname||Passeroidea}}{{Sname||Fringillidae}}{{Sname||Emberizinae}}{{Sname||Emberizini}}{{Bird-stub}}{{デフォルトソート:すあおほおしろ}}</META>
  <DESCRIPTION>	\n{{生物分類表\n|名称 = ズアオホオジロ\n|画像 = [[ファイル:Ortolan.jpg|250px]]\n|画像キャプション = ズアオホオジロ\n|省略 = 鳥綱\n|目 = [[スズメ目]] \n|科 = [[ホオジロ科]] \n|属 = [[ホオジロ属]] \n|種 = '''ズアオホオジロ''' \n|学名 = \n|和名 = ズアオホオジロ\n|英名 = [[:en:Cirl Bunting|Cirl Bunting]]\n}}\n[[File:Emberiza hortulana MHNT.ZOO.2010.11.217 Neschers.jpg|thumb|'' Emberiza Hortulano'']] \n\n'''ズアオホオジロ'''（[[学名]]：）は、[[鳥類]]の1種。[[ホオジロ]]の仲間。\n\n* [[旧北区]]、[[エチオピア区]]に生息する。\n* [[日本]]では、[[迷鳥]]。\n\n== Sibley分類体系上の位置 ==\n<table border="0" cellspacing="0" align="centor" cellpading="2">\n<tr  bgcolor="#DDFFFF">\n<td>\n[[スズメ目 (Sibley)|スズメ目]] \n:[[スズメ亜目 (Sibley)|鳴禽亜目]] \n::[[スズメ小目 (Sibley)|スズメ小目]] \n:::[[スズメ上科 (Sibley)|スズメ上科]]  \n::::[[アトリ科 (Sibley)|アトリ科]] \n:::::[[ホオジロ亜科 (Sibley)|ホオジロ亜科]] \n::::::[[ホオジロ族 (Sibley)|ホオジロ族]] \n</td>\n</tr>\n</table>\n\n\n\n\n[[Category:ホオジロ科]]	</DESCRIPTION>
  <BODY>47119964	{{出典の明記|date=2011年11月}}\n{{生物分類表\n|名称 = ズアオホオジロ\n|画像 = [[ファイル:Ortolan.jpg|250px]]\n|画像キャプション = ズアオホオジロ\n|省略 = 鳥綱\n|目 = [[スズメ目]] {{Sname||Passerine|Passeriformes}}\n|科 = [[ホオジロ科]] {{Sname||Emberizidae}}\n|属 = [[ホオジロ属]] {{Snamei||Emberiza}}\n|種 = '''ズアオホオジロ''' {{Snamei|E. hortulana}}\n|学名 = {{Snamei||Emberiza hortulana}}\n|和名 = ズアオホオジロ\n|英名 = [[:en:Cirl Bunting|Cirl Bunting]]\n}}\n[[File:Emberiza hortulana MHNT.ZOO.2010.11.217 Neschers.jpg|thumb|'' Emberiza Hortulano'']] \n\n'''ズアオホオジロ'''（[[学名]]：{{Snamei||Emberiza hortulana}}）は、[[鳥類]]の1種。[[ホオジロ]]の仲間。\n\n* [[旧北区]]、[[エチオピア区]]に生息する。\n* [[日本]]では、[[迷鳥]]。\n\n== Sibley分類体系上の位置 ==\n<table border="0" cellspacing="0" align="centor" cellpading="2">\n<tr  bgcolor="#DDFFFF">\n<td>\n[[スズメ目 (Sibley)|スズメ目]] {{Sname||Passeriformes}}\n:[[スズメ亜目 (Sibley)|鳴禽亜目]] {{Sname||Passeri}}\n::[[スズメ小目 (Sibley)|スズメ小目]] {{Sname||Passerida}}\n:::[[スズメ上科 (Sibley)|スズメ上科]] {{Sname||Passeroidea}} \n::::[[アトリ科 (Sibley)|アトリ科]] {{Sname||Fringillidae}}\n:::::[[ホオジロ亜科 (Sibley)|ホオジロ亜科]] {{Sname||Emberizinae}}\n::::::[[ホオジロ族 (Sibley)|ホオジロ族]] {{Sname||Emberizini}}\n</td>\n</tr>\n</table>\n\n{{Bird-stub}}\n{{デフォルトソート:すあおほおしろ}}\n\n[[Category:ホオジロ科]]	</BODY>
  <MECAB>ズアオホオジロ  ''' ズアオホオジロ '''（[[ 学名 ]]：） は 、 [[ 鳥類 ]] の 1種 。 [[ ホオジロ ]] の 仲間 。 
* [[ 旧北区 ]]、[[ エチオピア区 ]] に 生息 する 。 
* [[ 日本 ]] で は 、 [[ 迷鳥 ]]。 </MECAB>
  <ID>85033</ID><LATESTID>47119964</LATESTID><NAMESPACE>0</NAMESPACE><RESTRICTIONS>move=:edit=</RESTRICTIONS><ISREDIRECT>0</ISREDIRECT><ISNEW>0</ISNEW><RANDOM>1</RANDOM><TOUCHED>0.41857697442173958</TOUCHED><LINKSUPDATED>20130402161957</LINKSUPDATED><LEN>1589</LEN><CONTENTMODEL></CONTENTMODEL><LANG></LANG></ITEM>
