<ITEM>
  <TITEL>国士舘大学</TITLE>
  <META>{{大学n| 国=日本n| 大学名=国士舘大学n| ふりがな=こくしかんだいがくn| 英称=Kokushikan Universityn| 画像=国士舘大学.JPGn| 画像説明=世田谷キャンパスn| 大学設置年=1958年n| 創立年=1917年n| 学校種別=私立n| 設置者=学校法人国士舘n| 本部所在地=[[東京都]][[世田谷区]][[世田谷 (世田谷区)|世田谷]]n| キャンパス=世田谷（東京都世田谷区）<br />町田（東京都町田市）<br />多摩（東京都多摩市）<!--太宰府は正確には大学ではなく専門学校のキャンパスなのでここでは掲載しない-->n| 学部=政経学部<br />体育学部<br />理工学部<br />法学部<br />文学部<br />21世紀アジア学部<br />経営学部n| 研究科=政治学研究科<br />経済学研究科<br />経営学研究科<br />法学研究科<br />工学研究科<br />人文科学研究科<br />スポーツ・システム研究科<br />救急システム研究科<br />総合知的財産法学研究科<br />グローバルアジア研究科n| 大学の略称=国士大n| ウェブサイト=http://www.kokushikan.ac.jp/n}}{{脚注ヘルプ}}{{Reflist}}{{commonscat|Kokushikan University}}{{Official|http://www.kokushikan.ac.jp/}}{{学校法人国士舘}}{{首都圏西部大学単位互換協定会}}{{世田谷6大学コンソーシアム}}{{全国救急救命士教育施設協議会}}{{全国私立大学FD連携フォーラム}}{{デフォルトソート:こくしかんたいかく}}</META>
  <DESCRIPTION>	{{大学\n| 国=日本\n| 大学名=国士舘大学\n| ふりがな=こくしかんだいがく\n| 英称=Kokushikan University\n| 画像=国士舘大学.JPG\n| 画像説明=世田谷キャンパス\n| 大学設置年=1958年\n| 創立年=1917年\n| 学校種別=私立\n| 設置者=学校法人国士舘\n| 本部所在地=[[東京都]][[世田谷区]][[世田谷 (世田谷区)|世田谷]]\n| キャンパス=世田谷（東京都世田谷区）<br />町田（東京都町田市）<br />多摩（東京都多摩市）<!--太宰府は正確には大学ではなく専門学校のキャンパスなのでここでは掲載しない-->\n| 学部=政経学部<br />体育学部<br />理工学部<br />法学部<br />文学部<br />21世紀アジア学部<br />経営学部\n| 研究科=政治学研究科<br />経済学研究科<br />経営学研究科<br />法学研究科<br />工学研究科<br />人文科学研究科<br />スポーツ・システム研究科<br />救急システム研究科<br />総合知的財産法学研究科<br />グローバルアジア研究科\n| 大学の略称=国士大\n| ウェブサイト=http://www.kokushikan.ac.jp/\n}}\n\n== 概観 ==\n=== 大学全体 ===\n国士舘大学は[[1917年]]に[[柴田徳次郎]]により創設された私塾である国士舘とそれに続く[[旧制中学校]]が母体となって設立された[[大学]]である。元来は青年期における人間形成を目的とした中等教育機関として発足しており、大学の設置は比較的遅い[[1958年]]である。現在、3キャンパスに7学部10研究科を有する。\n\n=== 建学の精神 ===\n==== 設立趣旨 ====\n物質文明の弊日に甚だしく、人は唯だ科學智を重んじて、徳性涵養を忘る今日に於て敎育とは唯だ科學智の賣買たるのみ此の如きは唯だ物質文明に終る、精神文明なくして國家豈に一日の安きを得んや、蓋し精神文明は物質文明を統一指導するものなり、精巧の武器、萬種羅列するも、兵士起って之運用するに非るよりは、戦場に何の効果なからん、吾人は精神文明と精神敎育とを此際に唱道して國家の柱石たる眞知識を養成せん事を期す。\n\n一國の最高學府は未た天下に公開されざるなり、若し公開されるゝとするも、ノート式の講義は單竟死學のみ、其説く處高遠深邃なるが如きも、遂に之れ形式範畴のみ、何等の情熱なく、信念なし、人を化するの力なし、形式、規則、規律、試験、之れ今日の所謂敎育なるものなり。\n\n吾人茲に於てか卓落不覊高く形式の外に立つの士に依り、膝を交へて親しく活學を講ずるの道場を開設せんと欲す、法三章、唯だ眞に師たり弟たるの情誼に依って之を維持せん事を期す、來る者は拒まず去る者は追はず、天空海濶他の覊束なく、唯だ自ら守る禮節を尚ぶのみ。\n\n而して此の道場は大自力を孕むの契機たるを期す、陋隘僅かに膝を容るるの一小寺小屋たりと雖も、大正維新の松蔭塾たる効果あらん、一心足つて萬能始めて用ゆべし、我が道場の期する處は、心學なり活學なり、信念の交感なり、理を説いて理に堕せず、術を語つて術に溺れず、舌頭萬有を吐呑して方丈裏に風雲を捲かんとするに在り。\n\n（出典.1917（大正6）年11月4日に青年大民團と国士舘の併記で配布された配布物）\n\n==== 目的 ====\n寄付行為に定められている以下の内容を建学の精神あるいは設立趣旨と誤解しているケースがあるが、これは設立趣旨ではなく、あくまで国士舘における教育指針の3大要綱「読書」「体験」「反省」と4条目「誠意」「勤労」「見識」「気魄」の訓話を学校法人至徳学園設立時に寄付行為にしたものである。大学の理念の根底とはなっているが、正確には設立趣旨ではない。\n\n聖人至徳を志し、不断の読書、体験、反省により、誠意・勤労・見識・気魄を涵養し、もって道義日本を建設し、世界の平和と進運とに貢献する有為の人材を養成する教育を行うことを目的とする。（出典.1919（大正8）年11月4日私塾国士舘入学式訓話、寄付行為自体は1952（昭和27）年10月10日に旧[[文部科学省|文部省]]によって認可され、その後改訂されていない）\n\n=== 教育および研究 ===\n体育学部を擁している高等教育機関であるため、[[警視庁]]、[[神奈川県警察|神奈川県警]]をはじめとする警察への就職は多い。また、体育学部・文学部の両学部では、それぞれの所定の[[教職課程]]を修了することにより[[養護教諭|養護教諭一種]]を取得することができるカリキュラムが用意されている<ref>[http://www.mext.go.jp/a_menu/shotou/kyoin/daigaku/04041301/007.htm 養護教諭の免許資格を取得することのできる大学,文部科学省HP]</ref><ref>[http://www.kokushikan.ac.jp/career/qualification/042700_0105.html 資格取得 教職課程,国士舘大学HP]</ref>。21世紀アジア学部においては、大学院のグローバルアジア研究科と合わせ修士課程を1年含め5年間で修了することが可能である。工学系においては、[[全日本学生フォーミュラ大会]]で好成績を収めている。また、平成27年度の[[科学研究費補助金|科研費]]採択数は40件（新規採択、継続および転入分）を数える。[[奨学金]]制度は、毎年4月ごろに各学部・各研究科で募集が行われている。[[首都圏西部大学単位互換協定会]]協定の会長校である。\n\n=== 学風および特色 ===\nスポーツ関係で活躍する在校生・出身者が多く、柔道ではオリンピック金メダリストを輩出するなどスポーツにおける著名な卒業生は層が厚い。また、サッカー部は[[日本プロサッカーリーグ|Jリーガー]]として活躍するプレイヤーを多く送り出し続ける実績は特筆できる一つである。全学部・学科において、各専攻に応じた教員免許状取得が可能な教職課程カリキュラムが設定されている<ref>[http://www.kokushikan.ac.jp/career/qualification/042700_0105.html 資格取得 教職課程,国士舘大学HP]</ref>。さらに学部によっては、在籍学科を修了することで他の資格取得や受験資格を得られる<ref>[http://www.kokushikan.ac.jp/career/qualification/042700_0106.html 資格取得 各種資格,国士舘大学HP]</ref>。大学関係者は、学生気質も以前に比べて柔らかくなり、かつての「硬派」「右より思想」というイメージは払拭されたと考え始めている<ref>[http://www.shidaikyo.or.jp/newspaper/online/2391/8_1.html 日本私立大学協会〔連載〕高めよ深めよ大学広報力〈61〉こうやって変革した58 平成22年2月 第2391号（2月17日）]</ref><ref>[http://www.amazon.co.jp/%E5%A4%A7%E5%AD%A6%E7%94%9F%E5%9B%B3%E9%91%91-2012-%E3%80%9C%E4%BA%BA%E6%B0%97%E3%82%A4%E3%83%A9%E3%82%B9%E3%83%88%E3%83%AC%E3%83%BC%E3%82%BF%E3%83%BC%E3%83%BB%E6%BC%AB%E7%94%BB%E5%AE%B6%E3%81%8C%E6%8F%8F%E3%81%8F%E6%9C%89%E5%90%8D%E5%A4%A7%E5%AD%A660%E6%A0%A1%EF%BC%81%E3%80%9C-%E6%99%8B%E9%81%8A%E8%88%8E%E3%83%A0%E3%83%83%E3%82%AF-%E5%B1%B1%E5%86%85-%E5%A4%AA%E5%9C%B0/dp/4863912528 山内太地 (監修) 『大学生図鑑2012』晋遊舎]</ref>。「うごパン」という学生向け情報誌が年5回（4・6・9・10・12月を予定）各キャンパスで配布されている。\n\n== 沿革 ==\n[[File:玄洋社跡.jpg|thumb|玄洋社跡]]\n=== 略歴 ===\n私塾国士舘は[[玄洋社]]の流れを組む[[青年大民團]]の思想を広める教育機関として設立された。 [[興亜専門学校 (旧制)|興亜専門学校]]（現在の[[亜細亜大学]]）と国士舘専門学校（旧制）における興亜科の関係は興亜専門学校の設立に興亜科の[[藤原繁]]やその他の教職員が加わっていたため、学校法人国士舘及び国士舘大学の正史には興亜科が国士舘専門学校より分離したと記述がある（設置申請者が財団法人国士舘であったが興亜科自体は独立経営であった）。ただし、興亜専門学校設置により興亜科は廃止となったのは事実である<ref>[http://www.tokyu.co.jp/kouken/k_asia.html （東急グループ）]</ref>。\n\n=== 年表 ===\n[[File:Kokushikan founding fathers.jpg|thumb|国士舘の設立を協議する有志<br />前列左から[[頭山満]]、[[野田卯太郎]]、[[渋沢栄一]]、[[徳富蘇峰]]、後列最右が創立者の[[柴田徳次郎]]。]]\n* 1917年 私塾国士舘創設\n* [[1919年]] 高等部を開設\n* 1919年 [[財団法人]]国士舘設立\n* [[1923年]] 中等部を開設\n* [[1925年]] 中等部を廃止、中学校を設置\n* [[1926年]] 商業学校を開設\n* [[1929年]] 専門学校を開設、弓道科・興亜科・国漢柔道科・剣道科を設置\n* [[1930年]] 高等拓植学校を設置、高等部を廃止\n* [[1934年]] 高等拓植学校を閉鎖\n* [[1942年]] 高等拓植学校を再設置\n* [[1941年]] 興亜科廃止\n* [[1945年]] [[第二次世界大戦]]終戦に伴い、高等拓植学校を閉鎖\n* [[1946年]] 第二次世界大戦終戦に伴い、名称を至徳学園に変更\n* [[1949年]] 商業学校を廃止\n* [[1951年]] 学校法人へ改組\n* [[1953年]] 名称を旧称である国士舘へ戻し、[[国士舘短期大学]]設置\n* [[1955年]] 至徳専門学校を閉鎖\n* [[1958年]] 国士舘大学設置、同時に体育学部（体育学科）を開設\n* [[1961年]] 政経学部（政治学科・経済学科）を開設、翌年同学部に経営学科を開設\n* [[1963年]] 工学部（機械工学科・電気工学科）を開設、翌年同学部に土木工学科、建築学科を開設\n* [[1965年]] 鶴川キャンパスを設置、同時に1・2年の授業を同キャンパスで開始、政経学部二部（政治学科・経済学科）、大学院・政治学研究科（修士課程・博士課程）、経済学研究科（修士課程・博士課程）開設\n* [[1966年]] 法学部（法律学科）、文学部（教育学科・史学地理学科・文学科）を開設\n* [[1974年]] 教養部開設\n* [[1992年]] 多摩キャンパスを開設、体育学部を同キャンパスへ移転\n* [[1994年]] 大学院・工学研究科（修士課程）を開設\n* [[1995年]] 大学院・法学研究科（修士課程）を開設\n* [[1996年]] 教養部を廃止\n* [[1997年]] 大学院・経営学研究科（修士課程）を開設\n* [[1998年]] 世田谷キャンパスに中央図書館、体育・武道館を開館\n* [[1999年]] 大学院・経営学研究科、法学研究科、工学研究科にそれぞれ博士課程を開設\n* [[2000年]] 体育学部（武道学科・スポーツ医科学科）を開設\n* [[2001年]] 法学部（現代ビジネス法学科）、大学院・スポーツ・システム研究科（修士課程）、人文科学研究科（修士課程）を開設\n* [[2002年]] 同年3月[[国士舘短期大学]]を廃止 21世紀アジア学部（21世紀アジア学科）を鶴川キャンパスに開設\n* [[2003年]] 大学院・スポーツ・システム研究科、人文科学研究科にそれぞれ博士課程を開設\n* [[2006年]] 大学院・グローバルアジア研究科（修士課程・博士課程）、総合知的財産法学研究科（修士課程）を開設、政経学部二部を廃止し政経学部へ編入\n* [[2007年]] 工学部を理工学部へ改組、創立90周年を迎える\n* [[2008年]] 鶴川キャンパスに体育学部こどもスポーツ教育学科開設、世田谷キャンパスに梅ヶ丘校舎設置 政経学部、法学部、文学部に所属する1･2年生を世田谷キャンパスへ移転\n* [[2009年]] 鶴川キャンパスの名称を、町田キャンパスに変更\n* [[2010年]] 大学院・救急システム研究科（修士課程）を開設\n* [[2011年]] 政経学部「経営学科」を分離独立させ、経営学部（経営学科）を開設\n* [[2013年]] 大学院・救急システム研究科（博士課程）を開設\n* 2013年 大学院・法学研究科に３コース制（基幹法コース・税法・ビジネスコース・スポーツ法コース）を導入。\n* 2013年 旧第二体育館跡地に複合施設・メイプルセンチュリーホール竣工\n* [[2017年]] 創立100周年を迎える\n\n== 基礎データ ==\n=== 所在地 ===\n<!--太宰府は正確には大学ではなく専門学校のキャンパスなのでここでは掲載しない-->\n[[ファイル:Kokushikanuniv.jpg|thumb|220px|町田キャンパス]]\n[[ファイル:kokushikantama.jpg|thumb|220px|多摩キャンパス]]\n* 世田谷キャンパス（[[世田谷区]][[世田谷 (世田谷区)|世田谷]]）\n** 世田谷校舎\n** 梅ヶ丘校舎（34号館）(世田谷区梅丘）\n*** 政経学部\n*** 理工学部\n*** 法学部\n*** 文学部\n*** 経営学部\n* 町田キャンパス（[[町田市]][[広袴 (町田市)|広袴]]）\n** 21世紀アジア学部\n** 体育学部 こどもスポーツ教育学科\n* 多摩キャンパス（[[多摩市]][[永山 (多摩市)|永山]]）\n** 体育学部 体育学科・武道学科・スポーツ医科学科\n\n===象徴===\n\n*校章は[[楓]]をイメージしている（中高に若干のデザインの違いがある）。\n*大学歌はない。しかし、学校法人国士舘が設置している学校で統一的に舘歌として歌われている。（中高においては歌詞が“皇國”が“御國”、“殉す”が“ゆるす”となっている）\n**作詞柴田徳次郎、作曲[[東儀鉄笛]]、編曲[[石川太郎]]\n*シンボルマークはアルファベットのKをデザインである。\n*スクールカラーは特に決まってはいないが、近年はシンボルマークのKの色を、深紅の楓の色をオリジナルの国士舘レッドとして使用している。\n\n== 教育および研究 ==\n=== 組織 ===\n==== 学部 ====\n* [[政治経済学部|政経学部]]\n** [[政治学科]]\n** [[経済学科]]\n** 経営学科（平成23年度入学以前の学生に適用）\n* [[体育学部]]\n** [[体育学科]]\n** [[武道学科]]\n** [[スポーツ医科学科]]\n** [[こどもスポーツ教育学科]]\n* [[理工学部]]\n** [[理工学科]]\n*** [[機械工学科|機械工学系]]\n*** [[電子情報学系]]\n*** [[建築学科|建築学系]]\n*** [[ランドスケープ学科|都市ランドスケープ学系]]\n*** [[医用生体工学|健康医工学系]]\n*** [[理学科|基礎理学系]]\n* [[法学部]]\n** [[法学部#法学部を持つ日本の大学|法律学科]]\n** [[現代]]ビジネス法学科\n* [[文学部]]\n** [[教育学科]]\n*** [[教育学|教育学専攻]]\n*** [[倫理学|倫理学専攻]]\n*** [[初等教育|初等教育専攻]]\n** [[史学・地理学科]]\n*** [[考古学|考古]]・[[日本史]]学専攻\n*** [[東洋史|東洋史学専攻]]\n*** [[地理]]・[[環境]]専攻\n** [[文学科]]\n*** [[中国語]]・[[中国文学]]専攻\n*** [[日本文学]]・文化専攻\n* [[21世紀アジア学部]]\n** 21世紀アジア学科\n*** アジア[[ビジネス]]コース\n*** 21世紀日本[[理解]]コース\n*** [[アジア|アジア地域]]デザインコース\n* [[経営学部]]\n** [[経営学科]]\n\n==== 大学院 ====\n* [[政治学研究科]]\n** 政治学専攻（修士課程・博士課程）\n* [[経済学研究科]]\n** 経済学専攻（修士課程・博士課程）\n* [[経営学研究科]]\n** 経営学専攻（修士課程・博士課程）\n* [[法学研究科]]\n** [[法学]]専攻（修士課程・博士課程）\n*** 基幹法コース\n*** 税法・ビジネスコース\n*** スポーツ法コース\n* [[総合知的財産法学研究科]]\n** [[知的財産権|総合知的財産法学専攻]]（修士課程）\n* [[工学研究科]]\n** 機械工学専攻（修士課程）\n** 電気工学専攻（修士課程）\n** 建設工学専攻（修士課程）\n** 応用システム工学専攻（博士課程）\n* [[人文科学研究科]]\n** 人文科学専攻（修士課程・博士課程）\n** 教育学専攻（修士課程・博士課程）\n* [[スポーツ・システム研究科]]\n** スポーツ・システム専攻（修士課程）\n*** スポーツ教育コース\n*** スポーツ科学コース\n** スポーツ・システム専攻（博士課程）\n*** スポーツ教育コース\n*** スポーツ科学コース\n* [[救急システム研究科]]\n** 救急システム専攻（修士課程）\n*** 救急救命システム専攻\n*** 救急救命システム専攻（1年コース）\n** 救急救命システム専攻（博士課程）\n*** [[救急医療|救急医療体制]]・政策分野　\n*** 病院前救急症候・鑑別診断分野\n*** [[災害医療]]・防災・災害危機管理マネージメント分野\n* [[グローバルアジア研究科]]\n** グローバルアジア専攻（修士課程）\n** グローバルアジア研究専攻（博士課程）\n\n==== 附属機関 ====\n* [[情報科学]]センター\n* イラク古代文化研究所\n* [[武道]]・[[徳育]]研究所\n* アジア・日本研究センター\n* [[生涯学習]]センター\n* [[ウエルネス]]・リサーチセンター\n* 理工学研究所（理工学部内研究所）\n* 政治研究所（政経部内研究所）\n* 経済研究所（政経部内研究所）\n* 経営研究所（政経部内研究所）\n* 比較法制研究所（法学部内研究所）\n* 最先端技術関連法研究所（法学部内研究所）\n* 体育研究所（体育学部内研究所）\n\n* [[サテライトキャンパス]]\n** キルギスキャンパス（[[ビシュケク人文大学]]内）\n\n;海外拠点\n* 国士舘大学大連事務所（中国・[[遼寧省]]・[[大連市]]）\n\n=== 教育 ===\n====採択されているプログラム====\n*専門職大学院等における[[高度専門職業人]]養成教育推進プログラム\n**海外経営専門職人財養成プログラム（[[早稲田大学]]（幹事校）・国士舘大学・[[武蔵野大学]]・[[明治大学]]・[[立教大学]]）<ref>[http://www.mext.go.jp/b_menu/houdou/20/07/08072909/001/001.htm 平成20年度「専門職大学院等における高度専門職業人養成教育推進プログラム」選定取組一覧]</ref>\n\n== 学生生活 ==\n=== 学園祭 ===\n国士舘大学ではキャンパスごとに学園祭が独立開催されている。\n\n*世田谷キャンパス\n**楓門祭（ふうもんさい）\n**11月2日、3日\n::芸能人のコンサートやミスコンテストが開催されている。なお、国士舘大学では、ミスコンテストの優勝者を『ミス国士舘』ではなく学章の楓にちなんで『メイプルクイーン』と呼ぶ。\n::近年はコンサートよりお笑い芸人のステージが多い。\n::昭和42年に創立50周年を記念して明治祭として開催され、昭和52年より楓門祭となる。\n::開催名は他祭と違い、第○○周年楓門祭\n\n*町田キャンパス\n**鶴川祭（つるかわさい）\n**5月下旬の土曜日、日曜日\n::新入生歓迎の運動会が始まりであったため、現在においてもスポーツ大会が多く開催されている。また、ちびっ子剣道大会、ちびっ子空手大会などの近隣参加企画も準備されている。かつてはバスケットボール、バレーボール、ソフトボール、モンゴル相撲等の大会があった。\n::第1回旧鶴川祭は昭和44年に明治祭に併設され開催。現在の鶴川祭は、昭和60年より開催。\n**アジアンフェスタ\n::21世紀アジア学部が設置される1年前より開催され、設置後は21世紀アジア学部の学生のみで組織され実施されている。第1回は21世紀アジア学部設置の1年前、平成13年度に開催。平成20年度より鶴川祭を継承する。\n\n*多摩キャンパス\n**多摩祭（たまさい）\n**11月第3土曜日、日曜日\n::体育会を中心としたスポーツの祭典である。柔道部や相撲部の学生が出場するカラオケや各競技のユニフォームで参加する部対抗駅伝が開催されている。また、近隣住民も対象としたビンゴ大会をメイン企画として運営しており、多くの家族連れが集まる。\n::平成7年に多摩カップとして開催され、平成8年より開催。\n\n=== スポーツ ===\n*学生スポーツは活発に行われている。全国大会で複数回の優勝を経験している[[国士舘大学サッカー部|サッカー部]]などはマスメディアで取り上げられる機会も多い。\n*[[国士舘大学硬式野球部|硬式野球部]]は[[東都大学野球連盟]]に加盟している。\n*ハンドボール部も長年関東学生ハンドボール連盟1部リーグを維持し、日本代表選手を輩出している。\n*バスケットボール部の愛称は「[[国士舘大学バイキングス|バイキングス]]」。2008年の[[全日本大学バスケットボール選手権大会]]で準優勝に輝いた。\n*[[国士舘大学ラグビー部|ラグビー部]]は1978年の[[関東大学ラグビーリーグ戦グループ]]で優勝を果たした。\n\n=== 学内奨学金 ===\n*入学試験に係わる学内奨学金\n**成績優秀奨学生制度\n\n*学業優秀奨学生\n*運動技能優秀奨学生\n*修学援助奨学生\n**奨学生A：納入金の全額免除\n**奨学生B：入学金を除く納入金の免除\n**奨学生C：授業料の免除\n**奨学生D：授業料の5割免除\n\n*塩沢奨学金（理工学部）\n*田中奨学金（理工学部）\n*中村宗雄奨学基金（法学部）\n*公益信託 橘高倫一記念奨学基金（文学部在籍・千葉県内高校卒業者限定）\n*外国人留学生奨学金\n\n*国際交流センター\n**国士舘大学外国人留学生奨学生\n*交換留学生対象\n**国士舘大学留学奨励金\n\n*国士舘大学同窓会奨学融資（長期・短期）\n\n== 大学関係者と組織 ==\n=== 大学関係者一覧 ===\n*[[国士舘大学の人物一覧]]\n\n== 施設 ==\n=== キャンパス ===\n[[ファイル:koutsuannai3.jpg|thumb|190px|交通]]\nすべてのキャンパスが[[小田急電鉄#路線|小田急線]]で結ばれている。\n*世田谷キャンパス（[[世田谷区]][[世田谷 (世田谷区)|世田谷]]）\n*:[[小田急小田原線]][[梅ヶ丘駅]]\n*:[[東急世田谷線]][[松陰神社前駅]]\n*町田キャンパス（[[町田市]]広袴）\n*:[[小田急小田原線]][[鶴川駅]]下車\n*:国士舘大学スクールバス乗車10分(駅前からキャンパス内まで)。\n*:[[小田急バス]]「鶴11」「鶴13」系統乗車およそ15分。　国士舘大学前下車徒歩1分。\n*:[[神奈川中央交通]]「鶴12」系統乗車およそ15分。　国士舘大学前下車徒歩1分。\n*:[[京王相模原線]][[若葉台駅]]下車\n*:[[神奈川中央交通]]バス「鶴21」系統乗車およそ15分。　[[和光学園]]下車徒歩5分。\n*:[[東急こどもの国線]][[こどもの国駅 (神奈川県)|こどもの国駅]]～小田急バス（鶴川駅下車乗り換え）\n*多摩キャンパス（[[多摩市]]永山7丁目3-1）\n*:[[小田急多摩線]][[永山駅 (東京都)|小田急永山駅]]下車\n*:京王相模原線[[永山駅 (東京都)|京王永山駅]]下車\n*:国士舘大学スクールバス乗車7分(駅前ロータリーからキャンパス前まで)。\n*:[[京王バス]][[神奈川中央交通]]バス「永13」「永14」「桜23」「桜24」「鶴31」のいずれか乗車7分。永山高校前下車徒歩10分。\n\n=== 学生食堂 ===\n<div style="float:left; margin-right: 2em;">\n*世田谷キャンパス\n**世田谷校舎\n*:ニコラス精養堂\n*:アンブラン\n*:[[モスフードサービス]]\n*:[[スエヒロレストラン]]\n**梅ヶ丘校舎\n*:[[エームサービス]]\n</div>\n<div style="float:left; margin-right: 2em;">\n*町田キャンパス\n*:ニコラス精養堂\n*:アンブラン\n*多摩キャンパス\n*:新東京食堂\n</div>\n<br style="clear: both;" />\n\n=== 学生寮 ===\n全寮制として設置された学校の名残として、現在も下記の寮が開設されている。\n*世田谷キャンパス\n**世田谷寮（昭和43年竣工）\n*:松陰寮（一般男子学生のみ）\n*:ゲストハウス（留学生のみ）\n*町田キャンパス\n**鶴川寮（昭和42年竣工）\n*:望嶽寮（一般男子学生と硬式野球部／サッカー部のみ）\n*:すみれ寮（一般女子学生のみ）（昭和45年設置）\n過去に存在した寮\n<div style="float:left; margin-right: 2em;">\n*男子寮\n**回天寮\n**正気寮\n**時習寮\n**青雲寮\n**富士見寮\n**錦楓寮\n</div>\n<div style="float:left; margin-right: 2em;">\n*女子寮\n**常盤寮\n**松柏寮\n**清節寮\n**菊寮\n</div>\n<br style="clear: both;" />\n\n== 対外関係 ==\n* [[2005年]]に[[山形県]][[鮭川村]]と理工学部付属理工学研究所が「学術友好交流協定」を締結。\n* [[2006年]]11月に[[東京都]][[町田市]]と「町田市学長懇談会包括連携協定」を締結。\n* [[2008年]]3月に[[世田谷区]]と「災害時協力協定」を締結。\n* [[2014年]]6月に[[東京オリンピック・パラリンピック競技大会組織委員会|公益財団法人東京オリンピック・パラリンピック競技大会組織委員会]]と2020年「東京オリンピック・パラリンピック競技大会に係る大学連携協定」を締結。<ref>[https://tokyo2020.jp/jp/news/index.php?mode=page&id=1122 2014年06月23日 大学連携協定締結式・記念シンポジウム開催]</ref>\n* 2014年12月に[[新潟県庁|新潟県]]と「学生Ｕ･Ｉターン就職促進に関する協定」を締結。\n* [[2015年]]3月に[[日本赤十字社]]と「社会の安心・安全及び福祉の向上に関するパートナーシップ協定」を締結。\n\n=== 他大学との協定 ===\n* [[首都圏西部大学単位互換協定会]]\n* [[世田谷6大学コンソーシアム]]\n* [[全国私立大学FD連携フォーラム]]\n\n; 大学院単位互換交流協定（人文科学研究科 人文科学専攻）\n* [[史学]]分野の単位互換協定・協定校'''\n** [[青山学院大学|青山学院大学大学院]] [[文学研究科]]史学専攻\n** [[國學院大學|國學院大學大学院]] 文学研究科日本史学専攻\n** [[駒澤大学|駒澤大学大学院]] [[人文科学研究科]]歴史学専攻\n** [[専修大学|専修大学大学院]] 文学研究科史学専攻\n** [[上智大学|上智大学大学院]] 文学研究科史学専攻\n** [[中央大学|中央大学大学院]] 文学研究科国史学専攻・東洋史学専攻・西洋史学専攻\n** [[東海大学|東海大学大学院]] 文学研究科史学専攻\n** [[東洋大学|東洋大学大学院]] 文学研究科史学専攻\n** [[明治大学|明治大学大学院]] 文学研究科史学専攻\n** [[立教大学|立教大学大学院]] 文学研究科史学専攻\n** 国士舘大学大学院 人文科学研究科人文科学専攻\n\n* [[地理学]]分野の単位互換協定・協定校\n** 駒澤大学大学院 人文科学研究科地理学専攻\n** 専修大学大学院 文学研究科地理学専攻\n** [[日本大学|日本大学大学院]] [[理工学研究科]]地理学専攻\n** [[法政大学|法政大学大学院]] 人文科学研究科地理学専攻\n** 明治大学大学院 文学研究科地理学専攻\n** 国士舘大学大学院 人文科学研究科人文科学専攻\n\n* [[考古学]]分野の単位互換協定・協定校\n** 駒澤大学大学院 人文科学研究科歴史学専攻\n** [[昭和女子大学|昭和女子大学大学院]] [[生活機構研究科]]生活文化研究専攻\n** 国士舘大学大学院 人文科学研究科人文科学専攻\n\n===協定校===\n* [[サンフランシスコ州立大学]](アメリカ・[[サンフランシスコ]])\n* [[サイモンフレーザー大学]]([[カナダ]]・[[BC州]])\n* [[カレッジ・オブ・ザ・ロッキーズ]](カナダ・ブリティッシュコロンビア州)\n* [[グリフィス大学]]([[オーストラリア]]・[[クイーンズランド州]])\n* [[漢陽大学校]]([[韓国]]・[[ソウル特別市]])\n* [[高麗大学校]](韓国・ソウル特別市)\n* [[東義大学校]](韓国・[[釜山広域市]])\n* [[安東大学校]](韓国・[[慶尚北道]][[安東市]])\n* [[北京師範大学]]([[中国]]・[[北京市]])\n* [[上海対外貿易学院]](中国・[[上海市]])\n* [[黒龍江大学]]([[中国]]・[[黒竜江省]])\n* [[山西大学]](中国・[[山西省]]・[[太原市]])\n* [[蘇州大学]](中国・[[江蘇省]]・[[蘇州市]]）\n* [[武漢大学]](中国・[[湖北省]]・[[武漢市]]）\n* [[深圳職業技術学院]](中国・[[広東省]])\n* [[青島大学]](中国・[[山東省]]・[[青島市]])\n* [[中国文化大学]]([[台湾]]・[[台北市]])\n* [[国立中山大学]](台湾・[[高雄市]])\n* [[キルギス国立大学]]([[キルギス共和国]])\n* [[ビシュケク人文大学]](キルギス共和国)\n* [[モンゴル国立大学]]([[モンゴル]])\n* [[デ・ラ・サール大学]]([[フィリピン]]・[[マニラ]])\n* [[チュラーロンコーン大学]]([[タイ王国]]・[[バンコク]])\n* [[チエンマイ大学]](タイ王国・[[チエンマイ県]])\n* [[ベトナム国家大学ホーチミン市校|ベトナム国家社会人文科学大学]]([[ベトナム]]・[[ホーチミン市]])\n* [[ヤンゴン大学]]([[ミャンマー]]・[[ヤンゴン]])\n* [[ガジャマダ大学]]([[インドネシア]]・[[ジョグジャカルタ特別州]])\n* [[セブラスマル大学]](インドネシア)\n* [[国立サマルカンド外国語大学]]([[ウズベキスタン]])\n* [[世界経済外交大学]](ウズベキスタン)\n* [[ポーツマス大学]]([[イギリス]]・[[ポーツマス (イングランド)|ポーツマス]])\n* [[ミュンヘン大学]]([[ドイツ]]・[[バイエルン州]]・[[ミュンヘン]])\n* [[センメルヴェイス大学]]([[ハンガリー]]・[[ブダペスト]])\n* [[ルレオ工科大学]]([[スウェーデン]]・[[ノールボッテン県]]・[[ルレオ]])\n* [[極東国立工科大学]]([[ロシア]]・[[ウラジオストック]])\n* [[ヴェリコ・タルノヴォ大学]]([[ブルガリア]]・[[ヴェリコ・タルノヴォ州]]・[[ヴェリコ・タルノヴォ]])\n* [[ユズンチュ・ユル大学]]([[トルコ]]・[[ヴァン県]]・[[ヴァン]])\n* [[ハジェットテッペ大学]](トルコ・[[アンカラ県]]・[[アンカラ]])\n* [[ヤルムーク大学]]([[ヨルダン]]・[[イルビド県]])\n* [[アディスアベバ大学]]([[エチオピア]]・[[アディスアベバ]])\n\n=== 系列校 ===\nいわゆる大学を頂点とする「[[附属学校]]」ではなく、同一学校法人が運営する独立した学校の集合体という形態を取っている。\n*[[国士舘中学校・高等学校]]（世田谷区）\n*過去に存在した系列校。\n**[[国士舘短期大学]]（[[町田市]]広袴）\n**[[国士舘大学福祉専門学校]]（[[太宰府市]]御笠）\n\n== 脚注 ==\n\n\n\n== 外部リンク ==\n\n*\n\n\n\n\n\n\n\n\n[[Category:国士舘大学|*]]\n[[Category:学校記事]]	</DESCRIPTION>
  <BODY>58613573	{{大学\n| 国=日本\n| 大学名=国士舘大学\n| ふりがな=こくしかんだいがく\n| 英称=Kokushikan University\n| 画像=国士舘大学.JPG\n| 画像説明=世田谷キャンパス\n| 大学設置年=1958年\n| 創立年=1917年\n| 学校種別=私立\n| 設置者=学校法人国士舘\n| 本部所在地=[[東京都]][[世田谷区]][[世田谷 (世田谷区)|世田谷]]\n| キャンパス=世田谷（東京都世田谷区）<br />町田（東京都町田市）<br />多摩（東京都多摩市）<!--太宰府は正確には大学ではなく専門学校のキャンパスなのでここでは掲載しない-->\n| 学部=政経学部<br />体育学部<br />理工学部<br />法学部<br />文学部<br />21世紀アジア学部<br />経営学部\n| 研究科=政治学研究科<br />経済学研究科<br />経営学研究科<br />法学研究科<br />工学研究科<br />人文科学研究科<br />スポーツ・システム研究科<br />救急システム研究科<br />総合知的財産法学研究科<br />グローバルアジア研究科\n| 大学の略称=国士大\n| ウェブサイト=http://www.kokushikan.ac.jp/\n}}\n\n== 概観 ==\n=== 大学全体 ===\n国士舘大学は[[1917年]]に[[柴田徳次郎]]により創設された私塾である国士舘とそれに続く[[旧制中学校]]が母体となって設立された[[大学]]である。元来は青年期における人間形成を目的とした中等教育機関として発足しており、大学の設置は比較的遅い[[1958年]]である。現在、3キャンパスに7学部10研究科を有する。\n\n=== 建学の精神 ===\n==== 設立趣旨 ====\n物質文明の弊日に甚だしく、人は唯だ科學智を重んじて、徳性涵養を忘る今日に於て敎育とは唯だ科學智の賣買たるのみ此の如きは唯だ物質文明に終る、精神文明なくして國家豈に一日の安きを得んや、蓋し精神文明は物質文明を統一指導するものなり、精巧の武器、萬種羅列するも、兵士起って之運用するに非るよりは、戦場に何の効果なからん、吾人は精神文明と精神敎育とを此際に唱道して國家の柱石たる眞知識を養成せん事を期す。\n\n一國の最高學府は未た天下に公開されざるなり、若し公開されるゝとするも、ノート式の講義は單竟死學のみ、其説く處高遠深邃なるが如きも、遂に之れ形式範畴のみ、何等の情熱なく、信念なし、人を化するの力なし、形式、規則、規律、試験、之れ今日の所謂敎育なるものなり。\n\n吾人茲に於てか卓落不覊高く形式の外に立つの士に依り、膝を交へて親しく活學を講ずるの道場を開設せんと欲す、法三章、唯だ眞に師たり弟たるの情誼に依って之を維持せん事を期す、來る者は拒まず去る者は追はず、天空海濶他の覊束なく、唯だ自ら守る禮節を尚ぶのみ。\n\n而して此の道場は大自力を孕むの契機たるを期す、陋隘僅かに膝を容るるの一小寺小屋たりと雖も、大正維新の松蔭塾たる効果あらん、一心足つて萬能始めて用ゆべし、我が道場の期する處は、心學なり活學なり、信念の交感なり、理を説いて理に堕せず、術を語つて術に溺れず、舌頭萬有を吐呑して方丈裏に風雲を捲かんとするに在り。\n\n（出典.1917（大正6）年11月4日に青年大民團と国士舘の併記で配布された配布物）\n\n==== 目的 ====\n寄付行為に定められている以下の内容を建学の精神あるいは設立趣旨と誤解しているケースがあるが、これは設立趣旨ではなく、あくまで国士舘における教育指針の3大要綱「読書」「体験」「反省」と4条目「誠意」「勤労」「見識」「気魄」の訓話を学校法人至徳学園設立時に寄付行為にしたものである。大学の理念の根底とはなっているが、正確には設立趣旨ではない。\n\n聖人至徳を志し、不断の読書、体験、反省により、誠意・勤労・見識・気魄を涵養し、もって道義日本を建設し、世界の平和と進運とに貢献する有為の人材を養成する教育を行うことを目的とする。（出典.1919（大正8）年11月4日私塾国士舘入学式訓話、寄付行為自体は1952（昭和27）年10月10日に旧[[文部科学省|文部省]]によって認可され、その後改訂されていない）\n\n=== 教育および研究 ===\n体育学部を擁している高等教育機関であるため、[[警視庁]]、[[神奈川県警察|神奈川県警]]をはじめとする警察への就職は多い。また、体育学部・文学部の両学部では、それぞれの所定の[[教職課程]]を修了することにより[[養護教諭|養護教諭一種]]を取得することができるカリキュラムが用意されている<ref>[http://www.mext.go.jp/a_menu/shotou/kyoin/daigaku/04041301/007.htm 養護教諭の免許資格を取得することのできる大学,文部科学省HP]</ref><ref>[http://www.kokushikan.ac.jp/career/qualification/042700_0105.html 資格取得 教職課程,国士舘大学HP]</ref>。21世紀アジア学部においては、大学院のグローバルアジア研究科と合わせ修士課程を1年含め5年間で修了することが可能である。工学系においては、[[全日本学生フォーミュラ大会]]で好成績を収めている。また、平成27年度の[[科学研究費補助金|科研費]]採択数は40件（新規採択、継続および転入分）を数える。[[奨学金]]制度は、毎年4月ごろに各学部・各研究科で募集が行われている。[[首都圏西部大学単位互換協定会]]協定の会長校である。\n\n=== 学風および特色 ===\nスポーツ関係で活躍する在校生・出身者が多く、柔道ではオリンピック金メダリストを輩出するなどスポーツにおける著名な卒業生は層が厚い。また、サッカー部は[[日本プロサッカーリーグ|Jリーガー]]として活躍するプレイヤーを多く送り出し続ける実績は特筆できる一つである。全学部・学科において、各専攻に応じた教員免許状取得が可能な教職課程カリキュラムが設定されている<ref>[http://www.kokushikan.ac.jp/career/qualification/042700_0105.html 資格取得 教職課程,国士舘大学HP]</ref>。さらに学部によっては、在籍学科を修了することで他の資格取得や受験資格を得られる<ref>[http://www.kokushikan.ac.jp/career/qualification/042700_0106.html 資格取得 各種資格,国士舘大学HP]</ref>。大学関係者は、学生気質も以前に比べて柔らかくなり、かつての「硬派」「右より思想」というイメージは払拭されたと考え始めている<ref>[http://www.shidaikyo.or.jp/newspaper/online/2391/8_1.html 日本私立大学協会〔連載〕高めよ深めよ大学広報力〈61〉こうやって変革した58 平成22年2月 第2391号（2月17日）]</ref><ref>[http://www.amazon.co.jp/%E5%A4%A7%E5%AD%A6%E7%94%9F%E5%9B%B3%E9%91%91-2012-%E3%80%9C%E4%BA%BA%E6%B0%97%E3%82%A4%E3%83%A9%E3%82%B9%E3%83%88%E3%83%AC%E3%83%BC%E3%82%BF%E3%83%BC%E3%83%BB%E6%BC%AB%E7%94%BB%E5%AE%B6%E3%81%8C%E6%8F%8F%E3%81%8F%E6%9C%89%E5%90%8D%E5%A4%A7%E5%AD%A660%E6%A0%A1%EF%BC%81%E3%80%9C-%E6%99%8B%E9%81%8A%E8%88%8E%E3%83%A0%E3%83%83%E3%82%AF-%E5%B1%B1%E5%86%85-%E5%A4%AA%E5%9C%B0/dp/4863912528 山内太地 (監修) 『大学生図鑑2012』晋遊舎]</ref>。「うごパン」という学生向け情報誌が年5回（4・6・9・10・12月を予定）各キャンパスで配布されている。\n\n== 沿革 ==\n[[File:玄洋社跡.jpg|thumb|玄洋社跡]]\n=== 略歴 ===\n私塾国士舘は[[玄洋社]]の流れを組む[[青年大民團]]の思想を広める教育機関として設立された。 [[興亜専門学校 (旧制)|興亜専門学校]]（現在の[[亜細亜大学]]）と国士舘専門学校（旧制）における興亜科の関係は興亜専門学校の設立に興亜科の[[藤原繁]]やその他の教職員が加わっていたため、学校法人国士舘及び国士舘大学の正史には興亜科が国士舘専門学校より分離したと記述がある（設置申請者が財団法人国士舘であったが興亜科自体は独立経営であった）。ただし、興亜専門学校設置により興亜科は廃止となったのは事実である<ref>[http://www.tokyu.co.jp/kouken/k_asia.html （東急グループ）]</ref>。\n\n=== 年表 ===\n[[File:Kokushikan founding fathers.jpg|thumb|国士舘の設立を協議する有志<br />前列左から[[頭山満]]、[[野田卯太郎]]、[[渋沢栄一]]、[[徳富蘇峰]]、後列最右が創立者の[[柴田徳次郎]]。]]\n* 1917年 私塾国士舘創設\n* [[1919年]] 高等部を開設\n* 1919年 [[財団法人]]国士舘設立\n* [[1923年]] 中等部を開設\n* [[1925年]] 中等部を廃止、中学校を設置\n* [[1926年]] 商業学校を開設\n* [[1929年]] 専門学校を開設、弓道科・興亜科・国漢柔道科・剣道科を設置\n* [[1930年]] 高等拓植学校を設置、高等部を廃止\n* [[1934年]] 高等拓植学校を閉鎖\n* [[1942年]] 高等拓植学校を再設置\n* [[1941年]] 興亜科廃止\n* [[1945年]] [[第二次世界大戦]]終戦に伴い、高等拓植学校を閉鎖\n* [[1946年]] 第二次世界大戦終戦に伴い、名称を至徳学園に変更\n* [[1949年]] 商業学校を廃止\n* [[1951年]] 学校法人へ改組\n* [[1953年]] 名称を旧称である国士舘へ戻し、[[国士舘短期大学]]設置\n* [[1955年]] 至徳専門学校を閉鎖\n* [[1958年]] 国士舘大学設置、同時に体育学部（体育学科）を開設\n* [[1961年]] 政経学部（政治学科・経済学科）を開設、翌年同学部に経営学科を開設\n* [[1963年]] 工学部（機械工学科・電気工学科）を開設、翌年同学部に土木工学科、建築学科を開設\n* [[1965年]] 鶴川キャンパスを設置、同時に1・2年の授業を同キャンパスで開始、政経学部二部（政治学科・経済学科）、大学院・政治学研究科（修士課程・博士課程）、経済学研究科（修士課程・博士課程）開設\n* [[1966年]] 法学部（法律学科）、文学部（教育学科・史学地理学科・文学科）を開設\n* [[1974年]] 教養部開設\n* [[1992年]] 多摩キャンパスを開設、体育学部を同キャンパスへ移転\n* [[1994年]] 大学院・工学研究科（修士課程）を開設\n* [[1995年]] 大学院・法学研究科（修士課程）を開設\n* [[1996年]] 教養部を廃止\n* [[1997年]] 大学院・経営学研究科（修士課程）を開設\n* [[1998年]] 世田谷キャンパスに中央図書館、体育・武道館を開館\n* [[1999年]] 大学院・経営学研究科、法学研究科、工学研究科にそれぞれ博士課程を開設\n* [[2000年]] 体育学部（武道学科・スポーツ医科学科）を開設\n* [[2001年]] 法学部（現代ビジネス法学科）、大学院・スポーツ・システム研究科（修士課程）、人文科学研究科（修士課程）を開設\n* [[2002年]] 同年3月[[国士舘短期大学]]を廃止 21世紀アジア学部（21世紀アジア学科）を鶴川キャンパスに開設\n* [[2003年]] 大学院・スポーツ・システム研究科、人文科学研究科にそれぞれ博士課程を開設\n* [[2006年]] 大学院・グローバルアジア研究科（修士課程・博士課程）、総合知的財産法学研究科（修士課程）を開設、政経学部二部を廃止し政経学部へ編入\n* [[2007年]] 工学部を理工学部へ改組、創立90周年を迎える\n* [[2008年]] 鶴川キャンパスに体育学部こどもスポーツ教育学科開設、世田谷キャンパスに梅ヶ丘校舎設置 政経学部、法学部、文学部に所属する1･2年生を世田谷キャンパスへ移転\n* [[2009年]] 鶴川キャンパスの名称を、町田キャンパスに変更\n* [[2010年]] 大学院・救急システム研究科（修士課程）を開設\n* [[2011年]] 政経学部「経営学科」を分離独立させ、経営学部（経営学科）を開設\n* [[2013年]] 大学院・救急システム研究科（博士課程）を開設\n* 2013年 大学院・法学研究科に３コース制（基幹法コース・税法・ビジネスコース・スポーツ法コース）を導入。\n* 2013年 旧第二体育館跡地に複合施設・メイプルセンチュリーホール竣工\n* [[2017年]] 創立100周年を迎える\n\n== 基礎データ ==\n=== 所在地 ===\n<!--太宰府は正確には大学ではなく専門学校のキャンパスなのでここでは掲載しない-->\n[[ファイル:Kokushikanuniv.jpg|thumb|220px|町田キャンパス]]\n[[ファイル:kokushikantama.jpg|thumb|220px|多摩キャンパス]]\n* 世田谷キャンパス（[[世田谷区]][[世田谷 (世田谷区)|世田谷]]）\n** 世田谷校舎\n** 梅ヶ丘校舎（34号館）(世田谷区梅丘）\n*** 政経学部\n*** 理工学部\n*** 法学部\n*** 文学部\n*** 経営学部\n* 町田キャンパス（[[町田市]][[広袴 (町田市)|広袴]]）\n** 21世紀アジア学部\n** 体育学部 こどもスポーツ教育学科\n* 多摩キャンパス（[[多摩市]][[永山 (多摩市)|永山]]）\n** 体育学部 体育学科・武道学科・スポーツ医科学科\n\n===象徴===\n\n*校章は[[楓]]をイメージしている（中高に若干のデザインの違いがある）。\n*大学歌はない。しかし、学校法人国士舘が設置している学校で統一的に舘歌として歌われている。（中高においては歌詞が“皇國”が“御國”、“殉す”が“ゆるす”となっている）\n**作詞柴田徳次郎、作曲[[東儀鉄笛]]、編曲[[石川太郎]]\n*シンボルマークはアルファベットのKをデザインである。\n*スクールカラーは特に決まってはいないが、近年はシンボルマークのKの色を、深紅の楓の色をオリジナルの国士舘レッドとして使用している。\n\n== 教育および研究 ==\n=== 組織 ===\n==== 学部 ====\n* [[政治経済学部|政経学部]]\n** [[政治学科]]\n** [[経済学科]]\n** 経営学科（平成23年度入学以前の学生に適用）\n* [[体育学部]]\n** [[体育学科]]\n** [[武道学科]]\n** [[スポーツ医科学科]]\n** [[こどもスポーツ教育学科]]\n* [[理工学部]]\n** [[理工学科]]\n*** [[機械工学科|機械工学系]]\n*** [[電子情報学系]]\n*** [[建築学科|建築学系]]\n*** [[ランドスケープ学科|都市ランドスケープ学系]]\n*** [[医用生体工学|健康医工学系]]\n*** [[理学科|基礎理学系]]\n* [[法学部]]\n** [[法学部#法学部を持つ日本の大学|法律学科]]\n** [[現代]]ビジネス法学科\n* [[文学部]]\n** [[教育学科]]\n*** [[教育学|教育学専攻]]\n*** [[倫理学|倫理学専攻]]\n*** [[初等教育|初等教育専攻]]\n** [[史学・地理学科]]\n*** [[考古学|考古]]・[[日本史]]学専攻\n*** [[東洋史|東洋史学専攻]]\n*** [[地理]]・[[環境]]専攻\n** [[文学科]]\n*** [[中国語]]・[[中国文学]]専攻\n*** [[日本文学]]・文化専攻\n* [[21世紀アジア学部]]\n** 21世紀アジア学科\n*** アジア[[ビジネス]]コース\n*** 21世紀日本[[理解]]コース\n*** [[アジア|アジア地域]]デザインコース\n* [[経営学部]]\n** [[経営学科]]\n\n==== 大学院 ====\n* [[政治学研究科]]\n** 政治学専攻（修士課程・博士課程）\n* [[経済学研究科]]\n** 経済学専攻（修士課程・博士課程）\n* [[経営学研究科]]\n** 経営学専攻（修士課程・博士課程）\n* [[法学研究科]]\n** [[法学]]専攻（修士課程・博士課程）\n*** 基幹法コース\n*** 税法・ビジネスコース\n*** スポーツ法コース\n* [[総合知的財産法学研究科]]\n** [[知的財産権|総合知的財産法学専攻]]（修士課程）\n* [[工学研究科]]\n** 機械工学専攻（修士課程）\n** 電気工学専攻（修士課程）\n** 建設工学専攻（修士課程）\n** 応用システム工学専攻（博士課程）\n* [[人文科学研究科]]\n** 人文科学専攻（修士課程・博士課程）\n** 教育学専攻（修士課程・博士課程）\n* [[スポーツ・システム研究科]]\n** スポーツ・システム専攻（修士課程）\n*** スポーツ教育コース\n*** スポーツ科学コース\n** スポーツ・システム専攻（博士課程）\n*** スポーツ教育コース\n*** スポーツ科学コース\n* [[救急システム研究科]]\n** 救急システム専攻（修士課程）\n*** 救急救命システム専攻\n*** 救急救命システム専攻（1年コース）\n** 救急救命システム専攻（博士課程）\n*** [[救急医療|救急医療体制]]・政策分野　\n*** 病院前救急症候・鑑別診断分野\n*** [[災害医療]]・防災・災害危機管理マネージメント分野\n* [[グローバルアジア研究科]]\n** グローバルアジア専攻（修士課程）\n** グローバルアジア研究専攻（博士課程）\n\n==== 附属機関 ====\n* [[情報科学]]センター\n* イラク古代文化研究所\n* [[武道]]・[[徳育]]研究所\n* アジア・日本研究センター\n* [[生涯学習]]センター\n* [[ウエルネス]]・リサーチセンター\n* 理工学研究所（理工学部内研究所）\n* 政治研究所（政経部内研究所）\n* 経済研究所（政経部内研究所）\n* 経営研究所（政経部内研究所）\n* 比較法制研究所（法学部内研究所）\n* 最先端技術関連法研究所（法学部内研究所）\n* 体育研究所（体育学部内研究所）\n\n* [[サテライトキャンパス]]\n** キルギスキャンパス（[[ビシュケク人文大学]]内）\n\n;海外拠点\n* 国士舘大学大連事務所（中国・[[遼寧省]]・[[大連市]]）\n\n=== 教育 ===\n====採択されているプログラム====\n*専門職大学院等における[[高度専門職業人]]養成教育推進プログラム\n**海外経営専門職人財養成プログラム（[[早稲田大学]]（幹事校）・国士舘大学・[[武蔵野大学]]・[[明治大学]]・[[立教大学]]）<ref>[http://www.mext.go.jp/b_menu/houdou/20/07/08072909/001/001.htm 平成20年度「専門職大学院等における高度専門職業人養成教育推進プログラム」選定取組一覧]</ref>\n\n== 学生生活 ==\n=== 学園祭 ===\n国士舘大学ではキャンパスごとに学園祭が独立開催されている。\n\n*世田谷キャンパス\n**楓門祭（ふうもんさい）\n**11月2日、3日\n::芸能人のコンサートやミスコンテストが開催されている。なお、国士舘大学では、ミスコンテストの優勝者を『ミス国士舘』ではなく学章の楓にちなんで『メイプルクイーン』と呼ぶ。\n::近年はコンサートよりお笑い芸人のステージが多い。\n::昭和42年に創立50周年を記念して明治祭として開催され、昭和52年より楓門祭となる。\n::開催名は他祭と違い、第○○周年楓門祭\n\n*町田キャンパス\n**鶴川祭（つるかわさい）\n**5月下旬の土曜日、日曜日\n::新入生歓迎の運動会が始まりであったため、現在においてもスポーツ大会が多く開催されている。また、ちびっ子剣道大会、ちびっ子空手大会などの近隣参加企画も準備されている。かつてはバスケットボール、バレーボール、ソフトボール、モンゴル相撲等の大会があった。\n::第1回旧鶴川祭は昭和44年に明治祭に併設され開催。現在の鶴川祭は、昭和60年より開催。\n**アジアンフェスタ\n::21世紀アジア学部が設置される1年前より開催され、設置後は21世紀アジア学部の学生のみで組織され実施されている。第1回は21世紀アジア学部設置の1年前、平成13年度に開催。平成20年度より鶴川祭を継承する。\n\n*多摩キャンパス\n**多摩祭（たまさい）\n**11月第3土曜日、日曜日\n::体育会を中心としたスポーツの祭典である。柔道部や相撲部の学生が出場するカラオケや各競技のユニフォームで参加する部対抗駅伝が開催されている。また、近隣住民も対象としたビンゴ大会をメイン企画として運営しており、多くの家族連れが集まる。\n::平成7年に多摩カップとして開催され、平成8年より開催。\n\n=== スポーツ ===\n*学生スポーツは活発に行われている。全国大会で複数回の優勝を経験している[[国士舘大学サッカー部|サッカー部]]などはマスメディアで取り上げられる機会も多い。\n*[[国士舘大学硬式野球部|硬式野球部]]は[[東都大学野球連盟]]に加盟している。\n*ハンドボール部も長年関東学生ハンドボール連盟1部リーグを維持し、日本代表選手を輩出している。\n*バスケットボール部の愛称は「[[国士舘大学バイキングス|バイキングス]]」。2008年の[[全日本大学バスケットボール選手権大会]]で準優勝に輝いた。\n*[[国士舘大学ラグビー部|ラグビー部]]は1978年の[[関東大学ラグビーリーグ戦グループ]]で優勝を果たした。\n\n=== 学内奨学金 ===\n*入学試験に係わる学内奨学金\n**成績優秀奨学生制度\n\n*学業優秀奨学生\n*運動技能優秀奨学生\n*修学援助奨学生\n**奨学生A：納入金の全額免除\n**奨学生B：入学金を除く納入金の免除\n**奨学生C：授業料の免除\n**奨学生D：授業料の5割免除\n\n*塩沢奨学金（理工学部）\n*田中奨学金（理工学部）\n*中村宗雄奨学基金（法学部）\n*公益信託 橘高倫一記念奨学基金（文学部在籍・千葉県内高校卒業者限定）\n*外国人留学生奨学金\n\n*国際交流センター\n**国士舘大学外国人留学生奨学生\n*交換留学生対象\n**国士舘大学留学奨励金\n\n*国士舘大学同窓会奨学融資（長期・短期）\n\n== 大学関係者と組織 ==\n=== 大学関係者一覧 ===\n*[[国士舘大学の人物一覧]]\n\n== 施設 ==\n=== キャンパス ===\n[[ファイル:koutsuannai3.jpg|thumb|190px|交通]]\nすべてのキャンパスが[[小田急電鉄#路線|小田急線]]で結ばれている。\n*世田谷キャンパス（[[世田谷区]][[世田谷 (世田谷区)|世田谷]]）\n*:[[小田急小田原線]][[梅ヶ丘駅]]\n*:[[東急世田谷線]][[松陰神社前駅]]\n*町田キャンパス（[[町田市]]広袴）\n*:[[小田急小田原線]][[鶴川駅]]下車\n*:国士舘大学スクールバス乗車10分(駅前からキャンパス内まで)。\n*:[[小田急バス]]「鶴11」「鶴13」系統乗車およそ15分。　国士舘大学前下車徒歩1分。\n*:[[神奈川中央交通]]「鶴12」系統乗車およそ15分。　国士舘大学前下車徒歩1分。\n*:[[京王相模原線]][[若葉台駅]]下車\n*:[[神奈川中央交通]]バス「鶴21」系統乗車およそ15分。　[[和光学園]]下車徒歩5分。\n*:[[東急こどもの国線]][[こどもの国駅 (神奈川県)|こどもの国駅]]～小田急バス（鶴川駅下車乗り換え）\n*多摩キャンパス（[[多摩市]]永山7丁目3-1）\n*:[[小田急多摩線]][[永山駅 (東京都)|小田急永山駅]]下車\n*:京王相模原線[[永山駅 (東京都)|京王永山駅]]下車\n*:国士舘大学スクールバス乗車7分(駅前ロータリーからキャンパス前まで)。\n*:[[京王バス]][[神奈川中央交通]]バス「永13」「永14」「桜23」「桜24」「鶴31」のいずれか乗車7分。永山高校前下車徒歩10分。\n\n=== 学生食堂 ===\n<div style="float:left; margin-right: 2em;">\n*世田谷キャンパス\n**世田谷校舎\n*:ニコラス精養堂\n*:アンブラン\n*:[[モスフードサービス]]\n*:[[スエヒロレストラン]]\n**梅ヶ丘校舎\n*:[[エームサービス]]\n</div>\n<div style="float:left; margin-right: 2em;">\n*町田キャンパス\n*:ニコラス精養堂\n*:アンブラン\n*多摩キャンパス\n*:新東京食堂\n</div>\n<br style="clear: both;" />\n\n=== 学生寮 ===\n全寮制として設置された学校の名残として、現在も下記の寮が開設されている。\n*世田谷キャンパス\n**世田谷寮（昭和43年竣工）\n*:松陰寮（一般男子学生のみ）\n*:ゲストハウス（留学生のみ）\n*町田キャンパス\n**鶴川寮（昭和42年竣工）\n*:望嶽寮（一般男子学生と硬式野球部／サッカー部のみ）\n*:すみれ寮（一般女子学生のみ）（昭和45年設置）\n過去に存在した寮\n<div style="float:left; margin-right: 2em;">\n*男子寮\n**回天寮\n**正気寮\n**時習寮\n**青雲寮\n**富士見寮\n**錦楓寮\n</div>\n<div style="float:left; margin-right: 2em;">\n*女子寮\n**常盤寮\n**松柏寮\n**清節寮\n**菊寮\n</div>\n<br style="clear: both;" />\n\n== 対外関係 ==\n* [[2005年]]に[[山形県]][[鮭川村]]と理工学部付属理工学研究所が「学術友好交流協定」を締結。\n* [[2006年]]11月に[[東京都]][[町田市]]と「町田市学長懇談会包括連携協定」を締結。\n* [[2008年]]3月に[[世田谷区]]と「災害時協力協定」を締結。\n* [[2014年]]6月に[[東京オリンピック・パラリンピック競技大会組織委員会|公益財団法人東京オリンピック・パラリンピック競技大会組織委員会]]と2020年「東京オリンピック・パラリンピック競技大会に係る大学連携協定」を締結。<ref>[https://tokyo2020.jp/jp/news/index.php?mode=page&id=1122 2014年06月23日 大学連携協定締結式・記念シンポジウム開催]</ref>\n* 2014年12月に[[新潟県庁|新潟県]]と「学生Ｕ･Ｉターン就職促進に関する協定」を締結。\n* [[2015年]]3月に[[日本赤十字社]]と「社会の安心・安全及び福祉の向上に関するパートナーシップ協定」を締結。\n\n=== 他大学との協定 ===\n* [[首都圏西部大学単位互換協定会]]\n* [[世田谷6大学コンソーシアム]]\n* [[全国私立大学FD連携フォーラム]]\n\n; 大学院単位互換交流協定（人文科学研究科 人文科学専攻）\n* [[史学]]分野の単位互換協定・協定校'''\n** [[青山学院大学|青山学院大学大学院]] [[文学研究科]]史学専攻\n** [[國學院大學|國學院大學大学院]] 文学研究科日本史学専攻\n** [[駒澤大学|駒澤大学大学院]] [[人文科学研究科]]歴史学専攻\n** [[専修大学|専修大学大学院]] 文学研究科史学専攻\n** [[上智大学|上智大学大学院]] 文学研究科史学専攻\n** [[中央大学|中央大学大学院]] 文学研究科国史学専攻・東洋史学専攻・西洋史学専攻\n** [[東海大学|東海大学大学院]] 文学研究科史学専攻\n** [[東洋大学|東洋大学大学院]] 文学研究科史学専攻\n** [[明治大学|明治大学大学院]] 文学研究科史学専攻\n** [[立教大学|立教大学大学院]] 文学研究科史学専攻\n** 国士舘大学大学院 人文科学研究科人文科学専攻\n\n* [[地理学]]分野の単位互換協定・協定校\n** 駒澤大学大学院 人文科学研究科地理学専攻\n** 専修大学大学院 文学研究科地理学専攻\n** [[日本大学|日本大学大学院]] [[理工学研究科]]地理学専攻\n** [[法政大学|法政大学大学院]] 人文科学研究科地理学専攻\n** 明治大学大学院 文学研究科地理学専攻\n** 国士舘大学大学院 人文科学研究科人文科学専攻\n\n* [[考古学]]分野の単位互換協定・協定校\n** 駒澤大学大学院 人文科学研究科歴史学専攻\n** [[昭和女子大学|昭和女子大学大学院]] [[生活機構研究科]]生活文化研究専攻\n** 国士舘大学大学院 人文科学研究科人文科学専攻\n\n===協定校===\n* [[サンフランシスコ州立大学]](アメリカ・[[サンフランシスコ]])\n* [[サイモンフレーザー大学]]([[カナダ]]・[[BC州]])\n* [[カレッジ・オブ・ザ・ロッキーズ]](カナダ・ブリティッシュコロンビア州)\n* [[グリフィス大学]]([[オーストラリア]]・[[クイーンズランド州]])\n* [[漢陽大学校]]([[韓国]]・[[ソウル特別市]])\n* [[高麗大学校]](韓国・ソウル特別市)\n* [[東義大学校]](韓国・[[釜山広域市]])\n* [[安東大学校]](韓国・[[慶尚北道]][[安東市]])\n* [[北京師範大学]]([[中国]]・[[北京市]])\n* [[上海対外貿易学院]](中国・[[上海市]])\n* [[黒龍江大学]]([[中国]]・[[黒竜江省]])\n* [[山西大学]](中国・[[山西省]]・[[太原市]])\n* [[蘇州大学]](中国・[[江蘇省]]・[[蘇州市]]）\n* [[武漢大学]](中国・[[湖北省]]・[[武漢市]]）\n* [[深圳職業技術学院]](中国・[[広東省]])\n* [[青島大学]](中国・[[山東省]]・[[青島市]])\n* [[中国文化大学]]([[台湾]]・[[台北市]])\n* [[国立中山大学]](台湾・[[高雄市]])\n* [[キルギス国立大学]]([[キルギス共和国]])\n* [[ビシュケク人文大学]](キルギス共和国)\n* [[モンゴル国立大学]]([[モンゴル]])\n* [[デ・ラ・サール大学]]([[フィリピン]]・[[マニラ]])\n* [[チュラーロンコーン大学]]([[タイ王国]]・[[バンコク]])\n* [[チエンマイ大学]](タイ王国・[[チエンマイ県]])\n* [[ベトナム国家大学ホーチミン市校|ベトナム国家社会人文科学大学]]([[ベトナム]]・[[ホーチミン市]])\n* [[ヤンゴン大学]]([[ミャンマー]]・[[ヤンゴン]])\n* [[ガジャマダ大学]]([[インドネシア]]・[[ジョグジャカルタ特別州]])\n* [[セブラスマル大学]](インドネシア)\n* [[国立サマルカンド外国語大学]]([[ウズベキスタン]])\n* [[世界経済外交大学]](ウズベキスタン)\n* [[ポーツマス大学]]([[イギリス]]・[[ポーツマス (イングランド)|ポーツマス]])\n* [[ミュンヘン大学]]([[ドイツ]]・[[バイエルン州]]・[[ミュンヘン]])\n* [[センメルヴェイス大学]]([[ハンガリー]]・[[ブダペスト]])\n* [[ルレオ工科大学]]([[スウェーデン]]・[[ノールボッテン県]]・[[ルレオ]])\n* [[極東国立工科大学]]([[ロシア]]・[[ウラジオストック]])\n* [[ヴェリコ・タルノヴォ大学]]([[ブルガリア]]・[[ヴェリコ・タルノヴォ州]]・[[ヴェリコ・タルノヴォ]])\n* [[ユズンチュ・ユル大学]]([[トルコ]]・[[ヴァン県]]・[[ヴァン]])\n* [[ハジェットテッペ大学]](トルコ・[[アンカラ県]]・[[アンカラ]])\n* [[ヤルムーク大学]]([[ヨルダン]]・[[イルビド県]])\n* [[アディスアベバ大学]]([[エチオピア]]・[[アディスアベバ]])\n\n=== 系列校 ===\nいわゆる大学を頂点とする「[[附属学校]]」ではなく、同一学校法人が運営する独立した学校の集合体という形態を取っている。\n*[[国士舘中学校・高等学校]]（世田谷区）\n*過去に存在した系列校。\n**[[国士舘短期大学]]（[[町田市]]広袴）\n**[[国士舘大学福祉専門学校]]（[[太宰府市]]御笠）\n\n== 脚注 ==\n{{脚注ヘルプ}}\n{{Reflist}}\n\n== 外部リンク ==\n{{commonscat|Kokushikan University}}\n*{{Official|http://www.kokushikan.ac.jp/}}\n\n{{学校法人国士舘}}\n{{首都圏西部大学単位互換協定会}}\n{{世田谷6大学コンソーシアム}}\n{{全国救急救命士教育施設協議会}}\n{{全国私立大学FD連携フォーラム}}\n\n{{デフォルトソート:こくしかんたいかく}}\n[[Category:国士舘大学|*]]\n[[Category:学校記事]]	</BODY>
  <MECAB>国士舘大学  国士舘大学 は [[ 1917年 ]] に [[ 柴田徳次郎 ]] により 創設 さ れ た 私塾 で ある 国士舘 と それ に 続く [[ 旧制中学校 ]] が 母体 と なっ て 設立 さ れ た [[ 大学 ]] で ある 。 元来 は 青年 期 における 人間 形成 を 目的 と し た 中等教育 機関 として 発足 し て おり 、 大学 の 設置 は 比較的 遅い [[ 1958年 ]] で ある 。 現在 、 3 キャンパス に 7 学部 10 研究 科 を 有する 。 
物質文明 の 弊 日 に 甚だしく 、 人 は 唯 だ科 學 智 を 重んじ て 、 徳性 涵養 を 忘 る 今日 に 於 て 敎育 と は 唯 だ科 學 智 の 賣 買 たる のみ 此 の 如き は 唯 だ 物質文明 に 終る 、 精神文明 なくし て 國家 豈 に 一日 の 安き を 得 ん や 、 蓋し 精神文明 は 物質文明 を 統一 指導 する もの なり 、 精巧 の 武器 、 萬 種 羅列 する も 、 兵士 起っ て 之 運用 する に 非 る より は 、 戦場 に 何 の 効果 なから ん 、 吾 人 は 精神文明 と 精神 敎育 と を 此 際 に 唱道 し て 國家 の 柱石 たる 眞 知識 を 養成 せん 事 を 期す 。 
一國 の 最高 學 府 は 未 た 天下 に 公開 さ れ ざる なり 、 若し 公開 さ れる ゝ と する も 、 ノート 式 の 講義 は 單竟 死 學 のみ 、 其 説く 處 高遠 深邃 なる が 如き も 、 遂に 之 れ 形式 範 畴 のみ 、 何等 の 情熱 なく 、 信念 なし 、 人 を 化 する の 力 なし 、 形式 、 規則 、 規律 、 試験 、 之 れ 今日 の 所謂 敎育 なる もの なり 。 
吾 人 茲に 於 てか 卓 落 不 覊 高く 形式 の 外 に 立つ の 士 に 依り 、 膝 を 交 へ て 親しく 活 學 を 講ずる の 道場 を 開設 せ ん と 欲す 、 法三章 、 唯 だ 眞 に 師 たり 弟 たる の 情誼 に 依っ て 之 を 維持 せん 事 を 期す 、 來 る 者 は 拒ま ず 去る 者 は 追 はず 、 天 空海 濶 他 の 覊束 なく 、 唯 だ 自ら 守る 禮 節 を 尚ぶ のみ 。 
而 し て 此 の 道場 は 大 自力 を 孕む の 契機 たる を 期す 、 陋隘 僅か に 膝 を 容 るる の 一 小寺 小屋 たり と 雖 も 、 大正 維新 の 松蔭 塾 たる 効果 あら ん 、 一心 足 つて 萬 能 始め て 用 ゆべし 、 我が 道場 の 期する 處 は 、 心 學 なり 活 學 なり 、 信念 の 交感 なり 、 理 を 説い て 理 に 堕せ ず 、 術 を 語 つて 術 に 溺れ ず 、 舌頭 萬 有 を 吐呑 し て 方丈 裏 に 風雲 を 捲か ん と する に 在り 。 
寄付行為 に 定め られ て いる 以下 の 内容 を 建 学 の 精神 あるいは 設立 趣旨 と 誤解 し て いる ケース が ある が 、 これ は 設立 趣旨 で は なく 、 あくまで 国士舘 における 教育 指針 の 3 大 要綱 「 読書 」 「 体験 」 「 反省 」 と 4条 目 「 誠意 」 「 勤労 」 「 見識 」 「 気魄 」 の 訓話 を 学校法人 至徳 学園 設立 時 に 寄付行為 に し た もの で ある 。 大学 の 理念 の 根底 と は なっ て いる が 、 正確 に は 設立 趣旨 で は ない 。 
聖人 至徳 を 志し 、 不断 の 読書 、 体験 、 反省 により 、 誠意 ・ 勤労 ・ 見識 ・ 気魄 を 涵養 し 、 もっ て 道義 日本 を 建設 し 、 世界 の 平和 と 進運 と に 貢献 する 有為 の 人材 を 養成 する 教育 を 行う こと を 目的 と する 。 （ 出典 . 1919 （ 大正 8 ） 年 11月4日 私塾 国士舘 入学式 訓話 、 寄付行為 自体 は 1952 （ 昭和 27 ） 年 10月10日 に 旧 [[ 文部科学省 | 文部省 ]] によって 認可 さ れ 、 その後 改訂 さ れ て い ない ） 
体育学部 を 擁し て いる 高等教育 機関 で ある ため 、 [[ 警視庁 ]]、[[ 神奈川県警察 | 神奈川県警 ]] を はじめ と する 警察 へ の 就職 は 多い 。 また 、 体育学部 ・ 文学部 の 両 学部 で は 、 それぞれ の 所定 の [[ 教職課程 ]] を 修了 する こと により [[ 養護教諭 | 養護教諭 一 種 ]] を 取得 する こと が できる カリキュラム が 用意 さ れ て いる < ref >[ http:// www . mext . go .jp / a _ menu / shotou / ky oi n/ daigaku / 04041301 / 007 . htm 養護教諭 の 免許 資格 を 取得 する こと の できる 大学 , 文部科学省 HP ]</ ref >< ref >[ http:// www . kokushikan . ac.jp / career / qualification / 042700 _ 0105 . html 資格 取得 教職課程 , 国士舘大学 HP ]</ ref >。 21世紀 アジア 学部 において は 、 大学院 の グローバル アジア 研究科 と 合わせ 修士課程 を 1年 含め 5年間 で 修了 する こと が 可能 で ある 。 工学 系 において は 、 [[ 全日本学生フォーミュラ大会 ]] で 好成績 を 収め て いる 。 また 、 平成27年度 の [[ 科学 研究 費 補助金 | 科研費 ]] 採択 数 は 40件 （ 新規 採択 、 継続 および 転入 分 ） を 数える 。 [[ 奨学金 ]] 制度 は 、 毎年 4月 ごろ に 各 学部 ・ 各 研究科 で 募集 が 行わ れ て いる 。 [[ 首都圏西部大学単位互換協定会 ]] 協定 の 会長 校 で ある 。 
スポーツ 関係 で 活躍 する 在校生 ・ 出身 者 が 多く 、 柔道 で は オリンピック 金 メダリスト を 輩出 する など スポーツ における 著名 な 卒業生 は 層 が 厚い 。 また 、 サッカー部 は [[ 日本プロサッカーリーグ | Jリーガー ]] として 活躍 する プレイヤー を 多く 送り出し 続ける 実績 は 特筆 できる 一つ で ある 。 全 学部 ・ 学科 において 、 各 専攻 に 応じ た 教員免許 状 取得 が 可能 な 教職課程 カリキュラム が 設定 さ れ て いる < ref >[ http:// www . kokushikan . ac.jp / career / qualification / 042700 _ 0105 . html 資格 取得 教職課程 , 国士舘大学 HP ]</ ref >。 さらに 学部 によって は 、 在籍 学科 を 修了 する こと で 他 の 資格 取得 や 受験 資格 を 得 られる < ref >[ http:// www . kokushikan . ac.jp / career / qualification / 042700 _ 0106 . html 資格 取得 各種 資格 , 国士舘大学 HP ]</ ref >。 大学 関係者 は 、 学生 気質 も 以前 に 比べ て 柔らかく なり 、 かつて の 「 硬派 」 「 右 より 思想 」 という イメージ は 払拭 さ れ た と 考え 始め て いる < ref >[ http:// www .s hid aik yo. or .jp / newspaper / online / 2391 / 8 _ 1 . html 日本私立大学協会 〔 連載 〕 高め よ 深めよ 大学 広報 力 〈 61 〉 こう やっ て 変革 し た 58 平成22年 2月 第 2391 号 （ 2月17日 ）]</ ref >< ref >[ http:// www . amazon.co.jp /% E 5% A 4% A 7% E 5% AD % A6 % E 7% 94% 9 F % E 5% 9 B % B 3% E 9% 91% 91 - 2012 -% E3 % 80% 9 C % E 4% BA % BA % E 6% B 0% 97% E3 % 82% A 4% E3 % 83% A9 % E3 % 82% B 9% E3 % 83% 88% E3 % 83% AC % E3 % 83% BC % E3 % 82% BF % E3 % 83% BC % E3 % 83% BB % E 6% BC % AB % E 7% 94% BB % E 5% AE % B 6% E3 % 81% 8 C % E 6% 8 F % 8 F % E3 % 81% 8 F % E 6% 9 C % 89% E 5% 90% 8 D % E 5% A 4% A 7% E 5% AD % A6 60% E 6% A 0% A1 % EF % BC % 81% E3 % 80% 9 C -% E 6% 99% 8 B % E 9% 81% 8 A % E 8% 88% 8 E % E3 % 83% A 0% E3 % 83% 83% E3 % 82% AF -% E 5% B 1% B 1% E 5% 86% 85 -% E 5% A 4% AA % E 5% 9 C % B 0 / dp / 4863912528 山内太地 ( 監修 ) 『 大学生 図鑑 2012 』 晋遊舎 ]</ ref >。「 うご パン 」 という 学生 向け 情報誌 が 年 5回 （ 4 ・ 6 ・ 9 ・ 10 ・ 12月 を 予定 ） 各 キャンパス で 配布 さ れ て いる 。 
私塾 国士舘 は [[ 玄洋社 ]] の 流れ を 組む [[ 青年 大 民 團 ]] の 思想 を 広める 教育機関 として 設立 さ れ た 。 [[ 興亜専門学校 ( 旧制 )| 興亜専門学校 ]]（ 現在 の [[ 亜細亜大学 ]]） と 国士舘 専門学校 （ 旧制 ） における 興亜 科 の 関係 は 興亜専門学校 の 設立 に 興亜 科 の [[ 藤原 繁 ]] や その他 の 教職員 が 加わっ て い た ため 、 学校法人国士舘 及び 国士舘大学 の 正史 に は 興亜 科 が 国士舘 専門学校 より 分離 し た と 記述 が ある （ 設置 申請 者 が 財団法人 国士舘 で あっ た が 興亜 科 自体 は 独立 経営 で あっ た ） 。 ただし 、 興亜専門学校 設置 により 興亜 科 は 廃止 と なっ た の は 事実 で ある < ref >[ http:// www . tokyu . co.jp / kouken / k _ asia . html （ 東急グループ ）]</ ref >。 
[[ File : Kokushikan found ing fathers .jpg | thumb | 国士舘 の 設立 を 協議 する 有志 < br /> 前列 左 から [[ 頭山 満 ]]、[[ 野田卯太郎 ]]、[[ 渋沢 栄一 ]]、[[ 徳富 蘇峰 ]]、 後列 最 右 が 創立者 の [[ 柴田徳次郎 ]]。]] 
* 2013年 大学院 ・ 法学研究科 に ３ コース 制 （ 基幹 法 コース ・ 税法 ・ ビジネス コース ・ スポーツ 法 コース ） を 導入 。 
* 校章 は [[ 楓 ]] を イメージ し て いる （ 中高 に 若干 の デザイン の 違い が ある ） 。 
* 大学 歌 は ない 。 しかし 、 学校法人国士舘 が 設置 し て いる 学校 で 統一 的 に 舘 歌 として 歌わ れ て いる 。 （ 中高 において は 歌詞 が “ 皇 國 ” が “ 御 國 ” 、 “ 殉 す ” が “ ゆるす ” と なっ て いる ） 
* シンボルマーク は アルファベット の K を デザイン で ある 。 
* スクールカラー は 特に 決まっ て は い ない が 、 近年 は シンボルマーク の K の 色 を 、 深紅 の 楓 の 色 を オリジナル の 国士舘 レッド として 使用 し て いる 。 
国士舘大学 で は キャンパス ごと に 学園祭 が 独立 開催 さ れ て いる 。 
:: 芸能人 の コンサート や ミスコンテスト が 開催 さ れ て いる 。 なお 、 国士舘大学 で は 、 ミスコンテスト の 優勝者 を 『 ミス 国士舘 』 では な く学 章 の 楓 に ちなん で 『 メイプル クイーン 』 と 呼ぶ 。 
:: 近年 は コンサート より お笑い芸人 の ステージ が 多い 。 
:: 昭和42年 に 創立 50周年 を 記念 し て 明治 祭 として 開催 さ れ 、 昭和52年 より 楓 門 祭 と なる 。 
:: 新入生 歓迎 の 運動会 が 始まり で あっ た ため 、 現在 において も スポーツ大会 が 多く 開催 さ れ て いる 。 また 、 ちび っ子 剣道 大会 、 ちび っ子 空手 大会 など の 近隣 参加 企画 も 準備 さ れ て いる 。 かつて は バスケットボール 、 バレーボール 、 ソフトボール 、 モンゴル 相撲 等 の 大会 が あっ た 。 
:: 第 1回 旧 鶴川 祭 は 昭和44年 に 明治 祭 に 併設 さ れ 開催 。 現在 の 鶴川 祭 は 、 昭和60年 より 開催 。 
:: 21世紀 アジア 学部 が 設置 さ れる 1年前 より 開催 さ れ 、 設置 後 は 21世紀 アジア 学部 の 学生 のみ で 組織 さ れ 実施 さ れ て いる 。 第 1回 は 21世紀 アジア 学部 設置 の 1年前 、 平成13年度 に 開催 。 平成20年度 より 鶴川 祭 を 継承 する 。 
:: 体育会 を 中心 と し た スポーツ の 祭典 で ある 。 柔道部 や 相撲 部 の 学生 が 出場 する カラオケ や 各 競技 の ユニフォーム で 参加 する 部 対抗 駅伝 が 開催 さ れ て いる 。 また 、 近隣住民 も 対象 と し た ビンゴ 大会 を メイン 企画 として 運営 し て おり 、 多く の 家族連れ が 集まる 。 
:: 平成7年 に 多摩 カップ として 開催 さ れ 、 平成8年 より 開催 。 
* 学生スポーツ は 活発 に 行わ れ て いる 。 全国大会 で 複数回 の 優勝 を 経験 し て いる [[ 国士舘大学サッカー部 | サッカー部 ]] など は マスメディア で 取り上げ られる 機会 も 多い 。 
*[[ 国士舘大学硬式野球部 | 硬式野球部 ]] は [[ 東都大学野球連盟 ]] に 加盟 し て いる 。 
* ハンドボール 部 も 長年 関東 学生 ハンドボール 連盟 1部 リーグ を 維持 し 、 日本代表 選手 を 輩出 し て いる 。 
* バスケットボール部 の 愛称 は 「 [[ 国士舘大学 バイキングス | バイキングス ]]」。 2008年 の [[ 全日本大学バスケットボール選手権大会 ]] で 準優勝 に 輝い た 。 
*[[ 国士舘大学ラグビー部 | ラグビー部 ]] は 1978年 の [[ 関東大学ラグビーリーグ戦グループ ]] で 優勝 を 果たし た 。 
すべて の キャンパス が [[ 小田急電鉄 # 路線 | 小田急線 ]] で 結ば れ て いる 。 
*: 国士舘大学 スクールバス 乗車 10分 ( 駅前 から キャンパス 内 まで )。 
*:[[ 小田急バス ]]「 鶴 11 」 「 鶴 13 」 系統 乗車 およそ 15分 。 　 国士舘大学 前 下車 徒歩 1分 。 
*:[[ 神奈川中央 交通 ]]「 鶴 12 」 系統 乗車 およそ 15分 。 　 国士舘大学 前 下車 徒歩 1分 。 
*:[[ 神奈川中央 交通 ]] バス 「 鶴 21 」 系統 乗車 およそ 15分 。 　 [[ 和光学園 ]] 下車 徒歩 5分 。 
*: 国士舘大学 スクールバス 乗車 7分 ( 駅前 ロータリー から キャンパス前 まで )。 
*:[[ 京王バス ]][[ 神奈川中央 交通 ]] バス 「 永 13 」 「 永 14 」 「 桜 23 」 「 桜 24 」 「 鶴 31 」 の いずれ か 乗車 7分 。 永山 高校前 下車 徒歩 10分 。 
全寮 制 として 設置 さ れ た 学校 の 名残 として 、 現在 も 下記 の 寮 が 開設 さ れ て いる 。 
* [[ 2005年 ]] に [[ 山形県 ]][[ 鮭川村 ]] と 理工学部 付属 理工学 研究所 が 「 学術 友好 交流 協定 」 を 締結 。 
* [[ 2006年 ]] 11月 に [[ 東京都 ]][[ 町田市 ]] と 「 町田市 学長 懇談会 包括 連携 協定 」 を 締結 。 
* [[ 2008年 ]] 3月 に [[ 世田谷区 ]] と 「 災害時 協力 協定 」 を 締結 。 
* [[ 2014年 ]] 6月 に [[ 東京オリンピック・パラリンピック競技大会組織委員会 | 公益財団法人 東京オリンピック・パラリンピック競技大会組織委員会 ]] と 2020年 「 東京オリンピック ・ パラリンピック 競技大会 に 係る 大学 連携 協定 」 を 締結 。 < ref >[ https :// tokyo 2020 .jp / jp / news / index . php ? mode = page & id = 1122 2014年 06 月 23日 大学 連携 協定締結 式 ・ 記念 シンポジウム 開催 ]</ ref > 
* 2014年 12月 に [[ 新潟県庁 | 新潟県 ]] と 「 学生 Ｕ ･ Ｉ ターン 就職 促進 に関する 協定 」 を 締結 。 
* [[ 2015年 ]] 3月 に [[ 日本赤十字 社 ]] と 「 社会 の 安心 ・ 安全 及び 福祉 の 向上 に関する パートナーシップ 協定 」 を 締結 。 
いわゆる 大学 を 頂点 と する 「[[ 附属学校 ]]」 では なく 、 同 一 学校法人 が 運営 する 独立 し た 学校 の 集合体 という 形態 を 取っ て いる 。 
* 過去 に 存在 し た 系列 校 。 </MECAB>
  <ID>525778</ID><LATESTID>58613573</LATESTID><NAMESPACE>0</NAMESPACE><RESTRICTIONS>edit=autoconfirmed:move=autoconfirmed</RESTRICTIONS><ISREDIRECT>0</ISREDIRECT><ISNEW>0</ISNEW><RANDOM>1</RANDOM><TOUCHED>0.32289098319597542</TOUCHED><LINKSUPDATED>20160214124941</LINKSUPDATED><LEN>32122</LEN><CONTENTMODEL></CONTENTMODEL><LANG></LANG></ITEM>
