<ITEM>
  <TITEL>吉武真太郎</TITLE>
  <META>{{Infobox baseball playern|選手名             = 吉武 真太郎n|所属球団           = n|背番号             = n|選手写真ファイル名 = n|写真のコメント     = n|国籍               ={{JPN}}{{生年月日と年齢|1975|6|3}}{{NPBドラフト|1993}}{{cite book| 1=和書 | title=プロ野球カラー名鑑 2008 | publisher=[[ベースボール・マガジン社]] | year=2008 | page=15 | isbn=978-4-583-61526-4}}{{Cite book|和書|year=2005|title=応援ありがとう!2005福岡ソフトバンクホークス激闘の軌跡 |publisher=ソフトバンククリエイティブ |pages=82頁|id=ISBN 4-7973-3331-6}}{{Cite book|和書|year=2006|title=福岡ソフトバンクホークス激闘の軌跡2006 |publisher=福岡ソフトバンクホークスマーケティング |pages=85頁|id=ISBN 4-7973-3840-7}}{{投手成績|リーグ=日本プロ野球}}{{by2|1995}}{{by2|1996}}{{by2|1997}}{{by2|1998}}{{by2|1999}}{{by2|2001}}{{by2|2002}}{{by2|2003}}{{by2|2004}}{{by2|2005}}{{by2|2006}}{{by2|2007}}{{by2|2008}}{{NPB|11213889}}{{福岡ダイエーホークス1993年ドラフト指名選手}}{{DEFAULTSORT:よしたけ しんたろう}}</META>
  <DESCRIPTION>	{{Infobox baseball player\n|選手名             = 吉武 真太郎\n|所属球団           = \n|背番号             = \n|選手写真ファイル名 = \n|写真のコメント     = \n|国籍               = \n|出身地             = [[大分県]][[東国東郡]][[国見町 (大分県)|国見町]]（現：[[国東市]]）\n|生年月日           = \n|没年月日           = \n|身長               = 179\n|体重               = 84\n|利き腕             = 右\n|打席               = 右\n|守備位置           = [[投手]]\n|プロ入り年度       = \n|ドラフト順位       = ドラフト4位<ref name="meikan2008" />\n|初出場             = 1995年4月6日\n|最終出場           = 2008年4月4日\n|年俸               = \n|経歴               = <nowiki></nowiki>\n* [[大分県立国東高等学校]]<ref name="meikan2008" />\n* [[福岡ソフトバンクホークス|福岡ダイエーホークス<br />福岡ソフトバンクホークス]] (1994 - 2006)<ref name="meikan2008" />\n* [[読売ジャイアンツ]] (2007 - 2008)\n}}\n'''吉武 真太郎'''（よしたけ しんたろう、[[1975年]][[6月3日]]<ref name="meikan2008"></ref> - ）は、[[大分県]][[東国東郡]][[国見町 (大分県)|国見町]]（現：[[国東市]]）出身の元[[プロ野球選手]]（[[投手]]）。現在は、[[読売ジャイアンツ]]の[[スカウト (勧誘)|スカウト]]。\n\n== 経歴 ==\n=== プロ入り前 ===\n\n[[大分県立国東高等学校|国東高校]]野球部在籍時代にはプロには興味がなく、教員志望だった。ドラフト当日も自転車で帰宅し、指名を知った監督が追いかけて来た程だった<ref name="ベースボールマガジン2月9-16日">雑誌「週刊ベースボール」（ベースボールマガジン社刊）2009年2月9&16日号43-47ページ 「惜別球人 吉武真太郎」</ref>。[[1993年]]、ドラフト4位で[[福岡ソフトバンクホークス|福岡ダイエーホークス]]に指名され入団<ref name="meikan2008" />。\n=== プロ入り後 ===\n=== ダイエー・ソフトバンク時代 ===\n\n入団1年目の[[1994年]]は1軍登録はなく2軍でも未勝利に終わった。しかし秋の教育リーグで投球のコツをつかんだ。\n\n2年目の[[1995年]]春のキャンプでは[[村田兆治]]コーチの指導を受けて才能が開花<ref name="ベースボールマガジン2月9-16日" />。この年は24試合に登板し、先発としては11試合に登板した。最終的に5勝5敗、防御率4.28の成績を残した。\n\n[[1996年]]も先発と[[中継ぎ]]の両方で起用され、35試合に登板したが、4勝13敗1セーブと不本意な成績で終わったが、防御率は3.44と前年より良化した。\n\n4年目の[[1997年]]には'''3試合連続無[[四球]][[完投]]勝利で6月の月間MVP'''に選ばれるなど、7勝7敗の成績を残す見せた。\n\n将来を嘱望される若手投手であったが、翌年[[1998年]]は5勝止まりで終わってしまい、防御率も4点台と再び悪化した。\n\nチームがリーグ優勝を飾った[[1999年]]はわずか1勝に終わってしまった。\n\n[[2000年]]は1軍登板なしでシーズンを終了した。一方でチームは日本一は逃したものの、リーグ連覇を達成した。\n\n[[2001年]]からはチームの先発陣が安定してきたこともあり[[リリーフ]]に転向。同年は18試合に登板するも、防御率5.56と安定感を欠いた。\n\n[[2002年]]はわずか6試合の登板に終わった。\n\n[[2003年]]は才能が開花し、自身最多の42試合に登板した。防御率4.43と安定感は欠いたものの貴重なリリーバーとしてチーム3年ぶりのリーグ優勝と日本一に貢献した。この頃に[[カット・ファスト・ボール|カットボール]]を習得し、投球の幅が広がった。\n\n[[2004年]]は前年の疲労があったのか13試合の登板に終わったが、防御率は1点台だった。\n\n[[2005年]]は[[2005年のオールスターゲーム (日本プロ野球)|オールスターゲーム]]に監督推薦で初出場を果たした。シーズンではリーグ2位の61試合に登板し、6月にリーグ新記録となる8試合連続ホールドを記録し<ref></ref>、最終的に32ホールドを記録し、チーム勝率1位に貢献した。\n\n翌年[[2006年]]も60試合に登板し、20ホールドをマークするなど、貴重な中継ぎとして活躍した。[[12月10日]]、[[フリーエージェント (日本プロ野球)|FA宣言]]でホークスへ復帰した[[小久保裕紀]]の人的補償選手として[[読売ジャイアンツ]]へ移籍した。\n=== 巨人時代 ===\n\n移籍1年目の[[2007年]]は開幕第3戦の[[横浜DeNAベイスターズ|横浜ベイスターズ]]戦([[横浜スタジアム]])で移籍後初登板するが1失点すると、これまでの活躍によって肩の勤続疲労に悩まされていたこともあり、登録を抹消された。その後は2軍で再調整を兼ねた登板を続けた。8月1日に1軍昇格。敗戦処理から徐々に信頼を上げ好投を続けた。8月25日の[[広島東洋カープ]]戦で5-4の1点ビハインドから[[金刃憲人]]をリリーフ、6回裏を3者凡退に抑えると7回表に巨人が逆転。続く7回も無失点に抑え、巨人での初勝利を挙げた。この年は防御率1.89であったが、前半戦は2軍生活だったこともあり、16試合の登板にとどまった。\n\n[[2008年]]は前年同様開幕1軍だったものの、開幕第3戦の3月30日の[[東京ヤクルトスワローズ]]戦で勝ち越し点を与えるなど不安定で序盤の3試合の登板しただけで4月10日に1軍登録抹消された。その後は1軍登板することなくシーズンを終えた。オフに[[戦力外通告]]を受けた。その後現役を引退した。\n\n=== 引退後 ===\n\n引退後は巨人の[[打撃投手]]に転向。[[2011年]]からスカウト<ref name="shuube20140324_P20">週刊ベースボール2014年3月24日号 P20</ref>。\n\n== プレースタイル ==\n[[カット・ファスト・ボール|カットボール]]、[[シュートボール|シュート]]、[[フォークボール|フォーク]]を使ってベースの四隅を突くピッチングが特徴<ref></ref>。\n\n== 詳細情報 ==\n=== 年度別投手成績 ===\n{| \n|-\n|style="text-align: center;"|\n|rowspan="11" style="text-align:center; white-space:nowrap;"|[[福岡ソフトバンクホークス|ダイエー<br />ソフトバンク]]\n||24||11||1||0||0||5||5||0||--||.500||352||82.0||78||13||35||1||2||38||5||'''2'''||43||39||4.28||1.38\n|-\n|style="text-align: center;"|\n||35||16||6||1||0||4||13||1||--||.235||599||141.1||136||14||48||5||7||83||3||0||59||54||3.44||1.30\n|-\n|style="text-align: center;"|\n||18||15||7||2||'''4'''||7||7||0||--||.500||438||109.1||97||13||22||0||1||76||0||0||44||43||3.54||1.09\n|-\n|style="text-align: center;"|\n||15||11||2||1||0||5||4||0||--||.556||332||74.2||89||7||23||1||4||24||2||1||42||38||4.58||1.50\n|-\n|style="text-align: center;"|\n||8||2||0||0||0||1||1||0||--||.500||84||18.2||30||2||3||0||0||9||1||0||18||15||7.23||1.77\n|-\n|style="text-align: center;"|\n||18||0||0||0||0||0||1||0||--||.000||100||22.2||29||6||7||0||0||21||1||0||14||14||5.56||1.59\n|-\n|style="text-align: center;"|\n||6||0||0||0||0||0||0||0||--||----||35||7.2||9||2||2||0||1||9||0||0||9||3||3.52||1.43\n|-\n|style="text-align: center;"|\n||42||0||0||0||0||1||3||1||--||.250||189||44.2||45||3||13||2||2||34||0||0||22||22||4.43||1.30\n|-\n|style="text-align: center;"|\n||13||0||0||0||0||0||0||2||--||----||58||14.2||13||2||2||0||1||10||0||1||3||3||1.84||1.02\n|-\n|style="text-align: center;"|\n||61||0||0||0||0||2||4||1||32||.333||252||66.1||70||2||19||4||3||49||0||0||24||23||3.12||1.34\n|-\n|style="text-align: center;"|\n||60||0||0||0||0||3||2||0||20||.600||288||65.2||70||4||20||0||3||36||0||0||24||22||3.02||1.37\n|-\n|style="text-align: center;"|\n|rowspan="2" style="text-align:center;"|[[読売ジャイアンツ|巨人]]\n||16||0||0||0||0||2||0||0||0||1.000||71||19.0||12||1||5||1||0||11||0||1||4||4||1.89||0.89\n|-\n|style="text-align: center;"|\n||3||0||0||0||0||0||1||0||0||.000||13||2.1||4||0||2||0||0||2||0||0||3||3||11.57||2.57\n|-\n!colspan="2"|通算：13年\n||319||55||16||4||4||30||41||5||52||.423||2844||669.0||682||69||201||14||24||402||12||5||309||283||3.81||1.32\n|}\n* 各年度の'''太字'''はリーグ最高\n\n=== 表彰 ===\n* [[月間MVP (日本プロ野球)|月間MVP]]：1回（1997年6月）\n\n=== 記録 ===\n* 初登板・初先発・初勝利：1995年4月6日、対[[千葉ロッテマリーンズ]]3回戦（[[千葉マリンスタジアム]]）、5回2/3を2失点\n* 初奪三振：同上、1回裏に[[安藤学]]から\n* 初完投勝利：1995年7月12日、対[[埼玉西武ライオンズ|西武ライオンズ]]12回戦（[[福岡ドーム]]）、9回2失点\n* 初完封勝利：1996年5月22日、対西武ライオンズ12回戦（[[西武ドーム|西武ライオンズ球場]]）\n* 初セーブ：1996年9月7日、対[[北海道日本ハムファイターズ|日本ハムファイターズ]]25回戦（[[東京ドーム]]）、9回裏1死に7番手として救援登板・完了、2/3回無失点\n* 初ホールド：2005年3月30日、対[[東北楽天ゴールデンイーグルス]]3回戦（福岡Yahoo! JAPANドーム）、6回表2死に3番手として救援登板、2回1/3を無失点\n* 最高年俸：6800万(推定)\n* [[オールスターゲーム (日本プロ野球)|オールスターゲーム]]出場：1回（2005年）\n\n=== 背番号 ===\n* '''37''' （1994年 - 1994年途中）\n* '''67''' （1994年途中 - 1996年）\n* '''34''' （1997年 - 2006年）\n* '''39''' （2007年 - 2008年）\n* '''122''' （2009年）\n* '''008''' （2010年）\n\n== 脚注 ==\n<references />\n\n== 関連項目 ==\n* [[大分県出身の人物一覧]]\n* [[福岡ソフトバンクホークスの選手一覧]]\n* [[読売ジャイアンツの選手一覧]]\n* [[死球#危険球|危険球]] - 現在の規則で退場者パシフィック第1号\n* [[苺みるく]] - 現役時代に交際していた\n\n== 外部リンク ==\n\n\n\n\n\n[[Category:日本の野球選手]]\n[[Category:福岡ソフトバンクホークス及びその前身球団の選手]]\n[[Category:読売ジャイアンツ及び東京巨人軍の選手]]\n[[Category:日本の打撃投手]]\n[[Category:大分県出身の人物]]\n[[Category:1975年生]]\n[[Category:存命人物]]	</DESCRIPTION>
  <BODY>59163359	{{Infobox baseball player\n|選手名             = 吉武 真太郎\n|所属球団           = \n|背番号             = \n|選手写真ファイル名 = \n|写真のコメント     = \n|国籍               = {{JPN}}\n|出身地             = [[大分県]][[東国東郡]][[国見町 (大分県)|国見町]]（現：[[国東市]]）\n|生年月日           = {{生年月日と年齢|1975|6|3}}\n|没年月日           = \n|身長               = 179\n|体重               = 84\n|利き腕             = 右\n|打席               = 右\n|守備位置           = [[投手]]\n|プロ入り年度       = {{NPBドラフト|1993}}\n|ドラフト順位       = ドラフト4位<ref name="meikan2008" />\n|初出場             = 1995年4月6日\n|最終出場           = 2008年4月4日\n|年俸               = \n|経歴               = <nowiki></nowiki>\n* [[大分県立国東高等学校]]<ref name="meikan2008" />\n* [[福岡ソフトバンクホークス|福岡ダイエーホークス<br />福岡ソフトバンクホークス]] (1994 - 2006)<ref name="meikan2008" />\n* [[読売ジャイアンツ]] (2007 - 2008)\n}}\n'''吉武 真太郎'''（よしたけ しんたろう、[[1975年]][[6月3日]]<ref name="meikan2008">{{cite book| 1=和書 | title=プロ野球カラー名鑑 2008 | publisher=[[ベースボール・マガジン社]] | year=2008 | page=15 | isbn=978-4-583-61526-4}}</ref> - ）は、[[大分県]][[東国東郡]][[国見町 (大分県)|国見町]]（現：[[国東市]]）出身の元[[プロ野球選手]]（[[投手]]）。現在は、[[読売ジャイアンツ]]の[[スカウト (勧誘)|スカウト]]。\n\n== 経歴 ==\n=== プロ入り前 ===\n\n[[大分県立国東高等学校|国東高校]]野球部在籍時代にはプロには興味がなく、教員志望だった。ドラフト当日も自転車で帰宅し、指名を知った監督が追いかけて来た程だった<ref name="ベースボールマガジン2月9-16日">雑誌「週刊ベースボール」（ベースボールマガジン社刊）2009年2月9&16日号43-47ページ 「惜別球人 吉武真太郎」</ref>。[[1993年]]、ドラフト4位で[[福岡ソフトバンクホークス|福岡ダイエーホークス]]に指名され入団<ref name="meikan2008" />。\n=== プロ入り後 ===\n=== ダイエー・ソフトバンク時代 ===\n\n入団1年目の[[1994年]]は1軍登録はなく2軍でも未勝利に終わった。しかし秋の教育リーグで投球のコツをつかんだ。\n\n2年目の[[1995年]]春のキャンプでは[[村田兆治]]コーチの指導を受けて才能が開花<ref name="ベースボールマガジン2月9-16日" />。この年は24試合に登板し、先発としては11試合に登板した。最終的に5勝5敗、防御率4.28の成績を残した。\n\n[[1996年]]も先発と[[中継ぎ]]の両方で起用され、35試合に登板したが、4勝13敗1セーブと不本意な成績で終わったが、防御率は3.44と前年より良化した。\n\n4年目の[[1997年]]には'''3試合連続無[[四球]][[完投]]勝利で6月の月間MVP'''に選ばれるなど、7勝7敗の成績を残す見せた。\n\n将来を嘱望される若手投手であったが、翌年[[1998年]]は5勝止まりで終わってしまい、防御率も4点台と再び悪化した。\n\nチームがリーグ優勝を飾った[[1999年]]はわずか1勝に終わってしまった。\n\n[[2000年]]は1軍登板なしでシーズンを終了した。一方でチームは日本一は逃したものの、リーグ連覇を達成した。\n\n[[2001年]]からはチームの先発陣が安定してきたこともあり[[リリーフ]]に転向。同年は18試合に登板するも、防御率5.56と安定感を欠いた。\n\n[[2002年]]はわずか6試合の登板に終わった。\n\n[[2003年]]は才能が開花し、自身最多の42試合に登板した。防御率4.43と安定感は欠いたものの貴重なリリーバーとしてチーム3年ぶりのリーグ優勝と日本一に貢献した。この頃に[[カット・ファスト・ボール|カットボール]]を習得し、投球の幅が広がった。\n\n[[2004年]]は前年の疲労があったのか13試合の登板に終わったが、防御率は1点台だった。\n\n[[2005年]]は[[2005年のオールスターゲーム (日本プロ野球)|オールスターゲーム]]に監督推薦で初出場を果たした。シーズンではリーグ2位の61試合に登板し、6月にリーグ新記録となる8試合連続ホールドを記録し<ref>{{Cite book|和書|year=2005|title=応援ありがとう!2005福岡ソフトバンクホークス激闘の軌跡 |publisher=ソフトバンククリエイティブ |pages=82頁|id=ISBN 4-7973-3331-6}}</ref>、最終的に32ホールドを記録し、チーム勝率1位に貢献した。\n\n翌年[[2006年]]も60試合に登板し、20ホールドをマークするなど、貴重な中継ぎとして活躍した。[[12月10日]]、[[フリーエージェント (日本プロ野球)|FA宣言]]でホークスへ復帰した[[小久保裕紀]]の人的補償選手として[[読売ジャイアンツ]]へ移籍した。\n=== 巨人時代 ===\n\n移籍1年目の[[2007年]]は開幕第3戦の[[横浜DeNAベイスターズ|横浜ベイスターズ]]戦([[横浜スタジアム]])で移籍後初登板するが1失点すると、これまでの活躍によって肩の勤続疲労に悩まされていたこともあり、登録を抹消された。その後は2軍で再調整を兼ねた登板を続けた。8月1日に1軍昇格。敗戦処理から徐々に信頼を上げ好投を続けた。8月25日の[[広島東洋カープ]]戦で5-4の1点ビハインドから[[金刃憲人]]をリリーフ、6回裏を3者凡退に抑えると7回表に巨人が逆転。続く7回も無失点に抑え、巨人での初勝利を挙げた。この年は防御率1.89であったが、前半戦は2軍生活だったこともあり、16試合の登板にとどまった。\n\n[[2008年]]は前年同様開幕1軍だったものの、開幕第3戦の3月30日の[[東京ヤクルトスワローズ]]戦で勝ち越し点を与えるなど不安定で序盤の3試合の登板しただけで4月10日に1軍登録抹消された。その後は1軍登板することなくシーズンを終えた。オフに[[戦力外通告]]を受けた。その後現役を引退した。\n\n=== 引退後 ===\n\n引退後は巨人の[[打撃投手]]に転向。[[2011年]]からスカウト<ref name="shuube20140324_P20">週刊ベースボール2014年3月24日号 P20</ref>。\n\n== プレースタイル ==\n[[カット・ファスト・ボール|カットボール]]、[[シュートボール|シュート]]、[[フォークボール|フォーク]]を使ってベースの四隅を突くピッチングが特徴<ref>{{Cite book|和書|year=2006|title=福岡ソフトバンクホークス激闘の軌跡2006 |publisher=福岡ソフトバンクホークスマーケティング |pages=85頁|id=ISBN 4-7973-3840-7}}</ref>。\n\n== 詳細情報 ==\n=== 年度別投手成績 ===\n{| {{投手成績|リーグ=日本プロ野球}}\n|-\n|style="text-align: center;"|{{by2|1995}}\n|rowspan="11" style="text-align:center; white-space:nowrap;"|[[福岡ソフトバンクホークス|ダイエー<br />ソフトバンク]]\n||24||11||1||0||0||5||5||0||--||.500||352||82.0||78||13||35||1||2||38||5||'''2'''||43||39||4.28||1.38\n|-\n|style="text-align: center;"|{{by2|1996}}\n||35||16||6||1||0||4||13||1||--||.235||599||141.1||136||14||48||5||7||83||3||0||59||54||3.44||1.30\n|-\n|style="text-align: center;"|{{by2|1997}}\n||18||15||7||2||'''4'''||7||7||0||--||.500||438||109.1||97||13||22||0||1||76||0||0||44||43||3.54||1.09\n|-\n|style="text-align: center;"|{{by2|1998}}\n||15||11||2||1||0||5||4||0||--||.556||332||74.2||89||7||23||1||4||24||2||1||42||38||4.58||1.50\n|-\n|style="text-align: center;"|{{by2|1999}}\n||8||2||0||0||0||1||1||0||--||.500||84||18.2||30||2||3||0||0||9||1||0||18||15||7.23||1.77\n|-\n|style="text-align: center;"|{{by2|2001}}\n||18||0||0||0||0||0||1||0||--||.000||100||22.2||29||6||7||0||0||21||1||0||14||14||5.56||1.59\n|-\n|style="text-align: center;"|{{by2|2002}}\n||6||0||0||0||0||0||0||0||--||----||35||7.2||9||2||2||0||1||9||0||0||9||3||3.52||1.43\n|-\n|style="text-align: center;"|{{by2|2003}}\n||42||0||0||0||0||1||3||1||--||.250||189||44.2||45||3||13||2||2||34||0||0||22||22||4.43||1.30\n|-\n|style="text-align: center;"|{{by2|2004}}\n||13||0||0||0||0||0||0||2||--||----||58||14.2||13||2||2||0||1||10||0||1||3||3||1.84||1.02\n|-\n|style="text-align: center;"|{{by2|2005}}\n||61||0||0||0||0||2||4||1||32||.333||252||66.1||70||2||19||4||3||49||0||0||24||23||3.12||1.34\n|-\n|style="text-align: center;"|{{by2|2006}}\n||60||0||0||0||0||3||2||0||20||.600||288||65.2||70||4||20||0||3||36||0||0||24||22||3.02||1.37\n|-\n|style="text-align: center;"|{{by2|2007}}\n|rowspan="2" style="text-align:center;"|[[読売ジャイアンツ|巨人]]\n||16||0||0||0||0||2||0||0||0||1.000||71||19.0||12||1||5||1||0||11||0||1||4||4||1.89||0.89\n|-\n|style="text-align: center;"|{{by2|2008}}\n||3||0||0||0||0||0||1||0||0||.000||13||2.1||4||0||2||0||0||2||0||0||3||3||11.57||2.57\n|-\n!colspan="2"|通算：13年\n||319||55||16||4||4||30||41||5||52||.423||2844||669.0||682||69||201||14||24||402||12||5||309||283||3.81||1.32\n|}\n* 各年度の'''太字'''はリーグ最高\n\n=== 表彰 ===\n* [[月間MVP (日本プロ野球)|月間MVP]]：1回（1997年6月）\n\n=== 記録 ===\n* 初登板・初先発・初勝利：1995年4月6日、対[[千葉ロッテマリーンズ]]3回戦（[[千葉マリンスタジアム]]）、5回2/3を2失点\n* 初奪三振：同上、1回裏に[[安藤学]]から\n* 初完投勝利：1995年7月12日、対[[埼玉西武ライオンズ|西武ライオンズ]]12回戦（[[福岡ドーム]]）、9回2失点\n* 初完封勝利：1996年5月22日、対西武ライオンズ12回戦（[[西武ドーム|西武ライオンズ球場]]）\n* 初セーブ：1996年9月7日、対[[北海道日本ハムファイターズ|日本ハムファイターズ]]25回戦（[[東京ドーム]]）、9回裏1死に7番手として救援登板・完了、2/3回無失点\n* 初ホールド：2005年3月30日、対[[東北楽天ゴールデンイーグルス]]3回戦（福岡Yahoo! JAPANドーム）、6回表2死に3番手として救援登板、2回1/3を無失点\n* 最高年俸：6800万(推定)\n* [[オールスターゲーム (日本プロ野球)|オールスターゲーム]]出場：1回（2005年）\n\n=== 背番号 ===\n* '''37''' （1994年 - 1994年途中）\n* '''67''' （1994年途中 - 1996年）\n* '''34''' （1997年 - 2006年）\n* '''39''' （2007年 - 2008年）\n* '''122''' （2009年）\n* '''008''' （2010年）\n\n== 脚注 ==\n<references />\n\n== 関連項目 ==\n* [[大分県出身の人物一覧]]\n* [[福岡ソフトバンクホークスの選手一覧]]\n* [[読売ジャイアンツの選手一覧]]\n* [[死球#危険球|危険球]] - 現在の規則で退場者パシフィック第1号\n* [[苺みるく]] - 現役時代に交際していた\n\n== 外部リンク ==\n{{NPB|11213889}}\n\n{{福岡ダイエーホークス1993年ドラフト指名選手}}\n\n{{DEFAULTSORT:よしたけ しんたろう}}\n[[Category:日本の野球選手]]\n[[Category:福岡ソフトバンクホークス及びその前身球団の選手]]\n[[Category:読売ジャイアンツ及び東京巨人軍の選手]]\n[[Category:日本の打撃投手]]\n[[Category:大分県出身の人物]]\n[[Category:1975年生]]\n[[Category:存命人物]]	</BODY>
  <MECAB>吉武真太郎  ''' 吉武 真太郎 '''（ よし た け しんたろう 、 [[ 1975年 ]][[ 6月3日 ]]< ref name =" meikan 2008 "></ ref > - ） は 、 [[ 大分県 ]][[ 東国東郡 ]][[ 国見町 ( 大分県 )| 国見町 ]]（ 現 ：[[ 国東市 ]]） 出身 の 元 [[ プロ野球選手 ]]（[[ 投手 ]]）。 現在 は 、 [[ 読売ジャイアンツ ]] の [[ スカウト ( 勧誘 )| スカウト ]]。 
[[ 大分県立国東高等学校 | 国東 高校 ]] 野球部 在籍 時代 に は プロ に は 興味 が なく 、 教員 志望 だっ た 。 ドラフト 当日 も 自転車 で 帰宅 し 、 指名 を 知っ た 監督 が 追いかけ て 来 た 程 だっ た < ref name =" ベースボールマガジン 2月 9 - 16日 "> 雑誌 「 週刊ベースボール 」 （ ベースボールマガジン社 刊 ） 2009年 2月 9 & 16日 号 43 - 47 ページ 「 惜別 球人 吉武 真太郎 」</ ref >。[[ 1993年 ]]、 ドラフト 4位 で [[ 福岡ソフトバンクホークス | 福岡 ダイエーホークス ]] に 指名 さ れ 入団 < ref name =" meikan 2008 " />。 
入団1年目 の [[ 1994年 ]] は 1軍 登録 は なく 2軍 で も 未 勝利 に 終わっ た 。 しかし 秋 の 教育リーグ で 投球 の コツ を つかん だ 。 
2年目 の [[ 1995年 ]] 春 の キャンプ で は [[ 村田 兆治 ]] コーチ の 指導 を 受けて 才能 が 開花 < ref name =" ベースボールマガジン 2月 9 - 16日 " />。 この 年 は 24試合 に 登板 し 、 先発 として は 11試合 に 登板 し た 。 最終的 に 5勝 5敗 、 防御率 4 . 28 の 成績 を 残し た 。 
[[ 1996年 ]] も 先発 と [[ 中継ぎ ]] の 両方 で 起用 さ れ 、 35試合 に 登板 し た が 、 4勝 13敗 1 セーブ と 不本意 な 成績 で 終わっ た が 、 防御率 は 3 . 44 と 前年 より 良 化 し た 。 
4年目 の [[ 1997年 ]] に は ''' 3試合 連続 無 [[ 四球 ]][[ 完投 ]] 勝利 で 6月 の 月間MVP ''' に 選ば れる など 、 7勝 7敗 の 成績 を 残す 見せ た 。 
将来 を 嘱望 さ れる 若手 投手 で あっ た が 、 翌年 [[ 1998年 ]] は 5勝 止まり で 終わっ て しまい 、 防御率 も 4点 台 と 再び 悪化 し た 。 
チーム が リーグ優勝 を 飾っ た [[ 1999年 ]] は わずか 1勝 に 終わっ て しまっ た 。 
[[ 2000年 ]] は 1軍 登板 なし で シーズン を 終了 し た 。 一方 で チーム は 日本一 は 逃し た ものの 、 リーグ連覇 を 達成 し た 。 
[[ 2001年 ]] から は チーム の 先発 陣 が 安定 し て き た こと も あり [[ リリーフ ]] に 転向 。 同年 は 18試合 に 登板 する も 、 防御率 5 . 56 と 安定感 を 欠い た 。 
[[ 2002年 ]] は わずか 6試合 の 登板 に 終わっ た 。 
[[ 2003年 ]] は 才能 が 開花 し 、 自身 最多 の 42試合 に 登板 し た 。 防御率 4 . 43 と 安定感 は 欠い た ものの 貴重 な リリー バー として チーム 3年ぶり の リーグ優勝 と 日本一 に 貢献 し た 。 この 頃 に [[ カット・ファスト・ボール | カットボール ]] を 習得 し 、 投球 の 幅 が 広がっ た 。 
[[ 2004年 ]] は 前年 の 疲労 が あっ た の か 13試合 の 登板 に 終わっ た が 、 防御率 は 1点 台 だっ た 。 
[[ 2005年 ]] は [[ 2005年 の オールスターゲーム ( 日本プロ野球 )| オールスターゲーム ]] に 監督 推薦 で 初 出場 を 果たし た 。 シーズン で は リーグ2 位 の 61試合 に 登板 し 、 6月 に リーグ 新 記録 と なる 8試合 連続 ホールド を 記録 し < ref ></ ref >、 最終的 に 32 ホールド を 記録 し 、 チーム 勝率 1位 に 貢献 し た 。 
翌年 [[ 2006年 ]] も 60試合 に 登板 し 、 20 ホールド を マーク する など 、 貴重 な 中継ぎ として 活躍 し た 。 [[ 12月10日 ]]、[[ フリーエージェント ( 日本プロ野球 )| FA宣言 ]] で ホークス へ 復帰 し た [[ 小久保裕紀 ]] の 人的補償 選手 として [[ 読売ジャイアンツ ]] へ 移籍 し た 。 
移籍 1年目 の [[ 2007年 ]] は 開幕 第3戦 の [[ 横浜DeNAベイスターズ | 横浜ベイスターズ ]] 戦 ([[ 横浜 スタジアム ]]) で 移籍後 初 登板 する が 1失点 する と 、 これ まで の 活躍 によって 肩 の 勤続 疲労 に 悩まさ れ て い た こと も あり 、 登録 を 抹消 さ れ た 。 その後 は 2軍 で 再 調整 を 兼ね た 登板 を 続け た 。 8月1日 に 1軍 昇格 。 敗戦処理 から 徐々に 信頼 を 上げ 好投 を 続け た 。 8月25日 の [[ 広島東洋カープ ]] 戦 で 5 - 4 の 1点 ビハインド から [[ 金刃 憲人 ]] を リリーフ 、 6回 裏 を 3 者 凡退 に 抑える と 7回 表 に 巨人 が 逆転 。 続く 7回 も 無 失点 に 抑え 、 巨人 で の 初 勝利 を 挙げ た 。 この 年 は 防御率 1 . 89 で あっ た が 、 前半 戦 は 2軍 生活 だっ た こと も あり 、 16試合 の 登板 に とどまっ た 。 
[[ 2008年 ]] は 前年 同様 開幕 1軍 だっ た ものの 、 開幕 第3戦 の 3月30日 の [[ 東京ヤクルトスワローズ ]] 戦 で 勝ち越し点 を 与える など 不安定 で 序盤 の 3試合 の 登板 し た だけ で 4月10日 に 1軍 登録 抹消 さ れ た 。 その後 は 1軍 登板 する こと なく シーズン を 終え た 。 オフ に [[ 戦力外通告 ]] を 受け た 。 その後 現役 を 引退 し た 。 
引退後 は 巨人 の [[ 打撃投手 ]] に 転向 。 [[ 2011年 ]] から スカウト < ref name =" shuube 20140324 _ P2 0 "> 週刊ベースボール 2014年 3月24日 号 P2 0 </ ref >。 
[[ カット・ファスト・ボール | カットボール ]]、[[ シュート ボール | シュート ]]、[[ フォークボール | フォーク ]] を 使っ て ベース の 四隅 を 突く ピッチング が 特徴 < ref ></ ref >。 </MECAB>
  <ID>287124</ID><LATESTID>59163359</LATESTID><NAMESPACE>0</NAMESPACE><RESTRICTIONS>move=:edit=</RESTRICTIONS><ISREDIRECT>0</ISREDIRECT><ISNEW>0</ISNEW><RANDOM>1</RANDOM><TOUCHED>0.73202639445662498</TOUCHED><LINKSUPDATED>20160331030749</LINKSUPDATED><LEN>11494</LEN><CONTENTMODEL></CONTENTMODEL><LANG></LANG></ITEM>
