<ITEM>
  <TITEL>小田急30000形電車</TITLE>
  <META>{{鉄道車両n|車両名 =小田急30000形電車<br/><small>Excellent Express</small>n|社色 =#BE0032 <!--アッパーレッド 鉄道ピクトリアル通巻829号（2010年1月号臨時増刊）「特集・小田急電鉄」p191の表から色を抽出-->n|画像 =Odakyu Erectric Railway 30000.jpgn|pxl =300pxn|画像説明 =30000形EXE車<br/>（2007年12月9日、開成駅 - 栢山駅間）n|unit = selfn|編成 =4両固定編成<ref name="rp679-239"/>・6両固定編成<ref name="rp679-239"/>n|起動加速度 =2.0km/h/s<ref name="rf421-64"/>n|営業最高速度 =110km/hn|設計最高速度 =120km/h<ref name="rf421-64"/>n|最高速度 =n|定格速度 =n|減速度（常用最大）=（初速100km/h）3.5km/h/s<ref name="rf421-64"/>（常用最大）<br/>（初速60km/h）4.0km/h/s<ref name="rf421-64"/>n|減速度（非常） =（初速100km/h）4.0km/h/s<ref name="rf421-64"/>（非常）<br/>（初速60km/h）4.5km/h/s<ref name="rf421-64"/>n|編成定員 =588名（4両固定編成+6両固定編成）<ref name="2005-u-167"/>n|車両定員 =n|編成長 =199.500[[メートル|m]]（4両固定編成+6両固定編成）<ref name="2005-u-167"/>n|最大寸法 =19,750[[ミリメートル|mm]]×2,900mm×4,050mm（非貫通型先頭車）<ref name="rp829-317"/><br/>20,000mm×2,900mm×4,050mm（貫通型先頭車）<ref name="rp829-317"/><br/>20,000mm×2,900mm×4,065mm（集電装置付中間車）<ref name="rp829-317"/><br/>20,000mm×2,900mm×4,050mm（集電装置無し中間車）<ref name="rp829-317"/>n|全長 =n|全幅 =n|全高 =n|車体長 =n|車体幅 =n|車体高 =n|編成質量 =376.7[[トン|t]]（4両固定編成+6両固定編成）<ref name="2005-u-167"/>n|車両質量 =n|軸配置 =n|軌間 =1,067 mmn|電気方式 =[[直流電化|直流]]1,500V<br/>（[[架空電車線方式]]）n|出力 =n|主電動機 =[[東洋電機製造]] TDK6335-A<ref name="rp829-317"/><br/>[[三菱電機]] MB-5065-A<ref name="rp829-317"/><br/>[[かご形三相誘導電動機]]<ref name="rp829-317"/>n|モーター出力 =195[[ワット|kW]]<ref name="rp829-317"/>n|機関出力 =n|編成出力 =n|定格出力 =n|定格引張力 =n|駆動装置 =[[TD平行カルダン駆動方式]]<ref name="rp679-241"/><br/>（中実軸撓み板継手方式）n|歯車比 =98:15=6.53<ref name="rp829-317"/>n|変速段 =n|台車 =[[住友金属工業]] SS146（電動台車）<ref name="rp829-317"/><br/>住友金属工業 SS046（付随台車）<ref name="rp829-317"/>n|制御装置 =[[東芝]] SVF-024A（4両固定編成）<ref name="rp829-317"/><br/>東芝 SVF-024B（6両固定編成）<ref name="rp829-317"/><br/>[[絶縁ゲートバイポーラトランジスタ|IGBT]]-[[可変電圧可変周波数制御|VVVFインバータ制御]]n|ブレーキ方式 =[[電力回生ブレーキ|回生制動]]併用[[電気指令式ブレーキ|電気指令電気演算式]][[電磁直通ブレーキ|電磁直通制動]] (MBSA-R) <ref name="rp679-241"/>n|保安装置 =[[自動列車停止装置#多変周式信号ATS（多変周式（点制御、連続照査型））|OM-ATS]], [[自動列車停止装置#D-ATS-P（デジタルATS-P）形|D-ATS-P]]n|製造メーカー =[[日本車輌製造]]<ref name="rp829-306"/>・[[川崎重工業車両カンパニー|川崎重工業]]<ref name="rp829-306"/>n|備考 =n|備考全幅 =n}}{{Double image aside|right|Odakyu30000-1.JPG|180|Odakyu30000-2.JPG|180|非貫通型|貫通型}}{{Triple image|right|OER-EXE30000-inside.jpg|133|Counter of Odakyu RomanceCar EXE.JPG|77|OER 30100 inside service counter.jpg|133|客室|売店のショーケース|売店のカウンター}}{{Double image aside|right|OER 30150 inside cab.jpg|180|OER-30000-Coupling.jpg|180|貫通型の運転台|「自動ほろ装置」により接続された中間の運転台}}{{Cite web|author=鉄道友の会|url=http://www.jrc.gr.jp/award/bl/bl1997.htm|title=1997年 ブルーリボン・ローレル賞選定車両|work=|publisher=|language=日本語|accessdate=2011-10-10}}{{cite conference |url=http://warp.ndl.go.jp/info:ndljp/pid/283520/www.soumu.go.jp/joho_tsusin/policyreports/joho_tsusin/joho_bukai/pdf/020412_1_4.pdf |title=無線LANを用いたモバイル・インターネットサービスの研究開発 平成13年度の活動について |author= ノキア・ジャパン|authorlink= |coauthors= |date=2002-04-12 |publisher= |booktitle= |page=7 |location= |id= }}{{Cite web|author=[http://www.g-mark.org/ 日本デザイン振興会]|url=http://www.g-mark.org/award/detail.html?id=23365&lang=ja|title=Good Design Award|work=|publisher=|language=日本語|accessdate=2011-10-10}}{{TrainDirection|[[箱根湯本駅|箱根湯本]]・[[小田原駅|小田原]]|[[新宿駅|新宿]]}}{{TrainDirection|[[小田原駅|小田原]]・[[藤沢駅|藤沢]]|[[新宿駅|新宿]]・[[片瀬江ノ島駅|片瀬江ノ島]]}}{{脚注ヘルプ}}{{Reflist|group="注釈"}}{{Reflist|2|refs=n<ref name="dj145-15">[[#DJ145|『鉄道ダイヤ情報』通巻145号 p.15]]</ref>n<ref name="dj145-31">[[#DJ145|『鉄道ダイヤ情報』通巻145号 p.31]]</ref>n<ref name="dj145-34">[[#DB145|『鉄道ダイヤ情報』通巻145号 p.34]]</ref>n<ref name="dj145-42">[[#開発145|『鉄道ダイヤ情報』通巻145号 p.42]]</ref>n<ref name="dj145-43">[[#開発145|『鉄道ダイヤ情報』通巻145号 p.43]]</ref>n<ref name="dj145-44">[[#開発145|『鉄道ダイヤ情報』通巻145号 p.44]]</ref>n<ref name="2002-o-32">[[#大幡2002|大幡 (2002) p.32]]</ref>n<ref name="2005-u-167">[[#生方2005|生方 (2005) p.167]]</ref>n<ref name="2005-u-58">[[#生方2005|生方 (2005) p.58]]</ref>n<ref name="2005-u-59">[[#生方2005|生方 (2005) p.59]]</ref>n<ref name="2005-u-61">[[#生方2005|生方 (2005) p.61]]</ref>n<ref name="rf421-55">[[#飯塚421|『鉄道ファン』通巻421号 p.55]]</ref>n<ref name="rf421-56">[[#飯塚421|『鉄道ファン』通巻421号 p.56]]</ref>n<ref name="rf421-5657">[[#飯塚421|『鉄道ファン』通巻421号 pp.56-57]]</ref>n<ref name="rf421-57">[[#飯塚421|『鉄道ファン』通巻421号 p.57]]</ref>n<ref name="rf421-58">[[#飯塚421|『鉄道ファン』通巻421号 p.58]]</ref>n<ref name="rf421-5859">[[#飯塚421|『鉄道ファン』通巻421号 pp.58-59]]</ref>n<ref name="rf421-59">[[#飯塚421|『鉄道ファン』通巻421号 p.59]]</ref>n<ref name="rf421-60">[[#飯塚421|『鉄道ファン』通巻421号 p.60]]</ref>n<ref name="rf421-61">[[#飯塚421|『鉄道ファン』通巻421号 p.61]]</ref>n<ref name="rf421-6162">[[#飯塚421|『鉄道ファン』通巻421号 pp.61-62]]</ref>n<ref name="rf421-63">[[#飯塚421|『鉄道ファン』通巻421号 p.63]]</ref>n<ref name="rf421-64">[[#飯塚421|『鉄道ファン』通巻421号 p.64]]</ref>n<ref name="rf421-64">[[#飯塚421|『鉄道ファン』通巻421号 p.64]]</ref>n<ref name="rf421-RF22405">[[#飯塚421|『鉄道ファン』通巻421号付図 (RF22405) ]]</ref>n<ref name="rf421-RF22407">[[#飯塚421|『鉄道ファン』通巻421号付図 (RF22407) ]]</ref>n<ref name="rf422-23">[[#RF422|『鉄道ファン』通巻422号 p.23]]</ref>n<ref name="rf422-23">[[#RF422|『鉄道ファン』通巻422号 p.23]]</ref>n<ref name="rj464-33">[[#RJ464|『鉄道ジャーナル』通巻464号 p.33]]</ref>n<ref name="rj464-34">[[#RJ464|『鉄道ジャーナル』通巻464号 p.34]]</ref>n<ref name="rp679-239">[[#大幡679|『鉄道ピクトリアル』通巻679号 p.239]]</ref>n<ref name="rp679-240">[[#大幡679|『鉄道ピクトリアル』通巻679号 p.240]]</ref>n<ref name="rp679-240241">[[#大幡679|『鉄道ピクトリアル』通巻679号 pp.240-241]]</ref>n<ref name="rp679-241">[[#大幡679|『鉄道ピクトリアル』通巻679号 p.241]]</ref>n<ref name="rp679-242">[[#大幡679|『鉄道ピクトリアル』通巻679号 p.242]]</ref>n<ref name="rp679-39">[[#草門679|『鉄道ピクトリアル』通巻679号 p.39]]</ref>n<ref name="rp829-190">[[#中山829|『鉄道ピクトリアル』通巻829号 p.190]]</ref>n<ref name="rp829-210">[[#杉田829|『鉄道ピクトリアル』通巻829号 p.210]]</ref>n<ref name="rp829-212">[[#杉田829|『鉄道ピクトリアル』通巻829号 p.212]]</ref>n<ref name="rp829-217">[[#杉田829|『鉄道ピクトリアル』通巻829号 p.217]]</ref>n<ref name="rp829-280">[[#岸上829|『鉄道ピクトリアル』通巻829号 p.280]]</ref>n<ref name="rp829-281">[[#岸上829|『鉄道ピクトリアル』通巻829号 p.281]]</ref>n<ref name="rp829-282">[[#岸上829|『鉄道ピクトリアル』通巻829号 p.282]]</ref>n<ref name="rp829-306">[[#岸上829-1|『鉄道ピクトリアル』通巻829号 p.306]]</ref>n<ref name="rp829-317">[[#岸上829-2|『鉄道ピクトリアル』通巻829号 p.317]]</ref>n}}{{Cite book|和書|author = 生方良雄|authorlink = |coauthors = |year = 2005|title = 小田急ロマンスカー総覧|publisher = 大正出版|ref = 生方2005|id = |isbn = 4811706552}}{{Cite book|和書|author = 大幡哲海|authorlink = |coauthors = |year = 2002|title = 小田急電鉄の車両|publisher = [[JTBパブリッシング]]|ref = 大幡2002|id = |isbn = 4533044697}}{{Cite journal|和書|author=飯塚豊彦 |year=1996 |month=5 |title=小田急30000形 |journal=[[鉄道ファン (雑誌)|鉄道ファン]] |issue=421 |pages= 54-64 |publisher=[[交友社]] |ref = 飯塚421}}{{Cite journal|和書|author=大幡哲海 |year=1999 |month=12 |title=私鉄車両めぐり164 小田急電鉄 |journal=鉄道ピクトリアル |issue=679 |pages= 201-243 |publisher=電気車研究会 |ref = 大幡679}}{{Cite journal|和書|author=岸上明彦 |year=2010 |month=1 |title=小田急電鉄現有車両プロフィール |journal=鉄道ピクトリアル |issue= 829|pages= 241-295 |publisher=電気車研究会 |ref = 岸上829}}{{Cite journal|和書|author=岸上明彦 |year=2010 |month=1 |title=小田急電鉄 車歴表 |journal=鉄道ピクトリアル |issue=829 |pages= 300-309 |publisher=電気車研究会 |ref = 岸上829-1}}{{Cite journal|和書|author=岸上明彦 |year=2010 |month=1 |title=小田急電鉄 主要諸元表 |journal=鉄道ピクトリアル |issue=829 |pages= 310-318 |publisher=電気車研究会 |ref = 岸上829-2}}{{Cite journal|和書|author=草門隆 |year=1999 |month=12 |title=車両総説 |journal=鉄道ピクトリアル |issue=679 |pages= 36-41 |publisher=電気車研究会 |ref = 草門679 }}{{Cite journal|和書|author=杉田弘志 |year=2010 |month=1 |title=小田急電鉄 列車運転の変遷とその興味 |journal=鉄道ピクトリアル|issue=829 |pages= 204-219 |publisher=電気車研究会 |ref = 杉田829}}{{Cite journal|和書|author=鶴通孝・山﨑友也 |year=2005 |month=6 |title=列車追跡シリーズ548 何度でも乗ってみたい特急ロマンスカー わくわくの85分 |journal=[[鉄道ジャーナル]] |issue=464 |pages= 25-35 |publisher=鉄道ジャーナル社 |ref = RJ464}}{{Cite journal|和書|author=中山嘉彦 |year=2010 |month=1 |title=小田急車両 -音と色- |journal= 鉄道ピクトリアル|issue=829 |pages= 189-191 |publisher=電気車研究会 |ref = 中山829}}{{Cite journal|和書|author= |year=1996 |month=5 |title=EXE 115DAYS |journal=[[鉄道ダイヤ情報]] |issue=145 |pages= 14-32 |publisher=[[交通新聞社|弘済出版社]] |ref = DJ145}}{{Cite journal|和書|author= |year=1996 |month=5 |title=小田急DATA BANK |journal= 鉄道ダイヤ情報|issue=145 |pages= 33-41 |publisher= 弘済出版社|ref = DB145}}{{Cite journal|和書|author= |year=1996 |month=5 |title=開発担当者 EXEを語る |journal= 鉄道ダイヤ情報|issue=145 |pages= 42-48 |publisher= 弘済出版社|ref = 開発145}}{{Cite journal|和書|author= |year=1996 |month=5 |title=小田急ロマンスカー |journal=鉄道ファン |issue=422 |pages= 8-29 |publisher=交友社 |ref = RF422}}{{Commonscat|Odakyu 30000 series EXE}}{{小田急ロマンスカー}}{{小田急電鉄の車両}}{{DEFAULTSORT:おたきゆう30000かたてんしや}}</META>
  <DESCRIPTION>	{{鉄道車両\n|車両名 =小田急30000形電車<br/><small>Excellent Express</small>\n|社色 =#BE0032 <!--アッパーレッド 鉄道ピクトリアル通巻829号（2010年1月号臨時増刊）「特集・小田急電鉄」p191の表から色を抽出-->\n|画像 =Odakyu Erectric Railway 30000.jpg\n|pxl =300px\n|画像説明 =30000形EXE車<br/>（2007年12月9日、開成駅 - 栢山駅間）\n|unit = self\n|編成 =4両固定編成<ref name="rp679-239"/>・6両固定編成<ref name="rp679-239"/>\n|起動加速度 =2.0km/h/s<ref name="rf421-64"/>\n|営業最高速度 =110km/h\n|設計最高速度 =120km/h<ref name="rf421-64"/>\n|最高速度 =\n|定格速度 =\n|減速度（常用最大）=（初速100km/h）3.5km/h/s<ref name="rf421-64"/>（常用最大）<br/>（初速60km/h）4.0km/h/s<ref name="rf421-64"/>\n|減速度（非常） =（初速100km/h）4.0km/h/s<ref name="rf421-64"/>（非常）<br/>（初速60km/h）4.5km/h/s<ref name="rf421-64"/>\n|編成定員 =588名（4両固定編成+6両固定編成）<ref name="2005-u-167"/>\n|車両定員 =\n|編成長 =199.500[[メートル|m]]（4両固定編成+6両固定編成）<ref name="2005-u-167"/>\n|最大寸法 =19,750[[ミリメートル|mm]]×2,900mm×4,050mm（非貫通型先頭車）<ref name="rp829-317"/><br/>20,000mm×2,900mm×4,050mm（貫通型先頭車）<ref name="rp829-317"/><br/>20,000mm×2,900mm×4,065mm（集電装置付中間車）<ref name="rp829-317"/><br/>20,000mm×2,900mm×4,050mm（集電装置無し中間車）<ref name="rp829-317"/>\n|全長 =\n|全幅 =\n|全高 =\n|車体長 =\n|車体幅 =\n|車体高 =\n|編成質量 =376.7[[トン|t]]（4両固定編成+6両固定編成）<ref name="2005-u-167"/>\n|車両質量 =\n|軸配置 =\n|軌間 =1,067 mm\n|電気方式 =[[直流電化|直流]]1,500V<br/>（[[架空電車線方式]]）\n|出力 =\n|主電動機 =[[東洋電機製造]] TDK6335-A<ref name="rp829-317"/><br/>[[三菱電機]] MB-5065-A<ref name="rp829-317"/><br/>[[かご形三相誘導電動機]]<ref name="rp829-317"/>\n|モーター出力 =195[[ワット|kW]]<ref name="rp829-317"/>\n|機関出力 =\n|編成出力 =\n|定格出力 =\n|定格引張力 =\n|駆動装置 =[[TD平行カルダン駆動方式]]<ref name="rp679-241"/><br/>（中実軸撓み板継手方式）\n|歯車比 =98:15=6.53<ref name="rp829-317"/>\n|変速段 =\n|台車 =[[住友金属工業]] SS146（電動台車）<ref name="rp829-317"/><br/>住友金属工業 SS046（付随台車）<ref name="rp829-317"/>\n|制御装置 =[[東芝]] SVF-024A（4両固定編成）<ref name="rp829-317"/><br/>東芝 SVF-024B（6両固定編成）<ref name="rp829-317"/><br/>[[絶縁ゲートバイポーラトランジスタ|IGBT]]-[[可変電圧可変周波数制御|VVVFインバータ制御]]\n|ブレーキ方式 =[[電力回生ブレーキ|回生制動]]併用[[電気指令式ブレーキ|電気指令電気演算式]][[電磁直通ブレーキ|電磁直通制動]] (MBSA-R) <ref name="rp679-241"/>\n|保安装置 =[[自動列車停止装置#多変周式信号ATS（多変周式（点制御、連続照査型））|OM-ATS]], [[自動列車停止装置#D-ATS-P（デジタルATS-P）形|D-ATS-P]]\n|製造メーカー =[[日本車輌製造]]<ref name="rp829-306"/>・[[川崎重工業車両カンパニー|川崎重工業]]<ref name="rp829-306"/>\n|備考 =\n|備考全幅 =\n}}\n'''小田急30000形電車'''（おだきゅう30000がたでんしゃ）は、[[1996年]]に[[小田急電鉄]]（小田急）が運用を開始した<ref name="rp679-39"/>[[特急形車両|特急用車両]]<!--小田急では「特急形」という区分ではないため。2300形の登場当時は竣功図に「優等電動客車」というように書いてあるようですが-->（[[小田急ロマンスカー|ロマンスカー]]）である。\n\n特急ロマンスカーに使用されていた[[小田急3100形電車|3100形（NSE車）]]の置き換えを目的として登場した<ref name="rp829-280"/>特急車両で、特急ロマンスカーの利用実態の変化に対応し<ref name="rp679-239"/>、単位輸送力の増強を行った上で<ref name="rp679-239"/>、観光輸送だけではなくビジネス利用を強く意識した車両とした<ref name="rp679-39"/>。また、小田急の特急車両では初めて[[可変電圧可変周波数制御|VVVFインバータ制御]]を採用した<ref name="rp829-280"/>。 "Excellent Express" を略して「EXE（エクセ）」という愛称が設定され、1996年には当時の[[通商産業省]]より[[グッドデザイン賞|グッドデザイン商品]]に選定された<ref name="rp829-280"/>。[[鉄道友の会]]に[[ブルーリボン賞 (鉄道)|ブルーリボン賞]]の制度が創設されて以来、小田急の特急車両で唯一ブルーリボン賞を受賞していない車両である<ref name="2005-u-61"/>。\n\n小田急では、編成表記の際には「[[新宿駅|新宿]]寄り先頭車両の[[鉄道の車両番号|車両番号]]（新宿方の車号）×両数」という表記を使用している<ref name="dj145-15"/>ため、本項もそれに倣い、特定の編成を表記する際には「30051×4」「30251×6」のように表記する。また、[[小田急3100形電車|3100形]]は「NSE車」、[[小田急7000形電車|7000形]]は「LSE車」、[[小田急10000形電車|10000形]]は「HiSE車」、本形式30000形は「EXE車」、[[箱根登山鉄道]][[箱根湯本駅]]へ乗り入れる特急列車については「箱根特急」と表記する。\n\n== 登場の経緯 ==\n小田急の特急ロマンスカーはもともと[[箱根町|箱根]]への観光客が対象であり<ref name="2005-u-58"/>、箱根特急の途中駅停車も元来は沿線在住の箱根観光客を対象としたものであった<ref name="2005-u-58"/>。しかし、時代の進展とともに利用実態は変化し、観光客以外の日常利用が増加していた<ref name="2005-u-58"/>ほか、1967年より[[回送]]列車を客扱いすることから始まった通勤用の特急列車の利用者数も増加しており<ref name="2005-u-58"/>、輸送力が不足していた<ref name="dj145-42"/>。一方で、NSE車は更新修繕などが行なわれてはいたものの車齢30年を超えており<ref name="rp679-239"/>、代替の車両について検討が行なわれていた<ref name="rp679-239"/>。\n\nこのため、NSE車を置き換えると同時に、変化した利用実態に対応した車両を製作することになった<ref name="rp679-239"/>。設計に際しては、小田急や車両メーカーのほかに[[小田急百貨店]]のインテリアデザイナーや外部のグラフィックデザイナーも交えて検討が行なわれた<ref name="dj145-44"/>。検討過程では[[ボギー台車|ボギー車]]の方が定員増が可能であると判断され<ref name="dj145-42"/>、[[連接台車|連接構造]]は採用されなかった<ref name="dj145-42"/>。また、[[増解結|分割・併合]]を行なう際に通り抜け可能な貫通路を設けることとした<ref name="dj145-43"/>が、この構造では前面[[展望車|展望席]]の設置は困難であること<ref name="dj145-42"/>や、乗務員交代が短時間で可能なことを考慮し<ref name="dj145-42"/>、前面展望席は採用されないことになった<ref name="dj145-42"/>。\n\nこうして、それまでの特急ロマンスカーとは一線を画す特急車両として<ref name="rf421-56"/>登場したのがEXE車である。\n\n== 車両概説 ==\n本節では、登場当時の仕様を基本として、増備途上での変更点を個別に記述する。更新による変更については沿革で後述する。\n\nEXE車は単位輸送力の増強とともに<ref name="rf421-55"/>、弾力的な運用を行なうことを可能とするため<ref name="rf421-55"/>、全長20[[メートル|m]]の車両による4両固定編成と6両固定編成が製造され、分割・併合に対応した10両編成とした<ref name="rf421-56"/>。形式は先頭車が[[制御車]]のクハ30050形で<ref name="rf421-64"/>、中間車は[[動力車|電動車]]のデハ30000形<ref name="rf421-64"/>と[[付随車]]のサハ30050形である<ref name="rf421-64"/>。サハ30050形は6両固定編成にのみ連結される<ref name="rf421-64"/>。車両番号については、[[#編成表|巻末の編成表]]を参照のこと。\n\n=== 車体 ===\n先頭車・中間車とも車体長19,500[[ミリメートル|mm]]で<ref name="rf421-64"/>、全長は先頭車が19,750mm<ref name="rf421-64"/>、中間車が20,000mm<ref name="rf421-64"/>で、車体幅は2,900mmである<ref name="rf421-64"/>。車体は屋根板や床板に[[ステンレス鋼]]を使用<ref name="rp679-240"/>、それ以外の箇所は[[炭素鋼|普通鋼]]製である<ref name="rp679-240"/>。\n\n\n先頭形状は2種類存在し、10両編成組成時に両端となる1号車と10号車については正面に[[貫通扉]]のない非貫通型で<ref name="2002-o-32"/>、やや傾斜した形状としている<ref name="rf421-56"/>。これに対し、10両編成組成時に中間に入る6号車と7号車については正面に貫通扉が設けられた貫通型で<ref name="2002-o-32"/>、切妻に近い程度の緩い傾斜がつけられている<ref name="rf421-56"/>。6号車と7号車の正面貫通扉は両開き式[[プラグドア]]である<ref name="rf421-5859"/>。いずれの先頭車も、[[操縦席|運転室]]は通常の床高さに設置された<ref name="dj145-43"/>。\n\n側面客用扉は各車両とも1箇所で、片開き引戸が採用され<ref name="2002-o-32"/>、扉幅は[[車椅子]]対応座席のある2号車・5号車・8号車は1,000mm幅<ref name="rf421-57"/>、それ以外の車両は800mm幅とした<ref name="rf421-57"/>。客用扉は[[ハニカム構造|ペーパーハニカム構造]]とし<ref name="rf421-57"/>、指はさみ防止や遮音効果、曇り止めなどの目的で[[複層ガラス]]を採用した<ref name="rf421-57"/>。1997年の増備車からは、車体外部扉脇妻板に[[自動ドア#半自動|半自動]]扱いのドアスイッチを設置した。各扉上部には雨樋を設けた<ref name="rf421-5657"/>。\n\n[[ファイル:OER RomanceCar EXE -Super Hakone-.jpg|thumb|側面の愛称・行先表示器]]\n側面窓は、熱線吸収率の高いガラスを使用した<ref name="rf421-57"/>連続窓風の外観としたが、外部のガラス面積を高さ1,250mmに拡大した<ref name="rf421-RF22405"/>。全ての客用扉脇の客室窓上部には列車名や行き先を表示する[[発光ダイオード|LED]]式[[方向幕|表示器]]が設置された<ref group="注釈">RSE車では「[[あさぎり (列車)|あさぎり]]」での運行時以外列車名のみの表示だったが、EXE車では号数を含んだ列車名と行先が表示される。</ref>。車両間の貫通路は750mm幅で<ref name="rf421-RF22405"/>、6号車・7号車の前面貫通路は550mm幅である<ref name="rf421-RF22407"/>。各車両の連結面間には[[転落防止幌]]を設置した<ref name="rf421-56"/>。\n\n塗装デザインは全体をメタリック系のハーモニックパールブロンズ<ref name="rf421-57"/>とし、「小田急ロマンスカー」のシンボルカラーとして<ref name="rf421-57"/>アッパーレッドのワンポイントラインを入れた<ref name="rf421-57"/>。正面のワンポイントラインには "EXE" と文字が入るが、小田急ロマンスカーで車両愛称が車体外部に表示されるのは初めてである<ref name="rf422-23"/>。これは、10年経っても飽きのこないデザインを意図したものである<ref name="2005-u-59"/>。\n\n=== 内装 ===\n内装は、安らぎと落ち着きのある高級感の演出を図ったものとした<ref name="rf421-57"/>。\n\n\n[[鉄道車両の座席|座席]]は[[鉄道車両の座席#回転式クロスシート（回転腰掛）|回転式]][[リクライニングシート]]を採用<ref name="rp679-241"/>、[[座席#シートピッチ|シートピッチ]]1,000mmで配置した<ref name="rp829-281"/>。各座席の肘掛には収納式テーブルを設置した<ref name="rf421-60"/>。一斉回転機構は電動式が採用された<ref name="2002-o-34">[[#大幡2002|大幡 (2002) p.34]]</ref>。座席表地は1号車から6号車までが緑系統<ref name="rf421-57"/>、7号車から10号車までは青系統の色とする<ref name="rf421-57"/>ことで、分割運用時における行先別対応とした<ref name="rf421-57"/>。1999年の増備車では、全車両の座席の表地をグレーと茶色系のツートーンとした<ref name="rp679-242"/>。\n\n客室の壁面はグレー系統でまとめ<ref name="rf421-57"/>、出入台や売店部分は客室とは異なる青系統の配色とした<ref name="rp679-240241"/>。客室内の照明は電球色の[[蛍光灯]]を使用した間接照明とし<ref name="rf421-60"/>、蛍光灯のカバーに丸穴を開けることでアクセントとした<ref name="rf421-60"/>。また、[[網棚|荷物棚]]下には蛍光灯の直接照明を設置<ref name="rf421-60"/>、光の拡散を抑えるため集光板を備えた<ref name="rf421-60"/>。客室と出入台の間にある仕切り扉は、車椅子対応座席のある2号車・5号車・8号車は900mm幅<ref name="rp679-241"/>、それ以外の箇所は700mm幅とした<ref name="rp679-241"/>。1999年の増備車からは[[車内案内表示装置|車内案内装置]]において[[文字多重放送|FM文字多重装置]]「[[パパラビジョン]]」を搭載した<ref name="rp679-242"/>。\n\n3号車の新宿側車端部<ref name="rf421-58"/>と9号車の[[小田原駅|小田原]]側車端部<ref name="rf421-59"/>には売店と[[清涼飲料水]][[自動販売機]]を設置した<ref name="rp829-281"/>。売店のカウンターと、後述の化粧室には[[人工大理石]]を使用した<ref name="rf421-60"/>。[[テレホンカード]]式[[公衆電話]]を3号車・4号車・9号車に設置した<ref name="rf421-61"/>ほか、6号車・7号車を除く各車両の出入台には[[分別収集|分別回収]]が可能な[[ごみ箱|ゴミ箱]]を設置した<ref name="rf421-61"/>。\n\n2号車の新宿側車端部<ref name="rf421-60"/>と5号車・8号車の小田原側車端部<ref name="rf421-60"/>には男女共用[[便器#腰掛大便器（洋式・洋風大便器）|洋式]][[列車便所|トイレ]]・男性[[便器#小便器|小用トイレ]]・[[洗面器#洗面台・洗面所|化粧室]]を配置した<ref name="rf421-60"/>。このうち5号車の男女共用トイレについては車椅子対応となっており、扉を自動開閉式としたほか<ref name="rf421-60"/>ベビーベッドも設けた<ref name="rf421-60"/>。汚物処理装置はそれまでの小田急の車両で使用されていた循環式から真空式に変更した<ref name="rf421-60"/>。1997年の増備車からは、男性小用トイレの扉が開き戸から折戸に変更された<ref name="rp679-242"/>。\n\n=== 主要機器 ===\n\n[[運転士]]が乗務する乗務員室（運転室）は、貫通型と非貫通型では構造が異なっている。共通事項として、運転に必要な機器類は運転席周りに集約し<ref name="rf421-61"/>、[[マスター・コントローラー|主幹制御器]]を右手操作のワンハンドル式としたほか<ref name="rf421-61"/>、カラー液晶モニタ表示器を設けた<ref name="rf421-61"/>。また、乗務員が60秒間[[前照灯|前灯]]・[[警笛]]・主幹制御器の操作を行わなかった場合に警報を発し<ref name="rf421-64"/>、それでも操作がなかった場合に非常制動を動作させる[[緊急列車停止装置|EB装置]]を設置した<ref name="rf421-64"/>。非貫通型の運転台は前面に大型ガラスを採用し<ref name="rf421-61"/>、客室との仕切り窓も大型化することで客室内からの展望を考慮した<ref name="rf421-61"/>。貫通型の運転台では、後述する「自動ほろ装置」の収納スペースの関係から2室に分割されている<ref name="rf421-6162"/>。\n\nEXE車では分割・併合に対応する機器として「自動ほろ装置」を設置した<ref name="rf421-62">[[#飯塚421|『鉄道ファン』通巻421号 p.62]]</ref>。これは、分割・併合の操作を[[幌|貫通幌]]の連結まで自動的に行なうために開発・導入された<ref name="dj145-43"/>もので、2分以内に連結作業が終わるようにした<ref name="dj145-45">[[#開発145|『鉄道ダイヤ情報』通巻145号 p.45]]</ref>。曲線上でも自動連結を可能とするため、偏位自動調整装置が装備されている<ref name="rf421-62"/>。\n\n[[主電動機]]については、出力195[[ワット|kW]]の[[かご形三相誘導電動機]]を採用し<ref name="rf421-63"/>、各電動台車に2台ずつ装架した。[[東洋電機製造]]TDK6335-A形と[[三菱電機]]MB-5065-A形を併用している<ref name="rp679-241"/>。[[主制御器|制御装置]]は主電動機を1個単位で制御する個別制御方式を採用した[[絶縁ゲートバイポーラトランジスタ|IGBT]][[半導体素子|素子]]を用いた[[可変電圧可変周波数制御|VVVFインバータ制御]]である。4両編成が1台の制御装置で6台の主電動機を制御する方式 (1C6M) の[[東芝]]SVF-024A形を8号車に搭載し<ref name="rp829-282"/>、6両編成では1台の制御装置で4台の主電動機を制御する方式 (1C4M) の東芝SVF-024B形を2号車と5号車に搭載した<ref name="rp829-282"/>。SE車からRSE車までの特急車両に引き続き東芝製の採用である。個別制御方式の採用により電動機1台をカットしても急勾配を走行できる性能を有した<ref name="rf421-63"/>。このため、4両固定編成の電動車比率（[[MT比]]）は1.5M2.5T（主電動機は4両で6台）<ref name="rf421-63"/>、6両固定編成の電動車比率は2M4T（主電動機は6両で8台）とした<ref name="rf421-63"/><ref group="注釈">それまで、小田急の車両は電動車が編成の半分以上を占める編成が原則だったが、EXE車ではMT比を1:2とし、電動車が編成の半数を下回る構成となった。</ref>。4両固定編成と6両固定編成での電動車比率を可能な限り揃えるため<ref name="rp679-241"/>、4両編成の9号車新宿側の[[鉄道車両の台車|台車]]は付随台車としている<ref name="rp679-241"/>。[[鉄道のブレーキ|制動装置（ブレーキ）]]は[[電気指令式ブレーキ|電気指令式電磁直通制動]]で<ref name="rp679-241"/>、基礎制動装置はシングル式（片押し式）である<ref name="rp679-241"/>。\n\n[[ファイル:OER-30000-SS146-Truck.jpg|thumb|right|240px|電動台車 (SS146) ]]\n台車は、電動台車が[[住友金属工業]]製SS146<ref name="rp679-241"/>、付随台車が住友金属工業製SS046を採用した<ref name="rp679-241"/>。いずれも[[小田急2000形電車|2000形]]で採用されたモノリンク式軸箱支持形[[鉄道車両の台車史#ボルスタレス台車|ボルスタレス台車]]を特急車両向けに改良したもの<ref name="rp679-241"/>で、[[蛇行動#ヨーダンパ|ヨーダンパ]]を装備している<ref name="rf421-62"/>。\n\n[[集電装置]]（パンタグラフ）は[[集電装置#Z型・シングルアーム型|シングルアーム式]]のPT7100形を採用<ref name="rf421-63"/>、2号車・3号車・5号車・8号車・9号車に1台ずつ搭載した<ref name="rp679-241"/>。[[エアー・コンディショナー|冷房装置]]については、ヒーターを内蔵した[[集約分散式冷房装置|集約分散式]]とし<ref name="rf421-63"/>、11,500[[カロリー|kcal/h]]の冷凍能力を有する三菱電機製CU-195F形を1両に3台搭載した<ref name="rp679-241"/>。\n\n補助電源装置は、出力140[[ボルト (単位)|kV]][[アンペア|A]]のIGBT素子式[[静止形インバータ]] (IGBT-SIV) を7号車と9号車に<ref name="rp829-282"/>、出力200kVAのIGBT素子式静止形インバータを3号車と4号車に搭載した<ref name="rp829-282"/>。[[圧縮機|電動空気圧縮機]] (CP) については交流スクロール式のRC1500形を1号車・6号車・7号車・10号車に搭載した<ref name="rp829-282"/>。SE車からRSE車までの特急車両で採用されていた電子警報器（[[警笛#ミュージックホーン|補助警報音]]を発する装置）に代えて、[[警笛]]に電子笛が採用され<ref name="rp679-241"/>、八幡電気産業製のYA-95037型が搭載された<ref name="rp829-190"/>。\n\n== 沿革 ==\n[[ファイル:OdakyuExcellentExpressSeries30000 .JPG|thumb|「さがみ」「えのしま」併結列車に運用されるEXE車]]\n1996年3月23日の[[小田急電鉄のダイヤ改正#1990年代 - 特急ロマンスカーの新展開|ダイヤ改正]]から運行を開始した<ref name="dj145-31"/>。当初は10両編成が2編成で、本形式の特徴を生かした「[[はこね (列車)|はこね]]」と「[[えのしま (列車)|えのしま]]」の分割・併合がある運用に投入された<ref name="rf422-23"/>。また、検査時はHiSE車で代走する箱根特急「スーパーはこね」にも運用され<ref name="rf422-23"/>、運用初日は箱根湯本駅で到着式も行なわれた<ref name="dj145-31"/>。また、平日の夕方に新宿を発車する通勤向けの特急である「[[ホームウェイ (列車)|あしがら]]」（当時）<ref group="注釈">1999年7月16日からは、新宿を18時以降に発車する特急は通勤向けとして、愛称が「ホームウェイ」に変更された。</ref>にも投入され<ref name="dj145-34"/>、LSE車と比較して130人以上の定員増加となった<ref name="rp829-281"/>EXE車は、輸送力増強に貢献した。\n\nしかし、運行開始直後から[[鉄道ファン]]からは外装デザインに対して否定的な意見が多かった<ref name="2005-u-59"/>。運行開始翌年となる1997年ブルーリボン賞については候補車両にされたものの、この年のブルーリボン賞は「該当車なし」とされた<ref></ref><ref group="注釈">選考対象となった1997年の同賞では本形式の得票数が最多だったが、「該当なし」票がそれを上回ったためである。</ref>。小田急電鉄OBの[[生方良雄]]は、「EXE車が1997年のブルーリボン賞を受賞できなかった大きな要因の一つが、その外装デザインによる」としている<ref name="2005-u-61"/>。また、運用上の問題として「途中駅利用に対応するための車両であるにもかかわらず、新宿から小田原まで無停車の『スーパーはこね』に運用するなど、製作趣旨の徹底が不十分であった」ともしている<ref name="2005-u-61"/>。\n\n1999年までに4両固定編成・6両固定編成とも7編成が製造され<ref name="rp679-239"/>、これによってNSE車は「ゆめ70」に改装された車両を除いて淘汰された<ref name="rp829-282"/>。1999年に増備された編成では、座席の表地が4両固定編成・6両固定編成とも同じものとなり、その後他の車両も同一の表地に交換された。EXE車の投入と、途中駅を重視した特急施策によって、年間利用者数は1987年に1,100万人だったものが2003年には1,400万人に増加した<ref name="rj464-33"/>。\n\nEXE車は登場直後から小田急の広告ポスターなどでイメージリーダーとして起用されていた<ref name="rj464-33"/>が、箱根特急の利用者数は1987年の550万人から、2003年には300万人程度に減少していた<ref name="rj464-33"/>。箱根を訪れる観光客の減少も理由ではあったが、観光客全体の減少率が15[[パーセント|%]]程度であるのに対し<ref name="rj464-33"/>、箱根特急の利用者数は45%も減少していたのである<ref name="rj464-33"/>。この要因を調べると、EXE車には「小田急ロマンスカーのイメージ」とされた展望席が存在しなかったために他の交通手段に転移したとみられた<ref name="rj464-33"/>。2002年からはイメージリーダーとして起用される車両はHiSE車に変更された<ref name="rj464-34"/>。\n\nEXE車は登場以来、新宿駅へは[[臨時列車]]や突発的な運用変更がない限り10両編成で乗り入れていた<ref name="rp829-210"/>が、2003年3月29日のダイヤ改正からは平日の「はこね」2往復が全区間6両編成で運行されることになった<ref name="rp829-210"/>。6両編成で新宿駅に乗り入れる運用は初めてであった<ref name="rp829-210"/>が、この運用は2004年12月11日のダイヤ改正で見られなくなった<ref name="rp829-212"/>が、2009年3月14日のダイヤ改正では、平日の「はこね」1往復が全区間6両編成で運行されることになった<ref name="rp829-217"/>。\n\n2002年2月1日から3月31日まで、各編成の1号車で[[IPv6]]を用いた[[無線LAN]][[インターネット]]接続実験が行われ、<ref></ref>2012年からはWiMAXをバックホールとする「au Wi-Fi SPOT」と「Wi2 300」を民鉄の有料特急としては初めて導入した<ref>[http://www.odakyu.jp/program/info/data.info/7713_4317860_.pdf#search=%27%E5%B0%8F%E7%94%B0%E6%80%A5exe+%E7%84%A1%E7%B7%9Alan%27 民鉄有料特急初の公衆無線ＬＡＮサービス登場！ ロマンスカー・ＥＸＥに「au Wi-Fi SPOT」を導入 －今後、小田急外国人旅行センターなど、サービスを駅に拡充していきます－ ]</ref>。（登場してから10年余り経過した2007年には、日本デザイン振興会よりロングライフデザイン賞を受賞した<ref></ref>。\n\n== 編成表 ==\n; 凡例 : Tc…[[制御車]]、M…[[動力車|電動車]]、CON…[[主制御器|制御装置]]、SIV…補助電源装置、CP…[[圧縮機|電動空気圧縮機]]、PT…[[集電装置]]<br/>乗 …乗務員室、車…車椅子対応座席、売…売店、自…自動販売機、電…[[公衆電話]]、WC…[[列車便所|トイレ]]・[[洗面器#洗面台・洗面所|化粧室]]、VWC…車椅子対応トイレ・化粧室、AED…[[自動体外式除細動器]]\n\n<!--#857971はハーモニックパールブロンズ 鉄道ピクトリアル通巻829号（2010年1月号臨時増刊）「特集・小田急電鉄」p191の表から色を抽出-->\n{|style="text-align:left;"\n|-\n|\n{| class="wikitable" style="text-align:center; font-size:80%; margin:1em 0em 2em 3em;"\n|-\n|style="border-bottom:solid 3px #857971; background-color:#ccc;"|&nbsp;\n|style="border-bottom:solid 3px #857971;" colspan="6"|\n|-\n!号車\n| 1 || 2 || 3 || 4 || 5 || 6\n|-\n!形式\n| '''クハ30050''' || '''デハ30000''' || '''サハ30050''' || '''サハ30050''' || '''デハ30000''' || '''クハ30050'''\n|-\n!style="border-bottom:solid 3px #BE0032;"|区分\n|style="border-bottom:solid 3px #BE0032;"| 30550<br/>(Tc2) ||style="border-bottom:solid 3px #BE0032;"| 30500<br/>(M2) ||style="border-bottom:solid 3px #BE0032;"| 30450<br/>(T2) ||style="border-bottom:solid 3px #BE0032;"| 30350<br/>(T1) ||style="border-bottom:solid 3px #BE0032;"| 30200<br/>(M1') ||style="border-bottom:solid 3px #BE0032;"| 30250<br/>(Tc1')\n|-\n![[鉄道の車両番号|車両番号]]\n| 30551<br/>∥<br/>30557 || 30501<br/>∥<br/>30507 || 30451<br/>∥<br/>30457 || 30351<br/>∥<br/>30357 || 30201<br/>∥<br/>30207 || 30251<br/>∥<br/>30257\n|-\n!搭載機器\n| CP || CON,PT || SIV,PT || SIV || CON,PT || CP\n|-\n!style="border-bottom:solid 3px green;"|自重\n|style="border-bottom:solid 3px green;"| 33.8t ||style="border-bottom:solid 3px green;"| 41.8t ||style="border-bottom:solid 3px green;"| 36.9t ||style="border-bottom:solid 3px green;"| 35.8t ||style="border-bottom:solid 3px green;"| 41.8t ||style="border-bottom:solid 3px green;"| 34.7t\n|-\n!車内設備\n| 乗 || WC|| 売、自、電|| 電|| 車、VWC|| 乗、AED\n|-\n!定員\n| 56 || 60 || 56 || 68 || 58 ||60\n|}\n|\n{| class="wikitable" style="text-align:center; font-size:80%; margin:1em 0em 2em 3em;"\n|-\n|style="border-bottom:solid 3px #857971; background-color:#ccc;"|&nbsp;\n|style="border-bottom:solid 3px #857971;" colspan="6"|\n|-\n!号車\n| 7 || 8 || 9 || 10\n|-\n!形式\n| '''クハ30050''' || '''デハ30000''' || '''デハ30000''' || '''クハ30050'''\n|-\n!style="border-bottom:solid 3px #BE0032;"|区分\n|style="border-bottom:solid 3px #BE0032;"| 30150<br/>(Tc2') ||style="border-bottom:solid 3px #BE0032;"| 30100<br/>(M2') ||style="border-bottom:solid 3px #BE0032;"| 30000<br/>(M1) ||style="border-bottom:solid 3px #BE0032;"| 30050<br/>(Tc1)\n|-\n!車両番号\n| 30151<br/>∥<br/>30157 || 30101<br/>∥<br/>30107 || 30001<br/>∥<br/>30007 || 30051<br/>∥<br/>30057\n|-\n!搭載機器\n| SIV,CP || CON,PT || SIV,PT || CP\n|-\n!style="border-bottom:solid 3px blue;"|自重\n|style="border-bottom:solid 3px blue;"| 36.3t ||style="border-bottom:solid 3px blue;"| 42.7t ||style="border-bottom:solid 3px blue;"| 39.1t ||style="border-bottom:solid 3px blue;"| 33.8t\n|-\n!車内設備\n| 乗、AED || 車、WC|| 売、自、電|| 乗\n|-\n!定員\n| 60 || 58 || 56 || 56\n|}\n|}\n\n== 脚注 ==\n\n\n=== 注釈 ===\n\n\n=== 出典 ===\n{{Reflist|2|refs=\n<ref name="dj145-15">[[#DJ145|『鉄道ダイヤ情報』通巻145号 p.15]]</ref>\n<ref name="dj145-31">[[#DJ145|『鉄道ダイヤ情報』通巻145号 p.31]]</ref>\n<ref name="dj145-34">[[#DB145|『鉄道ダイヤ情報』通巻145号 p.34]]</ref>\n<ref name="dj145-42">[[#開発145|『鉄道ダイヤ情報』通巻145号 p.42]]</ref>\n<ref name="dj145-43">[[#開発145|『鉄道ダイヤ情報』通巻145号 p.43]]</ref>\n<ref name="dj145-44">[[#開発145|『鉄道ダイヤ情報』通巻145号 p.44]]</ref>\n<ref name="2002-o-32">[[#大幡2002|大幡 (2002) p.32]]</ref>\n<ref name="2005-u-167">[[#生方2005|生方 (2005) p.167]]</ref>\n<ref name="2005-u-58">[[#生方2005|生方 (2005) p.58]]</ref>\n<ref name="2005-u-59">[[#生方2005|生方 (2005) p.59]]</ref>\n<ref name="2005-u-61">[[#生方2005|生方 (2005) p.61]]</ref>\n<ref name="rf421-55">[[#飯塚421|『鉄道ファン』通巻421号 p.55]]</ref>\n<ref name="rf421-56">[[#飯塚421|『鉄道ファン』通巻421号 p.56]]</ref>\n<ref name="rf421-5657">[[#飯塚421|『鉄道ファン』通巻421号 pp.56-57]]</ref>\n<ref name="rf421-57">[[#飯塚421|『鉄道ファン』通巻421号 p.57]]</ref>\n<ref name="rf421-58">[[#飯塚421|『鉄道ファン』通巻421号 p.58]]</ref>\n<ref name="rf421-5859">[[#飯塚421|『鉄道ファン』通巻421号 pp.58-59]]</ref>\n<ref name="rf421-59">[[#飯塚421|『鉄道ファン』通巻421号 p.59]]</ref>\n<ref name="rf421-60">[[#飯塚421|『鉄道ファン』通巻421号 p.60]]</ref>\n<ref name="rf421-61">[[#飯塚421|『鉄道ファン』通巻421号 p.61]]</ref>\n<ref name="rf421-6162">[[#飯塚421|『鉄道ファン』通巻421号 pp.61-62]]</ref>\n<ref name="rf421-63">[[#飯塚421|『鉄道ファン』通巻421号 p.63]]</ref>\n<ref name="rf421-64">[[#飯塚421|『鉄道ファン』通巻421号 p.64]]</ref>\n<ref name="rf421-64">[[#飯塚421|『鉄道ファン』通巻421号 p.64]]</ref>\n<ref name="rf421-RF22405">[[#飯塚421|『鉄道ファン』通巻421号付図 (RF22405) ]]</ref>\n<ref name="rf421-RF22407">[[#飯塚421|『鉄道ファン』通巻421号付図 (RF22407) ]]</ref>\n<ref name="rf422-23">[[#RF422|『鉄道ファン』通巻422号 p.23]]</ref>\n<ref name="rf422-23">[[#RF422|『鉄道ファン』通巻422号 p.23]]</ref>\n<ref name="rj464-33">[[#RJ464|『鉄道ジャーナル』通巻464号 p.33]]</ref>\n<ref name="rj464-34">[[#RJ464|『鉄道ジャーナル』通巻464号 p.34]]</ref>\n<ref name="rp679-239">[[#大幡679|『鉄道ピクトリアル』通巻679号 p.239]]</ref>\n<ref name="rp679-240">[[#大幡679|『鉄道ピクトリアル』通巻679号 p.240]]</ref>\n<ref name="rp679-240241">[[#大幡679|『鉄道ピクトリアル』通巻679号 pp.240-241]]</ref>\n<ref name="rp679-241">[[#大幡679|『鉄道ピクトリアル』通巻679号 p.241]]</ref>\n<ref name="rp679-242">[[#大幡679|『鉄道ピクトリアル』通巻679号 p.242]]</ref>\n<ref name="rp679-39">[[#草門679|『鉄道ピクトリアル』通巻679号 p.39]]</ref>\n<ref name="rp829-190">[[#中山829|『鉄道ピクトリアル』通巻829号 p.190]]</ref>\n<ref name="rp829-210">[[#杉田829|『鉄道ピクトリアル』通巻829号 p.210]]</ref>\n<ref name="rp829-212">[[#杉田829|『鉄道ピクトリアル』通巻829号 p.212]]</ref>\n<ref name="rp829-217">[[#杉田829|『鉄道ピクトリアル』通巻829号 p.217]]</ref>\n<ref name="rp829-280">[[#岸上829|『鉄道ピクトリアル』通巻829号 p.280]]</ref>\n<ref name="rp829-281">[[#岸上829|『鉄道ピクトリアル』通巻829号 p.281]]</ref>\n<ref name="rp829-282">[[#岸上829|『鉄道ピクトリアル』通巻829号 p.282]]</ref>\n<ref name="rp829-306">[[#岸上829-1|『鉄道ピクトリアル』通巻829号 p.306]]</ref>\n<ref name="rp829-317">[[#岸上829-2|『鉄道ピクトリアル』通巻829号 p.317]]</ref>\n}}\n\n== 参考文献 ==\n=== 書籍 ===\n* \n* \n\n=== 雑誌記事 ===\n* \n* \n* \n* \n* \n* \n* \n* \n* \n* \n* \n* \n* \n\n<!--\n== 関連項目 ==\n<-->\n\n== 外部リンク ==\n* [http://www.odakyu.jp/romancecar/line_up/30000/ EXE（30000形）] - 小田急電鉄\n\n\n\n\n\n[[Category:小田急電鉄の電車|30000]]\n[[Category:1996年製の鉄道車両|おたきゆう電30000]]\n[[Category:日本車輌製造製の電車]]\n[[Category:川崎重工業製の電車]]\n[[Category:グッドデザイン賞]]	</DESCRIPTION>
  <BODY>58892203	{{鉄道車両\n|車両名 =小田急30000形電車<br/><small>Excellent Express</small>\n|社色 =#BE0032 <!--アッパーレッド 鉄道ピクトリアル通巻829号（2010年1月号臨時増刊）「特集・小田急電鉄」p191の表から色を抽出-->\n|画像 =Odakyu Erectric Railway 30000.jpg\n|pxl =300px\n|画像説明 =30000形EXE車<br/>（2007年12月9日、開成駅 - 栢山駅間）\n|unit = self\n|編成 =4両固定編成<ref name="rp679-239"/>・6両固定編成<ref name="rp679-239"/>\n|起動加速度 =2.0km/h/s<ref name="rf421-64"/>\n|営業最高速度 =110km/h\n|設計最高速度 =120km/h<ref name="rf421-64"/>\n|最高速度 =\n|定格速度 =\n|減速度（常用最大）=（初速100km/h）3.5km/h/s<ref name="rf421-64"/>（常用最大）<br/>（初速60km/h）4.0km/h/s<ref name="rf421-64"/>\n|減速度（非常） =（初速100km/h）4.0km/h/s<ref name="rf421-64"/>（非常）<br/>（初速60km/h）4.5km/h/s<ref name="rf421-64"/>\n|編成定員 =588名（4両固定編成+6両固定編成）<ref name="2005-u-167"/>\n|車両定員 =\n|編成長 =199.500[[メートル|m]]（4両固定編成+6両固定編成）<ref name="2005-u-167"/>\n|最大寸法 =19,750[[ミリメートル|mm]]×2,900mm×4,050mm（非貫通型先頭車）<ref name="rp829-317"/><br/>20,000mm×2,900mm×4,050mm（貫通型先頭車）<ref name="rp829-317"/><br/>20,000mm×2,900mm×4,065mm（集電装置付中間車）<ref name="rp829-317"/><br/>20,000mm×2,900mm×4,050mm（集電装置無し中間車）<ref name="rp829-317"/>\n|全長 =\n|全幅 =\n|全高 =\n|車体長 =\n|車体幅 =\n|車体高 =\n|編成質量 =376.7[[トン|t]]（4両固定編成+6両固定編成）<ref name="2005-u-167"/>\n|車両質量 =\n|軸配置 =\n|軌間 =1,067 mm\n|電気方式 =[[直流電化|直流]]1,500V<br/>（[[架空電車線方式]]）\n|出力 =\n|主電動機 =[[東洋電機製造]] TDK6335-A<ref name="rp829-317"/><br/>[[三菱電機]] MB-5065-A<ref name="rp829-317"/><br/>[[かご形三相誘導電動機]]<ref name="rp829-317"/>\n|モーター出力 =195[[ワット|kW]]<ref name="rp829-317"/>\n|機関出力 =\n|編成出力 =\n|定格出力 =\n|定格引張力 =\n|駆動装置 =[[TD平行カルダン駆動方式]]<ref name="rp679-241"/><br/>（中実軸撓み板継手方式）\n|歯車比 =98:15=6.53<ref name="rp829-317"/>\n|変速段 =\n|台車 =[[住友金属工業]] SS146（電動台車）<ref name="rp829-317"/><br/>住友金属工業 SS046（付随台車）<ref name="rp829-317"/>\n|制御装置 =[[東芝]] SVF-024A（4両固定編成）<ref name="rp829-317"/><br/>東芝 SVF-024B（6両固定編成）<ref name="rp829-317"/><br/>[[絶縁ゲートバイポーラトランジスタ|IGBT]]-[[可変電圧可変周波数制御|VVVFインバータ制御]]\n|ブレーキ方式 =[[電力回生ブレーキ|回生制動]]併用[[電気指令式ブレーキ|電気指令電気演算式]][[電磁直通ブレーキ|電磁直通制動]] (MBSA-R) <ref name="rp679-241"/>\n|保安装置 =[[自動列車停止装置#多変周式信号ATS（多変周式（点制御、連続照査型））|OM-ATS]], [[自動列車停止装置#D-ATS-P（デジタルATS-P）形|D-ATS-P]]\n|製造メーカー =[[日本車輌製造]]<ref name="rp829-306"/>・[[川崎重工業車両カンパニー|川崎重工業]]<ref name="rp829-306"/>\n|備考 =\n|備考全幅 =\n}}\n'''小田急30000形電車'''（おだきゅう30000がたでんしゃ）は、[[1996年]]に[[小田急電鉄]]（小田急）が運用を開始した<ref name="rp679-39"/>[[特急形車両|特急用車両]]<!--小田急では「特急形」という区分ではないため。2300形の登場当時は竣功図に「優等電動客車」というように書いてあるようですが-->（[[小田急ロマンスカー|ロマンスカー]]）である。\n\n特急ロマンスカーに使用されていた[[小田急3100形電車|3100形（NSE車）]]の置き換えを目的として登場した<ref name="rp829-280"/>特急車両で、特急ロマンスカーの利用実態の変化に対応し<ref name="rp679-239"/>、単位輸送力の増強を行った上で<ref name="rp679-239"/>、観光輸送だけではなくビジネス利用を強く意識した車両とした<ref name="rp679-39"/>。また、小田急の特急車両では初めて[[可変電圧可変周波数制御|VVVFインバータ制御]]を採用した<ref name="rp829-280"/>。 "Excellent Express" を略して「EXE（エクセ）」という愛称が設定され、1996年には当時の[[通商産業省]]より[[グッドデザイン賞|グッドデザイン商品]]に選定された<ref name="rp829-280"/>。[[鉄道友の会]]に[[ブルーリボン賞 (鉄道)|ブルーリボン賞]]の制度が創設されて以来、小田急の特急車両で唯一ブルーリボン賞を受賞していない車両である<ref name="2005-u-61"/>。\n\n小田急では、編成表記の際には「[[新宿駅|新宿]]寄り先頭車両の[[鉄道の車両番号|車両番号]]（新宿方の車号）×両数」という表記を使用している<ref name="dj145-15"/>ため、本項もそれに倣い、特定の編成を表記する際には「30051×4」「30251×6」のように表記する。また、[[小田急3100形電車|3100形]]は「NSE車」、[[小田急7000形電車|7000形]]は「LSE車」、[[小田急10000形電車|10000形]]は「HiSE車」、本形式30000形は「EXE車」、[[箱根登山鉄道]][[箱根湯本駅]]へ乗り入れる特急列車については「箱根特急」と表記する。\n\n== 登場の経緯 ==\n小田急の特急ロマンスカーはもともと[[箱根町|箱根]]への観光客が対象であり<ref name="2005-u-58"/>、箱根特急の途中駅停車も元来は沿線在住の箱根観光客を対象としたものであった<ref name="2005-u-58"/>。しかし、時代の進展とともに利用実態は変化し、観光客以外の日常利用が増加していた<ref name="2005-u-58"/>ほか、1967年より[[回送]]列車を客扱いすることから始まった通勤用の特急列車の利用者数も増加しており<ref name="2005-u-58"/>、輸送力が不足していた<ref name="dj145-42"/>。一方で、NSE車は更新修繕などが行なわれてはいたものの車齢30年を超えており<ref name="rp679-239"/>、代替の車両について検討が行なわれていた<ref name="rp679-239"/>。\n\nこのため、NSE車を置き換えると同時に、変化した利用実態に対応した車両を製作することになった<ref name="rp679-239"/>。設計に際しては、小田急や車両メーカーのほかに[[小田急百貨店]]のインテリアデザイナーや外部のグラフィックデザイナーも交えて検討が行なわれた<ref name="dj145-44"/>。検討過程では[[ボギー台車|ボギー車]]の方が定員増が可能であると判断され<ref name="dj145-42"/>、[[連接台車|連接構造]]は採用されなかった<ref name="dj145-42"/>。また、[[増解結|分割・併合]]を行なう際に通り抜け可能な貫通路を設けることとした<ref name="dj145-43"/>が、この構造では前面[[展望車|展望席]]の設置は困難であること<ref name="dj145-42"/>や、乗務員交代が短時間で可能なことを考慮し<ref name="dj145-42"/>、前面展望席は採用されないことになった<ref name="dj145-42"/>。\n\nこうして、それまでの特急ロマンスカーとは一線を画す特急車両として<ref name="rf421-56"/>登場したのがEXE車である。\n\n== 車両概説 ==\n本節では、登場当時の仕様を基本として、増備途上での変更点を個別に記述する。更新による変更については沿革で後述する。\n\nEXE車は単位輸送力の増強とともに<ref name="rf421-55"/>、弾力的な運用を行なうことを可能とするため<ref name="rf421-55"/>、全長20[[メートル|m]]の車両による4両固定編成と6両固定編成が製造され、分割・併合に対応した10両編成とした<ref name="rf421-56"/>。形式は先頭車が[[制御車]]のクハ30050形で<ref name="rf421-64"/>、中間車は[[動力車|電動車]]のデハ30000形<ref name="rf421-64"/>と[[付随車]]のサハ30050形である<ref name="rf421-64"/>。サハ30050形は6両固定編成にのみ連結される<ref name="rf421-64"/>。車両番号については、[[#編成表|巻末の編成表]]を参照のこと。\n\n=== 車体 ===\n先頭車・中間車とも車体長19,500[[ミリメートル|mm]]で<ref name="rf421-64"/>、全長は先頭車が19,750mm<ref name="rf421-64"/>、中間車が20,000mm<ref name="rf421-64"/>で、車体幅は2,900mmである<ref name="rf421-64"/>。車体は屋根板や床板に[[ステンレス鋼]]を使用<ref name="rp679-240"/>、それ以外の箇所は[[炭素鋼|普通鋼]]製である<ref name="rp679-240"/>。\n\n{{Double image aside|right|Odakyu30000-1.JPG|180|Odakyu30000-2.JPG|180|非貫通型|貫通型}}\n先頭形状は2種類存在し、10両編成組成時に両端となる1号車と10号車については正面に[[貫通扉]]のない非貫通型で<ref name="2002-o-32"/>、やや傾斜した形状としている<ref name="rf421-56"/>。これに対し、10両編成組成時に中間に入る6号車と7号車については正面に貫通扉が設けられた貫通型で<ref name="2002-o-32"/>、切妻に近い程度の緩い傾斜がつけられている<ref name="rf421-56"/>。6号車と7号車の正面貫通扉は両開き式[[プラグドア]]である<ref name="rf421-5859"/>。いずれの先頭車も、[[操縦席|運転室]]は通常の床高さに設置された<ref name="dj145-43"/>。\n\n側面客用扉は各車両とも1箇所で、片開き引戸が採用され<ref name="2002-o-32"/>、扉幅は[[車椅子]]対応座席のある2号車・5号車・8号車は1,000mm幅<ref name="rf421-57"/>、それ以外の車両は800mm幅とした<ref name="rf421-57"/>。客用扉は[[ハニカム構造|ペーパーハニカム構造]]とし<ref name="rf421-57"/>、指はさみ防止や遮音効果、曇り止めなどの目的で[[複層ガラス]]を採用した<ref name="rf421-57"/>。1997年の増備車からは、車体外部扉脇妻板に[[自動ドア#半自動|半自動]]扱いのドアスイッチを設置した。各扉上部には雨樋を設けた<ref name="rf421-5657"/>。\n\n[[ファイル:OER RomanceCar EXE -Super Hakone-.jpg|thumb|側面の愛称・行先表示器]]\n側面窓は、熱線吸収率の高いガラスを使用した<ref name="rf421-57"/>連続窓風の外観としたが、外部のガラス面積を高さ1,250mmに拡大した<ref name="rf421-RF22405"/>。全ての客用扉脇の客室窓上部には列車名や行き先を表示する[[発光ダイオード|LED]]式[[方向幕|表示器]]が設置された<ref group="注釈">RSE車では「[[あさぎり (列車)|あさぎり]]」での運行時以外列車名のみの表示だったが、EXE車では号数を含んだ列車名と行先が表示される。</ref>。車両間の貫通路は750mm幅で<ref name="rf421-RF22405"/>、6号車・7号車の前面貫通路は550mm幅である<ref name="rf421-RF22407"/>。各車両の連結面間には[[転落防止幌]]を設置した<ref name="rf421-56"/>。\n\n塗装デザインは全体をメタリック系のハーモニックパールブロンズ<ref name="rf421-57"/>とし、「小田急ロマンスカー」のシンボルカラーとして<ref name="rf421-57"/>アッパーレッドのワンポイントラインを入れた<ref name="rf421-57"/>。正面のワンポイントラインには "EXE" と文字が入るが、小田急ロマンスカーで車両愛称が車体外部に表示されるのは初めてである<ref name="rf422-23"/>。これは、10年経っても飽きのこないデザインを意図したものである<ref name="2005-u-59"/>。\n\n=== 内装 ===\n内装は、安らぎと落ち着きのある高級感の演出を図ったものとした<ref name="rf421-57"/>。\n\n{{Triple image|right|OER-EXE30000-inside.jpg|133|Counter of Odakyu RomanceCar EXE.JPG|77|OER 30100 inside service counter.jpg|133|客室|売店のショーケース|売店のカウンター}}\n[[鉄道車両の座席|座席]]は[[鉄道車両の座席#回転式クロスシート（回転腰掛）|回転式]][[リクライニングシート]]を採用<ref name="rp679-241"/>、[[座席#シートピッチ|シートピッチ]]1,000mmで配置した<ref name="rp829-281"/>。各座席の肘掛には収納式テーブルを設置した<ref name="rf421-60"/>。一斉回転機構は電動式が採用された<ref name="2002-o-34">[[#大幡2002|大幡 (2002) p.34]]</ref>。座席表地は1号車から6号車までが緑系統<ref name="rf421-57"/>、7号車から10号車までは青系統の色とする<ref name="rf421-57"/>ことで、分割運用時における行先別対応とした<ref name="rf421-57"/>。1999年の増備車では、全車両の座席の表地をグレーと茶色系のツートーンとした<ref name="rp679-242"/>。\n\n客室の壁面はグレー系統でまとめ<ref name="rf421-57"/>、出入台や売店部分は客室とは異なる青系統の配色とした<ref name="rp679-240241"/>。客室内の照明は電球色の[[蛍光灯]]を使用した間接照明とし<ref name="rf421-60"/>、蛍光灯のカバーに丸穴を開けることでアクセントとした<ref name="rf421-60"/>。また、[[網棚|荷物棚]]下には蛍光灯の直接照明を設置<ref name="rf421-60"/>、光の拡散を抑えるため集光板を備えた<ref name="rf421-60"/>。客室と出入台の間にある仕切り扉は、車椅子対応座席のある2号車・5号車・8号車は900mm幅<ref name="rp679-241"/>、それ以外の箇所は700mm幅とした<ref name="rp679-241"/>。1999年の増備車からは[[車内案内表示装置|車内案内装置]]において[[文字多重放送|FM文字多重装置]]「[[パパラビジョン]]」を搭載した<ref name="rp679-242"/>。\n\n3号車の新宿側車端部<ref name="rf421-58"/>と9号車の[[小田原駅|小田原]]側車端部<ref name="rf421-59"/>には売店と[[清涼飲料水]][[自動販売機]]を設置した<ref name="rp829-281"/>。売店のカウンターと、後述の化粧室には[[人工大理石]]を使用した<ref name="rf421-60"/>。[[テレホンカード]]式[[公衆電話]]を3号車・4号車・9号車に設置した<ref name="rf421-61"/>ほか、6号車・7号車を除く各車両の出入台には[[分別収集|分別回収]]が可能な[[ごみ箱|ゴミ箱]]を設置した<ref name="rf421-61"/>。\n\n2号車の新宿側車端部<ref name="rf421-60"/>と5号車・8号車の小田原側車端部<ref name="rf421-60"/>には男女共用[[便器#腰掛大便器（洋式・洋風大便器）|洋式]][[列車便所|トイレ]]・男性[[便器#小便器|小用トイレ]]・[[洗面器#洗面台・洗面所|化粧室]]を配置した<ref name="rf421-60"/>。このうち5号車の男女共用トイレについては車椅子対応となっており、扉を自動開閉式としたほか<ref name="rf421-60"/>ベビーベッドも設けた<ref name="rf421-60"/>。汚物処理装置はそれまでの小田急の車両で使用されていた循環式から真空式に変更した<ref name="rf421-60"/>。1997年の増備車からは、男性小用トイレの扉が開き戸から折戸に変更された<ref name="rp679-242"/>。\n\n=== 主要機器 ===\n{{Double image aside|right|OER 30150 inside cab.jpg|180|OER-30000-Coupling.jpg|180|貫通型の運転台|「自動ほろ装置」により接続された中間の運転台}}\n[[運転士]]が乗務する乗務員室（運転室）は、貫通型と非貫通型では構造が異なっている。共通事項として、運転に必要な機器類は運転席周りに集約し<ref name="rf421-61"/>、[[マスター・コントローラー|主幹制御器]]を右手操作のワンハンドル式としたほか<ref name="rf421-61"/>、カラー液晶モニタ表示器を設けた<ref name="rf421-61"/>。また、乗務員が60秒間[[前照灯|前灯]]・[[警笛]]・主幹制御器の操作を行わなかった場合に警報を発し<ref name="rf421-64"/>、それでも操作がなかった場合に非常制動を動作させる[[緊急列車停止装置|EB装置]]を設置した<ref name="rf421-64"/>。非貫通型の運転台は前面に大型ガラスを採用し<ref name="rf421-61"/>、客室との仕切り窓も大型化することで客室内からの展望を考慮した<ref name="rf421-61"/>。貫通型の運転台では、後述する「自動ほろ装置」の収納スペースの関係から2室に分割されている<ref name="rf421-6162"/>。\n\nEXE車では分割・併合に対応する機器として「自動ほろ装置」を設置した<ref name="rf421-62">[[#飯塚421|『鉄道ファン』通巻421号 p.62]]</ref>。これは、分割・併合の操作を[[幌|貫通幌]]の連結まで自動的に行なうために開発・導入された<ref name="dj145-43"/>もので、2分以内に連結作業が終わるようにした<ref name="dj145-45">[[#開発145|『鉄道ダイヤ情報』通巻145号 p.45]]</ref>。曲線上でも自動連結を可能とするため、偏位自動調整装置が装備されている<ref name="rf421-62"/>。\n\n[[主電動機]]については、出力195[[ワット|kW]]の[[かご形三相誘導電動機]]を採用し<ref name="rf421-63"/>、各電動台車に2台ずつ装架した。[[東洋電機製造]]TDK6335-A形と[[三菱電機]]MB-5065-A形を併用している<ref name="rp679-241"/>。[[主制御器|制御装置]]は主電動機を1個単位で制御する個別制御方式を採用した[[絶縁ゲートバイポーラトランジスタ|IGBT]][[半導体素子|素子]]を用いた[[可変電圧可変周波数制御|VVVFインバータ制御]]である。4両編成が1台の制御装置で6台の主電動機を制御する方式 (1C6M) の[[東芝]]SVF-024A形を8号車に搭載し<ref name="rp829-282"/>、6両編成では1台の制御装置で4台の主電動機を制御する方式 (1C4M) の東芝SVF-024B形を2号車と5号車に搭載した<ref name="rp829-282"/>。SE車からRSE車までの特急車両に引き続き東芝製の採用である。個別制御方式の採用により電動機1台をカットしても急勾配を走行できる性能を有した<ref name="rf421-63"/>。このため、4両固定編成の電動車比率（[[MT比]]）は1.5M2.5T（主電動機は4両で6台）<ref name="rf421-63"/>、6両固定編成の電動車比率は2M4T（主電動機は6両で8台）とした<ref name="rf421-63"/><ref group="注釈">それまで、小田急の車両は電動車が編成の半分以上を占める編成が原則だったが、EXE車ではMT比を1:2とし、電動車が編成の半数を下回る構成となった。</ref>。4両固定編成と6両固定編成での電動車比率を可能な限り揃えるため<ref name="rp679-241"/>、4両編成の9号車新宿側の[[鉄道車両の台車|台車]]は付随台車としている<ref name="rp679-241"/>。[[鉄道のブレーキ|制動装置（ブレーキ）]]は[[電気指令式ブレーキ|電気指令式電磁直通制動]]で<ref name="rp679-241"/>、基礎制動装置はシングル式（片押し式）である<ref name="rp679-241"/>。\n\n[[ファイル:OER-30000-SS146-Truck.jpg|thumb|right|240px|電動台車 (SS146) ]]\n台車は、電動台車が[[住友金属工業]]製SS146<ref name="rp679-241"/>、付随台車が住友金属工業製SS046を採用した<ref name="rp679-241"/>。いずれも[[小田急2000形電車|2000形]]で採用されたモノリンク式軸箱支持形[[鉄道車両の台車史#ボルスタレス台車|ボルスタレス台車]]を特急車両向けに改良したもの<ref name="rp679-241"/>で、[[蛇行動#ヨーダンパ|ヨーダンパ]]を装備している<ref name="rf421-62"/>。\n\n[[集電装置]]（パンタグラフ）は[[集電装置#Z型・シングルアーム型|シングルアーム式]]のPT7100形を採用<ref name="rf421-63"/>、2号車・3号車・5号車・8号車・9号車に1台ずつ搭載した<ref name="rp679-241"/>。[[エアー・コンディショナー|冷房装置]]については、ヒーターを内蔵した[[集約分散式冷房装置|集約分散式]]とし<ref name="rf421-63"/>、11,500[[カロリー|kcal/h]]の冷凍能力を有する三菱電機製CU-195F形を1両に3台搭載した<ref name="rp679-241"/>。\n\n補助電源装置は、出力140[[ボルト (単位)|kV]][[アンペア|A]]のIGBT素子式[[静止形インバータ]] (IGBT-SIV) を7号車と9号車に<ref name="rp829-282"/>、出力200kVAのIGBT素子式静止形インバータを3号車と4号車に搭載した<ref name="rp829-282"/>。[[圧縮機|電動空気圧縮機]] (CP) については交流スクロール式のRC1500形を1号車・6号車・7号車・10号車に搭載した<ref name="rp829-282"/>。SE車からRSE車までの特急車両で採用されていた電子警報器（[[警笛#ミュージックホーン|補助警報音]]を発する装置）に代えて、[[警笛]]に電子笛が採用され<ref name="rp679-241"/>、八幡電気産業製のYA-95037型が搭載された<ref name="rp829-190"/>。\n\n== 沿革 ==\n[[ファイル:OdakyuExcellentExpressSeries30000 .JPG|thumb|「さがみ」「えのしま」併結列車に運用されるEXE車]]\n1996年3月23日の[[小田急電鉄のダイヤ改正#1990年代 - 特急ロマンスカーの新展開|ダイヤ改正]]から運行を開始した<ref name="dj145-31"/>。当初は10両編成が2編成で、本形式の特徴を生かした「[[はこね (列車)|はこね]]」と「[[えのしま (列車)|えのしま]]」の分割・併合がある運用に投入された<ref name="rf422-23"/>。また、検査時はHiSE車で代走する箱根特急「スーパーはこね」にも運用され<ref name="rf422-23"/>、運用初日は箱根湯本駅で到着式も行なわれた<ref name="dj145-31"/>。また、平日の夕方に新宿を発車する通勤向けの特急である「[[ホームウェイ (列車)|あしがら]]」（当時）<ref group="注釈">1999年7月16日からは、新宿を18時以降に発車する特急は通勤向けとして、愛称が「ホームウェイ」に変更された。</ref>にも投入され<ref name="dj145-34"/>、LSE車と比較して130人以上の定員増加となった<ref name="rp829-281"/>EXE車は、輸送力増強に貢献した。\n\nしかし、運行開始直後から[[鉄道ファン]]からは外装デザインに対して否定的な意見が多かった<ref name="2005-u-59"/>。運行開始翌年となる1997年ブルーリボン賞については候補車両にされたものの、この年のブルーリボン賞は「該当車なし」とされた<ref>{{Cite web|author=鉄道友の会|url=http://www.jrc.gr.jp/award/bl/bl1997.htm|title=1997年 ブルーリボン・ローレル賞選定車両|work=|publisher=|language=日本語|accessdate=2011-10-10}}</ref><ref group="注釈">選考対象となった1997年の同賞では本形式の得票数が最多だったが、「該当なし」票がそれを上回ったためである。</ref>。小田急電鉄OBの[[生方良雄]]は、「EXE車が1997年のブルーリボン賞を受賞できなかった大きな要因の一つが、その外装デザインによる」としている<ref name="2005-u-61"/>。また、運用上の問題として「途中駅利用に対応するための車両であるにもかかわらず、新宿から小田原まで無停車の『スーパーはこね』に運用するなど、製作趣旨の徹底が不十分であった」ともしている<ref name="2005-u-61"/>。\n\n1999年までに4両固定編成・6両固定編成とも7編成が製造され<ref name="rp679-239"/>、これによってNSE車は「ゆめ70」に改装された車両を除いて淘汰された<ref name="rp829-282"/>。1999年に増備された編成では、座席の表地が4両固定編成・6両固定編成とも同じものとなり、その後他の車両も同一の表地に交換された。EXE車の投入と、途中駅を重視した特急施策によって、年間利用者数は1987年に1,100万人だったものが2003年には1,400万人に増加した<ref name="rj464-33"/>。\n\nEXE車は登場直後から小田急の広告ポスターなどでイメージリーダーとして起用されていた<ref name="rj464-33"/>が、箱根特急の利用者数は1987年の550万人から、2003年には300万人程度に減少していた<ref name="rj464-33"/>。箱根を訪れる観光客の減少も理由ではあったが、観光客全体の減少率が15[[パーセント|%]]程度であるのに対し<ref name="rj464-33"/>、箱根特急の利用者数は45%も減少していたのである<ref name="rj464-33"/>。この要因を調べると、EXE車には「小田急ロマンスカーのイメージ」とされた展望席が存在しなかったために他の交通手段に転移したとみられた<ref name="rj464-33"/>。2002年からはイメージリーダーとして起用される車両はHiSE車に変更された<ref name="rj464-34"/>。\n\nEXE車は登場以来、新宿駅へは[[臨時列車]]や突発的な運用変更がない限り10両編成で乗り入れていた<ref name="rp829-210"/>が、2003年3月29日のダイヤ改正からは平日の「はこね」2往復が全区間6両編成で運行されることになった<ref name="rp829-210"/>。6両編成で新宿駅に乗り入れる運用は初めてであった<ref name="rp829-210"/>が、この運用は2004年12月11日のダイヤ改正で見られなくなった<ref name="rp829-212"/>が、2009年3月14日のダイヤ改正では、平日の「はこね」1往復が全区間6両編成で運行されることになった<ref name="rp829-217"/>。\n\n2002年2月1日から3月31日まで、各編成の1号車で[[IPv6]]を用いた[[無線LAN]][[インターネット]]接続実験が行われ、<ref>{{cite conference |url=http://warp.ndl.go.jp/info:ndljp/pid/283520/www.soumu.go.jp/joho_tsusin/policyreports/joho_tsusin/joho_bukai/pdf/020412_1_4.pdf |title=無線LANを用いたモバイル・インターネットサービスの研究開発 平成13年度の活動について |author= ノキア・ジャパン|authorlink= |coauthors= |date=2002-04-12 |publisher= |booktitle= |page=7 |location= |id= }}</ref>2012年からはWiMAXをバックホールとする「au Wi-Fi SPOT」と「Wi2 300」を民鉄の有料特急としては初めて導入した<ref>[http://www.odakyu.jp/program/info/data.info/7713_4317860_.pdf#search=%27%E5%B0%8F%E7%94%B0%E6%80%A5exe+%E7%84%A1%E7%B7%9Alan%27 民鉄有料特急初の公衆無線ＬＡＮサービス登場！ ロマンスカー・ＥＸＥに「au Wi-Fi SPOT」を導入 －今後、小田急外国人旅行センターなど、サービスを駅に拡充していきます－ ]</ref>。（登場してから10年余り経過した2007年には、日本デザイン振興会よりロングライフデザイン賞を受賞した<ref>{{Cite web|author=[http://www.g-mark.org/ 日本デザイン振興会]|url=http://www.g-mark.org/award/detail.html?id=23365&lang=ja|title=Good Design Award|work=|publisher=|language=日本語|accessdate=2011-10-10}}</ref>。\n\n== 編成表 ==\n; 凡例 : Tc…[[制御車]]、M…[[動力車|電動車]]、CON…[[主制御器|制御装置]]、SIV…補助電源装置、CP…[[圧縮機|電動空気圧縮機]]、PT…[[集電装置]]<br/>乗 …乗務員室、車…車椅子対応座席、売…売店、自…自動販売機、電…[[公衆電話]]、WC…[[列車便所|トイレ]]・[[洗面器#洗面台・洗面所|化粧室]]、VWC…車椅子対応トイレ・化粧室、AED…[[自動体外式除細動器]]\n\n<!--#857971はハーモニックパールブロンズ 鉄道ピクトリアル通巻829号（2010年1月号臨時増刊）「特集・小田急電鉄」p191の表から色を抽出-->\n{|style="text-align:left;"\n|-\n|\n{| class="wikitable" style="text-align:center; font-size:80%; margin:1em 0em 2em 3em;"\n|-\n|style="border-bottom:solid 3px #857971; background-color:#ccc;"|&nbsp;\n|style="border-bottom:solid 3px #857971;" colspan="6"|{{TrainDirection|[[箱根湯本駅|箱根湯本]]・[[小田原駅|小田原]]|[[新宿駅|新宿]]}}\n|-\n!号車\n| 1 || 2 || 3 || 4 || 5 || 6\n|-\n!形式\n| '''クハ30050''' || '''デハ30000''' || '''サハ30050''' || '''サハ30050''' || '''デハ30000''' || '''クハ30050'''\n|-\n!style="border-bottom:solid 3px #BE0032;"|区分\n|style="border-bottom:solid 3px #BE0032;"| 30550<br/>(Tc2) ||style="border-bottom:solid 3px #BE0032;"| 30500<br/>(M2) ||style="border-bottom:solid 3px #BE0032;"| 30450<br/>(T2) ||style="border-bottom:solid 3px #BE0032;"| 30350<br/>(T1) ||style="border-bottom:solid 3px #BE0032;"| 30200<br/>(M1') ||style="border-bottom:solid 3px #BE0032;"| 30250<br/>(Tc1')\n|-\n![[鉄道の車両番号|車両番号]]\n| 30551<br/>∥<br/>30557 || 30501<br/>∥<br/>30507 || 30451<br/>∥<br/>30457 || 30351<br/>∥<br/>30357 || 30201<br/>∥<br/>30207 || 30251<br/>∥<br/>30257\n|-\n!搭載機器\n| CP || CON,PT || SIV,PT || SIV || CON,PT || CP\n|-\n!style="border-bottom:solid 3px green;"|自重\n|style="border-bottom:solid 3px green;"| 33.8t ||style="border-bottom:solid 3px green;"| 41.8t ||style="border-bottom:solid 3px green;"| 36.9t ||style="border-bottom:solid 3px green;"| 35.8t ||style="border-bottom:solid 3px green;"| 41.8t ||style="border-bottom:solid 3px green;"| 34.7t\n|-\n!車内設備\n| 乗 || WC|| 売、自、電|| 電|| 車、VWC|| 乗、AED\n|-\n!定員\n| 56 || 60 || 56 || 68 || 58 ||60\n|}\n|\n{| class="wikitable" style="text-align:center; font-size:80%; margin:1em 0em 2em 3em;"\n|-\n|style="border-bottom:solid 3px #857971; background-color:#ccc;"|&nbsp;\n|style="border-bottom:solid 3px #857971;" colspan="6"|{{TrainDirection|[[小田原駅|小田原]]・[[藤沢駅|藤沢]]|[[新宿駅|新宿]]・[[片瀬江ノ島駅|片瀬江ノ島]]}}\n|-\n!号車\n| 7 || 8 || 9 || 10\n|-\n!形式\n| '''クハ30050''' || '''デハ30000''' || '''デハ30000''' || '''クハ30050'''\n|-\n!style="border-bottom:solid 3px #BE0032;"|区分\n|style="border-bottom:solid 3px #BE0032;"| 30150<br/>(Tc2') ||style="border-bottom:solid 3px #BE0032;"| 30100<br/>(M2') ||style="border-bottom:solid 3px #BE0032;"| 30000<br/>(M1) ||style="border-bottom:solid 3px #BE0032;"| 30050<br/>(Tc1)\n|-\n!車両番号\n| 30151<br/>∥<br/>30157 || 30101<br/>∥<br/>30107 || 30001<br/>∥<br/>30007 || 30051<br/>∥<br/>30057\n|-\n!搭載機器\n| SIV,CP || CON,PT || SIV,PT || CP\n|-\n!style="border-bottom:solid 3px blue;"|自重\n|style="border-bottom:solid 3px blue;"| 36.3t ||style="border-bottom:solid 3px blue;"| 42.7t ||style="border-bottom:solid 3px blue;"| 39.1t ||style="border-bottom:solid 3px blue;"| 33.8t\n|-\n!車内設備\n| 乗、AED || 車、WC|| 売、自、電|| 乗\n|-\n!定員\n| 60 || 58 || 56 || 56\n|}\n|}\n\n== 脚注 ==\n{{脚注ヘルプ}}\n\n=== 注釈 ===\n{{Reflist|group="注釈"}}\n\n=== 出典 ===\n{{Reflist|2|refs=\n<ref name="dj145-15">[[#DJ145|『鉄道ダイヤ情報』通巻145号 p.15]]</ref>\n<ref name="dj145-31">[[#DJ145|『鉄道ダイヤ情報』通巻145号 p.31]]</ref>\n<ref name="dj145-34">[[#DB145|『鉄道ダイヤ情報』通巻145号 p.34]]</ref>\n<ref name="dj145-42">[[#開発145|『鉄道ダイヤ情報』通巻145号 p.42]]</ref>\n<ref name="dj145-43">[[#開発145|『鉄道ダイヤ情報』通巻145号 p.43]]</ref>\n<ref name="dj145-44">[[#開発145|『鉄道ダイヤ情報』通巻145号 p.44]]</ref>\n<ref name="2002-o-32">[[#大幡2002|大幡 (2002) p.32]]</ref>\n<ref name="2005-u-167">[[#生方2005|生方 (2005) p.167]]</ref>\n<ref name="2005-u-58">[[#生方2005|生方 (2005) p.58]]</ref>\n<ref name="2005-u-59">[[#生方2005|生方 (2005) p.59]]</ref>\n<ref name="2005-u-61">[[#生方2005|生方 (2005) p.61]]</ref>\n<ref name="rf421-55">[[#飯塚421|『鉄道ファン』通巻421号 p.55]]</ref>\n<ref name="rf421-56">[[#飯塚421|『鉄道ファン』通巻421号 p.56]]</ref>\n<ref name="rf421-5657">[[#飯塚421|『鉄道ファン』通巻421号 pp.56-57]]</ref>\n<ref name="rf421-57">[[#飯塚421|『鉄道ファン』通巻421号 p.57]]</ref>\n<ref name="rf421-58">[[#飯塚421|『鉄道ファン』通巻421号 p.58]]</ref>\n<ref name="rf421-5859">[[#飯塚421|『鉄道ファン』通巻421号 pp.58-59]]</ref>\n<ref name="rf421-59">[[#飯塚421|『鉄道ファン』通巻421号 p.59]]</ref>\n<ref name="rf421-60">[[#飯塚421|『鉄道ファン』通巻421号 p.60]]</ref>\n<ref name="rf421-61">[[#飯塚421|『鉄道ファン』通巻421号 p.61]]</ref>\n<ref name="rf421-6162">[[#飯塚421|『鉄道ファン』通巻421号 pp.61-62]]</ref>\n<ref name="rf421-63">[[#飯塚421|『鉄道ファン』通巻421号 p.63]]</ref>\n<ref name="rf421-64">[[#飯塚421|『鉄道ファン』通巻421号 p.64]]</ref>\n<ref name="rf421-64">[[#飯塚421|『鉄道ファン』通巻421号 p.64]]</ref>\n<ref name="rf421-RF22405">[[#飯塚421|『鉄道ファン』通巻421号付図 (RF22405) ]]</ref>\n<ref name="rf421-RF22407">[[#飯塚421|『鉄道ファン』通巻421号付図 (RF22407) ]]</ref>\n<ref name="rf422-23">[[#RF422|『鉄道ファン』通巻422号 p.23]]</ref>\n<ref name="rf422-23">[[#RF422|『鉄道ファン』通巻422号 p.23]]</ref>\n<ref name="rj464-33">[[#RJ464|『鉄道ジャーナル』通巻464号 p.33]]</ref>\n<ref name="rj464-34">[[#RJ464|『鉄道ジャーナル』通巻464号 p.34]]</ref>\n<ref name="rp679-239">[[#大幡679|『鉄道ピクトリアル』通巻679号 p.239]]</ref>\n<ref name="rp679-240">[[#大幡679|『鉄道ピクトリアル』通巻679号 p.240]]</ref>\n<ref name="rp679-240241">[[#大幡679|『鉄道ピクトリアル』通巻679号 pp.240-241]]</ref>\n<ref name="rp679-241">[[#大幡679|『鉄道ピクトリアル』通巻679号 p.241]]</ref>\n<ref name="rp679-242">[[#大幡679|『鉄道ピクトリアル』通巻679号 p.242]]</ref>\n<ref name="rp679-39">[[#草門679|『鉄道ピクトリアル』通巻679号 p.39]]</ref>\n<ref name="rp829-190">[[#中山829|『鉄道ピクトリアル』通巻829号 p.190]]</ref>\n<ref name="rp829-210">[[#杉田829|『鉄道ピクトリアル』通巻829号 p.210]]</ref>\n<ref name="rp829-212">[[#杉田829|『鉄道ピクトリアル』通巻829号 p.212]]</ref>\n<ref name="rp829-217">[[#杉田829|『鉄道ピクトリアル』通巻829号 p.217]]</ref>\n<ref name="rp829-280">[[#岸上829|『鉄道ピクトリアル』通巻829号 p.280]]</ref>\n<ref name="rp829-281">[[#岸上829|『鉄道ピクトリアル』通巻829号 p.281]]</ref>\n<ref name="rp829-282">[[#岸上829|『鉄道ピクトリアル』通巻829号 p.282]]</ref>\n<ref name="rp829-306">[[#岸上829-1|『鉄道ピクトリアル』通巻829号 p.306]]</ref>\n<ref name="rp829-317">[[#岸上829-2|『鉄道ピクトリアル』通巻829号 p.317]]</ref>\n}}\n\n== 参考文献 ==\n=== 書籍 ===\n* {{Cite book|和書|author = 生方良雄|authorlink = |coauthors = |year = 2005|title = 小田急ロマンスカー総覧|publisher = 大正出版|ref = 生方2005|id = |isbn = 4811706552}}\n* {{Cite book|和書|author = 大幡哲海|authorlink = |coauthors = |year = 2002|title = 小田急電鉄の車両|publisher = [[JTBパブリッシング]]|ref = 大幡2002|id = |isbn = 4533044697}}\n\n=== 雑誌記事 ===\n* {{Cite journal|和書|author=飯塚豊彦 |year=1996 |month=5 |title=小田急30000形 |journal=[[鉄道ファン (雑誌)|鉄道ファン]] |issue=421 |pages= 54-64 |publisher=[[交友社]] |ref = 飯塚421}}\n* {{Cite journal|和書|author=大幡哲海 |year=1999 |month=12 |title=私鉄車両めぐり164 小田急電鉄 |journal=鉄道ピクトリアル |issue=679 |pages= 201-243 |publisher=電気車研究会 |ref = 大幡679}}\n* {{Cite journal|和書|author=岸上明彦 |year=2010 |month=1 |title=小田急電鉄現有車両プロフィール |journal=鉄道ピクトリアル |issue= 829|pages= 241-295 |publisher=電気車研究会 |ref = 岸上829}}\n* {{Cite journal|和書|author=岸上明彦 |year=2010 |month=1 |title=小田急電鉄 車歴表 |journal=鉄道ピクトリアル |issue=829 |pages= 300-309 |publisher=電気車研究会 |ref = 岸上829-1}}\n* {{Cite journal|和書|author=岸上明彦 |year=2010 |month=1 |title=小田急電鉄 主要諸元表 |journal=鉄道ピクトリアル |issue=829 |pages= 310-318 |publisher=電気車研究会 |ref = 岸上829-2}}\n* {{Cite journal|和書|author=草門隆 |year=1999 |month=12 |title=車両総説 |journal=鉄道ピクトリアル |issue=679 |pages= 36-41 |publisher=電気車研究会 |ref = 草門679 }}\n* {{Cite journal|和書|author=杉田弘志 |year=2010 |month=1 |title=小田急電鉄 列車運転の変遷とその興味 |journal=鉄道ピクトリアル|issue=829 |pages= 204-219 |publisher=電気車研究会 |ref = 杉田829}}\n* {{Cite journal|和書|author=鶴通孝・山﨑友也 |year=2005 |month=6 |title=列車追跡シリーズ548 何度でも乗ってみたい特急ロマンスカー わくわくの85分 |journal=[[鉄道ジャーナル]] |issue=464 |pages= 25-35 |publisher=鉄道ジャーナル社 |ref = RJ464}}\n* {{Cite journal|和書|author=中山嘉彦 |year=2010 |month=1 |title=小田急車両 -音と色- |journal= 鉄道ピクトリアル|issue=829 |pages= 189-191 |publisher=電気車研究会 |ref = 中山829}}\n* {{Cite journal|和書|author= |year=1996 |month=5 |title=EXE 115DAYS |journal=[[鉄道ダイヤ情報]] |issue=145 |pages= 14-32 |publisher=[[交通新聞社|弘済出版社]] |ref = DJ145}}\n* {{Cite journal|和書|author= |year=1996 |month=5 |title=小田急DATA BANK |journal= 鉄道ダイヤ情報|issue=145 |pages= 33-41 |publisher= 弘済出版社|ref = DB145}}\n* {{Cite journal|和書|author= |year=1996 |month=5 |title=開発担当者 EXEを語る |journal= 鉄道ダイヤ情報|issue=145 |pages= 42-48 |publisher= 弘済出版社|ref = 開発145}}\n* {{Cite journal|和書|author= |year=1996 |month=5 |title=小田急ロマンスカー |journal=鉄道ファン |issue=422 |pages= 8-29 |publisher=交友社 |ref = RF422}}\n\n<!--\n== 関連項目 ==\n<-->\n\n== 外部リンク ==\n* [http://www.odakyu.jp/romancecar/line_up/30000/ EXE（30000形）] - 小田急電鉄\n\n{{Commonscat|Odakyu 30000 series EXE}}\n{{小田急ロマンスカー}}\n{{小田急電鉄の車両}}\n{{DEFAULTSORT:おたきゆう30000かたてんしや}}\n[[Category:小田急電鉄の電車|30000]]\n[[Category:1996年製の鉄道車両|おたきゆう電30000]]\n[[Category:日本車輌製造製の電車]]\n[[Category:川崎重工業製の電車]]\n[[Category:グッドデザイン賞]]	</BODY>
  <MECAB>小田急30000形電車  ''' 小田急30000形電車 '''（ おだきゅう 30000 が たでん しゃ ） は 、 [[ 1996年 ]] に [[ 小田急電鉄 ]]（ 小田急 ） が 運用 を 開始 し た < ref name =" rp 679 - 39 "/>[[ 特急形車両 | 特急 用 車両 ]]<!-- 小田急 で は 「 特急 形 」 という 区分 で は ない ため 。 2300 形 の 登場 当時 は 竣功 図 に 「 優等 電動 客車 」 という よう に 書い て ある よう です が -->（[[ 小田急ロマンスカー | ロマンスカー ]]） で ある 。 
特急 ロマンスカー に 使用 さ れ て い た [[ 小田急3100形電車 | 3100形 （ NSE 車 ）]] の 置き換え を 目的 として 登場 し た < ref name =" rp 829 - 280 "/> 特急 車両 で 、 特急 ロマンスカー の 利用実態 の 変化 に 対応 し < ref name =" rp 679 - 239 "/>、 単位 輸送 力 の 増強 を 行っ た 上 で < ref name =" rp 679 - 239 "/>、 観光 輸送 だけ で は なく ビジネス 利用 を 強く 意識 し た 車両 と し た < ref name =" rp 679 - 39 "/>。 また 、 小田急 の 特急 車両 で は 初めて [[ 可変電圧可変周波数制御 | VVVFインバータ制御 ]] を 採用 し た < ref name =" rp 829 - 280 "/>。 " Excellent Express " を 略し て 「 EXE （ エクセ ） 」 という 愛称 が 設定 さ れ 、 1996年 に は 当時 の [[ 通商産業省 ]] より [[ グッドデザイン賞 | グッド デザイン 商品 ]] に 選定 さ れ た < ref name =" rp 829 - 280 "/>。[[ 鉄道友の会 ]] に [[ ブルーリボン賞 ( 鉄道 )| ブルーリボン賞 ]] の 制度 が 創設 さ れ て 以来 、 小田急 の 特急 車両 で 唯一 ブルーリボン賞 を 受賞 し て い ない 車両 で ある < ref name =" 2005 - u - 61 "/>。 
小田急 で は 、 編成 表記 の 際 に は 「 [[ 新宿駅 | 新宿 ]] 寄り 先頭 車両 の [[ 鉄道の車両番号 | 車両番号 ]]（ 新宿 方 の 車 号 ） × 両 数 」 という 表記 を 使用 し て いる < ref name =" dj 145 - 15 "/> ため 、 本 項 も それ に 倣い 、 特定 の 編成 を 表記 する 際 に は 「 30051 × 4 」 「 30251 × 6 」 の よう に 表記 する 。 また 、 [[ 小田急3100形電車 | 3100形 ]] は 「 NSE 車 」 、 [[ 小田急7000形電車 | 7000形 ]] は 「 LSE 車 」 、 [[ 小田急10000形電車 | 10000形 ]] は 「 HiSE 車 」 、 本 形式 30000 形 は 「 EXE 車 」 、 [[ 箱根登山鉄道 ]][[ 箱根湯本駅 ]] へ 乗り入れる 特急 列車 について は 「 箱根 特急 」 と 表記 する 。 
小田急 の 特急 ロマンスカー は もともと [[ 箱根町 | 箱根 ]] へ の 観光客 が 対象 で あり < ref name =" 2005 - u - 58 "/>、 箱根 特急 の 途中駅 停車 も 元来 は 沿線 在住 の 箱根 観光客 を 対象 と し た もの で あっ た < ref name =" 2005 - u - 58 "/>。 しかし 、 時代 の 進展 とともに 利用実態 は 変化 し 、 観光客 以外 の 日常 利用 が 増加 し て い た < ref name =" 2005 - u - 58 "/> ほか 、 1967年 より [[ 回送 ]] 列車 を 客扱い する こと から 始まっ た 通勤 用 の 特急 列車 の 利用者 数 も 増加 し て おり < ref name =" 2005 - u - 58 "/>、 輸送力 が 不足 し て い た < ref name =" dj 145 - 42 "/>。 一方 で 、 NSE 車 は 更新 修繕 など が 行なわ れ て は い た ものの 車 齢 30年 を 超え て おり < ref name =" rp 679 - 239 "/>、 代替 の 車両 について 検討 が 行なわ れ て い た < ref name =" rp 679 - 239 "/>。 
この ため 、 NSE 車 を 置き換える と 同時に 、 変化 し た 利用実態 に 対応 し た 車両 を 製作 する こと に なっ た < ref name =" rp 679 - 239 "/>。 設計 に際して は 、 小田急 や 車両 メーカー の ほか に [[ 小田急百貨店 ]] の インテリアデザイナー や 外部 の グラフィックデザイナー も 交え て 検討 が 行なわ れ た < ref name =" dj 145 - 44 "/>。 検討 過程 で は [[ ボギー台車 | ボギー車 ]] の 方 が 定員 増 が 可能 で ある と 判断 さ れ < ref name =" dj 145 - 42 "/>、[[ 連接台車 | 連接 構造 ]] は 採用 さ れ なかっ た < ref name =" dj 145 - 42 "/>。 また 、 [[ 増解結 | 分割 ・ 併合 ]] を 行なう 際 に 通り抜け 可能 な 貫通 路 を 設ける こと と し た < ref name =" dj 145 - 43 "/> が 、 この 構造 で は 前面 [[ 展望車 | 展望 席 ]] の 設置 は 困難 で ある こと < ref name =" dj 145 - 42 "/> や 、 乗務員 交代 が 短時間 で 可能 な こと を 考慮 し < ref name =" dj 145 - 42 "/>、 前面 展望 席 は 採用 さ れ ない こと に なっ た < ref name =" dj 145 - 42 "/>。 
こうして 、 それ まで の 特急 ロマンスカー と は 一線 を 画す 特急 車両 として < ref name =" rf 421 - 56 "/> 登場 し た の が EXE 車 で ある 。 
本節 で は 、 登場 当時 の 仕様 を 基本 として 、 増 備 途上 で の 変更 点 を 個別 に 記述 する 。 更新 による 変更 について は 沿革 で 後述 する 。 
EXE 車 は 単位 輸送 力 の 増強 とともに < ref name =" rf 421 - 55 "/>、 弾力 的 な 運用 を 行なう こと を 可能 と する ため < ref name =" rf 421 - 55 "/>、 全長 20 [[ メートル | m ]] の 車両 による 4 両 固定 編成 と 6 両 固定 編成 が 製造 さ れ 、 分割 ・ 併合 に 対応 し た 10両編成 と し た < ref name =" rf 421 - 56 "/>。 形式 は 先頭 車 が [[ 制御車 ]] の クハ 30050 形 で < ref name =" rf 421 - 64 "/>、 中間 車 は [[ 動力車 | 電動 車 ]] の デハ 30000 形 < ref name =" rf 421 - 64 "/> と [[ 付随車 ]] の サハ 30050 形 で ある < ref name =" rf 421 - 64 "/>。 サハ 30050 形 は 6 両 固定 編成 に のみ 連結 さ れる < ref name =" rf 421 - 64 "/>。 車両番号 について は 、 [[# 編成 表 | 巻末 の 編成 表 ]] を 参照 の こと 。 
先頭 車 ・ 中間 車 とも 車体 長 19 , 500 [[ ミリメートル | mm ]] で < ref name =" rf 421 - 64 "/>、 全長 は 先頭 車 が 19 , 750m m < ref name =" rf 421 - 64 "/>、 中間 車 が 20 , 000 mm < ref name =" rf 421 - 64 "/> で 、 車体 幅 は 2 , 900m m で ある < ref name =" rf 421 - 64 "/>。 車体 は 屋根 板 や 床板 に [[ ステンレス鋼 ]] を 使用 < ref name =" rp 679 - 240 "/>、 それ 以外 の 箇所 は [[ 炭素鋼 | 普通 鋼 ]] 製 で ある < ref name =" rp 679 - 240 "/>。 
先頭 形状 は 2種類 存在 し 、 10両編成 組成 時 に 両端 と なる 1号 車 と 10号 車 について は 正面 に [[ 貫通扉 ]] の ない 非 貫通 型 で < ref name =" 2002 - o - 32 "/>、 やや 傾斜 し た 形状 と し て いる < ref name =" rf 421 - 56 "/>。 これ に対し 、 10両編成 組成 時 に 中間 に 入る 6号 車 と 7号 車 について は 正面 に 貫通扉 が 設け られ た 貫通 型 で < ref name =" 2002 - o - 32 "/>、 切妻 に 近い 程度 の 緩い 傾斜 が つけ られ て いる < ref name =" rf 421 - 56 "/>。 6号 車 と 7号 車 の 正面 貫通扉 は 両開き 式 [[ プラグドア ]] である < ref name =" rf 421 - 5859 "/>。 いずれ の 先頭 車 も 、 [[ 操縦席 | 運転 室 ]] は 通常 の 床 高さ に 設置 さ れ た < ref name =" dj 145 - 43 "/>。 
側面 客 用 扉 は 各 車両 とも 1 箇所 で 、 片開き 引戸 が 採用 さ れ < ref name =" 2002 - o - 32 "/>、 扉 幅 は [[ 車椅子 ]] 対応 座席 の ある 2号 車 ・ 5号 車 ・ 8号 車 は 1 , 000 mm 幅 < ref name =" rf 421 - 57 "/>、 それ 以外 の 車両 は 800m m 幅 と し た < ref name =" rf 421 - 57 "/>。 客 用 扉 は [[ ハニカム構造 | ペーパー ハニカム構造 ]] と し < ref name =" rf 421 - 57 "/>、 指 はさみ 防止 や 遮音 効果 、 曇り 止め など の 目的 で [[ 複層ガラス ]] を 採用 し た < ref name =" rf 421 - 57 "/>。 1997年 の 増 備 車 から は 、 車体 外部 扉 脇 妻板 に [[ 自動ドア # 半自動 | 半自動 ]] 扱い の ドア スイッチ を 設置 し た 。 各 扉 上部 に は 雨 樋 を 設け た < ref name =" rf 421 - 5657 "/>。 
側面 窓 は 、 熱線 吸収 率 の 高い ガラス を 使用 し た < ref name =" rf 421 - 57 "/> 連続 窓 風 の 外観 と し た が 、 外部 の ガラス 面積 を 高さ 1 , 250m m に 拡大 し た < ref name =" rf 421 - RF 22405 "/>。 全て の 客 用 扉 脇 の 客室 窓 上部 に は 列車 名 や 行き先 を 表示 する [[ 発光ダイオード | LED ]] 式 [[ 方向幕 | 表示 器 ]] が 設置 さ れ た < ref group =" 注釈 "> RSE 車 で は 「 [[ あさぎり ( 列車 )| あさぎり ]]」 で の 運行 時 以外 列車 名 のみ の 表示 だっ た が 、 EXE 車 では 号 数 を 含ん だ 列車 名 と 行先 が 表示 さ れる 。 </ ref >。 車両 間 の 貫通 路 は 750m m 幅 で < ref name =" rf 421 - RF 22405 "/>、 6号 車 ・ 7号 車 の 前面 貫通 路 は 550m m 幅 で ある < ref name =" rf 421 - RF 22407 "/>。 各 車両 の 連結 面 間 に は [[ 転落防止幌 ]] を 設置 し た < ref name =" rf 421 - 56 "/>。 
塗装 デザイン は 全体 を メタリック 系 の ハーモニックパールブロンズ < ref name =" rf 421 - 57 "/> と し 、 「 小田急ロマンスカー 」 の シンボル カラー として < ref name =" rf 421 - 57 "/> アッパー レッド の ワンポイント ライン を 入れ た < ref name =" rf 421 - 57 "/>。 正面 の ワンポイント ライン に は " EXE " と 文字 が 入る が 、 小田急ロマンスカー で 車両 愛称 が 車体 外部 に 表示 さ れる の は 初めて で ある < ref name =" rf 422 - 23 "/>。 これ は 、 10年 経っ て も 飽き の こない デザイン を 意図 し た もの で ある < ref name =" 2005 - u - 59 "/>。 
内装 は 、 安らぎ と 落ち着き の ある 高級感 の 演出 を 図っ た もの と し た < ref name =" rf 421 - 57 "/>。 
[[ 鉄道車両の座席 | 座席 ]] は [[ 鉄道車両の座席 # 回転 式 クロスシート （ 回転 腰掛 ）| 回転 式 ]][[ リクライニングシート ]] を 採用 < ref name =" rp 679 - 241 "/>、[[ 座席 # シート ピッチ | シート ピッチ ]] 1 , 000 mm で 配置 し た < ref name =" rp 829 - 281 "/>。 各 座席 の 肘掛 に は 収納 式 テーブル を 設置 し た < ref name =" rf 421 - 60 "/>。 一斉 回転 機構 は 電動 式 が 採用 さ れ た < ref name =" 2002 - o - 34 ">[[# 大幡 2002 | 大幡 ( 2002 ) p . 34 ]]</ ref >。 座席 表地 は 1号 車 から 6号 車 まで が 緑 系統 < ref name =" rf 421 - 57 "/>、 7号 車 から 10号 車 まで は 青 系統 の 色 と する < ref name =" rf 421 - 57 "/> こと で 、 分割 運用 時 における 行先 別 対応 と し た < ref name =" rf 421 - 57 "/>。 1999年 の 増 備 車 で は 、 全 車両 の 座席 の 表地 を グレー と 茶色 系 の ツートーン と し た < ref name =" rp 679 - 242 "/>。 
客室 の 壁面 は グレー 系統 で まとめ < ref name =" rf 421 - 57 "/>、 出入 台 や 売店 部分 は 客室 と は 異なる 青 系統 の 配色 と し た < ref name =" rp 679 - 240241 "/>。 客室 内 の 照明 は 電球 色 の [[ 蛍光灯 ]] を 使用 し た 間接照明 と し < ref name =" rf 421 - 60 "/>、 蛍光灯 の カバー に 丸 穴 を 開ける こと で アクセント と し た < ref name =" rf 421 - 60 "/>。 また 、 [[ 網棚 | 荷物 棚 ]] 下 に は 蛍光灯 の 直接照明 を 設置 < ref name =" rf 421 - 60 "/>、 光 の 拡散 を 抑える ため 集 光 板 を 備え た < ref name =" rf 421 - 60 "/>。 客室 と 出入 台 の 間 に ある 仕切り 扉 は 、 車椅子 対応 座席 の ある 2号 車 ・ 5号 車 ・ 8号 車 は 900m m 幅 < ref name =" rp 679 - 241 "/>、 それ 以外 の 箇所 は 700m m 幅 と し た < ref name =" rp 679 - 241 "/>。 1999年 の 増 備 車 から は [[ 車内案内表示装置 | 車内 案内 装置 ]] において [[ 文字 多重 放送 | FM 文字 多重 装置 ]]「[[ パパラビジョン ]]」 を 搭載 し た < ref name =" rp 679 - 242 "/>。 
3号 車 の 新宿 側 車 端 部 < ref name =" rf 421 - 58 "/> と 9号 車 の [[ 小田原駅 | 小田原 ]] 側 車 端 部 < ref name =" rf 421 - 59 "/> に は 売店 と [[ 清涼飲料水 ]][[ 自動販売機 ]] を 設置 し た < ref name =" rp 829 - 281 "/>。 売店 の カウンター と 、 後述 の 化粧 室 に は [[ 人工大理石 ]] を 使用 し た < ref name =" rf 421 - 60 "/>。[[ テレホンカード ]] 式 [[ 公衆電話 ]] を 3号 車 ・ 4号 車 ・ 9号 車 に 設置 し た < ref name =" rf 421 - 61 "/> ほか 、 6号 車 ・ 7号 車 を 除く 各 車両 の 出入 台 に は [[ 分別収集 | 分別 回収 ]] が 可能 な [[ ごみ箱 | ゴミ箱 ]] を 設置 し た < ref name =" rf 421 - 61 "/>。 
2号 車 の 新宿 側 車 端 部 < ref name =" rf 421 - 60 "/> と 5号 車 ・ 8号 車 の 小田原 側 車 端 部 < ref name =" rf 421 - 60 "/> に は 男女 共用 [[ 便器 # 腰掛 大便 器 （ 洋式 ・ 洋風 大便 器 ）| 洋式 ]][[ 列車便所 | トイレ ]] ・ 男性 [[ 便器 # 小便器 | 小用 トイレ ]] ・ [[ 洗面器 # 洗面 台 ・ 洗面所 | 化粧 室 ]] を 配置 し た < ref name =" rf 421 - 60 "/>。 この うち 5号 車 の 男女共用トイレ について は 車椅子 対応 と なっ て おり 、 扉 を 自動 開閉 式 と し た ほか < ref name =" rf 421 - 60 "/> ベビーベッド も 設け た < ref name =" rf 421 - 60 "/>。 汚物 処理 装置 は それ まで の 小田急 の 車両 で 使用 さ れ て い た 循環 式 から 真空 式 に 変更 し た < ref name =" rf 421 - 60 "/>。 1997年 の 増 備 車 から は 、 男性 小用 トイレ の 扉 が 開き戸 から 折戸 に 変更 さ れ た < ref name =" rp 679 - 242 "/>。 
[[ 運転士 ]] が 乗務 する 乗務員 室 （ 運転 室 ） は 、 貫通 型 と 非 貫通 型 で は 構造 が 異なっ て いる 。 共通 事項 として 、 運転 に 必要 な 機器 類 は 運転 席 周り に 集約 し < ref name =" rf 421 - 61 "/>、[[ マスター・コントローラー | 主幹 制御 器 ]] を 右手 操作 の ワン ハンドル 式 と し た ほか < ref name =" rf 421 - 61 "/>、 カラー 液晶 モニタ 表示 器 を 設け た < ref name =" rf 421 - 61 "/>。 また 、 乗務員 が 60秒間 [[ 前照灯 | 前 灯 ]] ・ [[ 警笛 ]] ・ 主幹 制御 器 の 操作 を 行わ なかっ た 場合 に 警報 を 発し < ref name =" rf 421 - 64 "/>、 それでも 操作 が なかっ た 場合 に 非常 制動 を 動作 さ せる [[ 緊急列車停止装置 | EB装置 ]] を 設置 し た < ref name =" rf 421 - 64 "/>。 非 貫通 型 の 運転 台 は 前面 に 大型 ガラス を 採用 し < ref name =" rf 421 - 61 "/>、 客室 と の 仕切り 窓 も 大型 化 する こと で 客室 内 から の 展望 を 考慮 し た < ref name =" rf 421 - 61 "/>。 貫通 型 の 運転 台 で は 、 後述 する 「 自動 ほろ 装置 」 の 収納 スペース の 関係 から 2 室 に 分割 さ れ て いる < ref name =" rf 421 - 6162 "/>。 
EXE 車 で は 分割 ・ 併合 に 対応 する 機器 として 「 自動 ほろ 装置 」 を 設置 し た < ref name =" rf 421 - 62 ">[[# 飯塚 421 |『 鉄道ファン 』 通巻 421 号 p . 62 ]]</ ref >。 これ は 、 分割 ・ 併合 の 操作 を [[ 幌 | 貫通 幌 ]] の 連結 まで 自動的 に 行なう ため に 開発 ・ 導入 さ れ た < ref name =" dj 145 - 43 "/> もの で 、 2分 以内 に 連結 作業 が 終わる よう に した < ref name =" dj 145 - 45 ">[[# 開発 145 |『 鉄道ダイヤ情報 』 通巻 145 号 p . 45 ]]</ ref >。 曲線 上 でも 自動 連結 を 可能 と する ため 、 偏 位 自動 調整 装置 が 装備 さ れ て いる < ref name =" rf 421 - 62 "/>。 
[[ 主電動機 ]] について は 、 出力 195 [[ ワット | kW ]] の [[ かご形三相誘導電動機 ]] を 採用 し < ref name =" rf 421 - 63 "/>、 各 電動 台車 に 2 台 ずつ 装 架 し た 。 [[ 東洋電機製造 ]] TDK 6335 - A 形 と [[ 三菱電機 ]] MB - 5065 - A 形 を 併用 し て いる < ref name =" rp 679 - 241 "/>。[[ 主制御器 | 制御装置 ]] は 主電動機 を 1 個 単位 で 制御 する 個別 制御 方式 を 採用 し た [[ 絶縁ゲートバイポーラトランジスタ | IGBT ]][[ 半導体 素子 | 素子 ]] を 用い た [[ 可変電圧可変周波数制御 | VVVFインバータ制御 ]] で ある 。 4両編成 が 1 台 の 制御装置 で 6 台 の 主電動機 を 制御 する 方式 ( 1 C 6 M ) の [[ 東芝 ]] SVF - 024 A 形 を 8号 車 に 搭載 し < ref name =" rp 829 - 282 "/>、 6両編成 で は 1 台 の 制御装置 で 4 台 の 主電動機 を 制御 する 方式 ( 1 C4 M ) の 東芝 SVF - 024 B 形 を 2号 車 と 5号 車 に 搭載 し た < ref name =" rp 829 - 282 "/>。 SE 車 から RSE 車 まで の 特急 車両 に 引き続き 東芝 製 の 採用 で ある 。 個別 制御 方式 の 採用 により 電動機 1 台 を カット し て も 急 勾配 を 走行 できる 性能 を 有し た < ref name =" rf 421 - 63 "/>。 この ため 、 4 両 固定 編成 の 電動 車 比率 （[[ MT比 ]]） は 1 . 5 M2 . 5 T （ 主電動機 は 4 両 で 6 台 ）< ref name =" rf 421 - 63 "/>、 6 両 固定 編成 の 電動 車 比率 は 2 M4 T （ 主電動機 は 6 両 で 8 台 ） と し た < ref name =" rf 421 - 63 "/>< ref group =" 注釈 "> それ まで 、 小田急 の 車両 は 電動 車 が 編成 の 半分 以上 を 占める 編成 が 原則 だっ た が 、 EXE 車 で は MT比 を 1 : 2 と し 、 電動 車 が 編成 の 半数 を 下回る 構成 と なっ た 。 </ ref >。 4 両 固定 編成 と 6 両 固定 編成 で の 電動 車 比率 を 可能 な 限り 揃える ため < ref name =" rp 679 - 241 "/>、 4両編成 の 9号 車 新宿 側 の [[ 鉄道車両の台車 | 台車 ]] は 付随 台車 と し て いる < ref name =" rp 679 - 241 "/>。[[ 鉄道のブレーキ | 制動 装置 （ ブレーキ ）]] は [[ 電気指令式ブレーキ | 電気 指令 式 電磁 直通 制動 ]] で < ref name =" rp 679 - 241 "/>、 基礎 制動 装置 は シングル 式 （ 片 押し 式 ） で ある < ref name =" rp 679 - 241 "/>。 
台車 は 、 電動 台車 が [[ 住友金属工業 ]] 製 SS 146 < ref name =" rp 679 - 241 "/>、 付随 台車 が 住友金属工業 製 SS 046 を 採用 し た < ref name =" rp 679 - 241 "/>。 いずれ も [[ 小田急2000形電車 | 2000形 ]] で 採用 さ れ た モノ リンク 式 軸 箱 支持 形 [[ 鉄道車両の台車史 # ボルスタレス台車 | ボルスタレス台車 ]] を 特急 車両 向け に 改良 し た もの < ref name =" rp 679 - 241 "/> で 、 [[ 蛇行動 # ヨーダンパ | ヨーダンパ ]] を 装備 し て いる < ref name =" rf 421 - 62 "/>。 
[[ 集電装置 ]]（ パンタグラフ ） は [[ 集電装置 # Z 型 ・ シングルアーム 型 | シングルアーム 式 ]] の PT 7100 形 を 採用 < ref name =" rf 421 - 63 "/>、 2号 車 ・ 3号 車 ・ 5号 車 ・ 8号 車 ・ 9号 車 に 1 台 ずつ 搭載 し た < ref name =" rp 679 - 241 "/>。[[ エアー ・ コンディショナー | 冷房 装置 ]] について は 、 ヒーター を 内蔵 し た [[ 集約分散式冷房装置 | 集約 分散 式 ]] と し < ref name =" rf 421 - 63 "/>、 11 , 500 [[ カロリー | kcal / h ]] の 冷凍能力 を 有する 三菱電機 製 CU - 195 F 形 を 1 両 に 3 台 搭載 し た < ref name =" rp 679 - 241 "/>。 
補助 電源 装置 は 、 出力 140 [[ ボルト ( 単位 )| kV ]][[ アンペア | A ]] の IGBT 素子 式 [[ 静止形インバータ ]] ( IGBT - SIV ) を 7号 車 と 9号 車 に < ref name =" rp 829 - 282 "/>、 出力 200k VA の IGBT 素子 式 静止形インバータ を 3号 車 と 4号 車 に 搭載 し た < ref name =" rp 829 - 282 "/>。[[ 圧縮機 | 電動 空気 圧縮機 ]] ( CP ) について は 交流 スクロール 式 の RC 1500形 を 1号 車 ・ 6号 車 ・ 7号 車 ・ 10号 車 に 搭載 し た < ref name =" rp 829 - 282 "/>。 SE 車 から RSE 車 まで の 特急 車両 で 採用 さ れ て い た 電子 警報 器 （[[ 警笛 # ミュージックホーン | 補助 警報 音 ]] を 発する 装置 ） に 代え て 、 [[ 警笛 ]] に 電子 笛 が 採用 さ れ < ref name =" rp 679 - 241 "/>、 八幡 電気 産業 製 の YA - 95037 型 が 搭載 さ れ た < ref name =" rp 829 - 190 "/>。 
1996年 3月23日 の [[ 小田急電鉄のダイヤ改正 # 1990年代 - 特急 ロマンスカー の 新 展開 | ダイヤ改正 ]] から 運行 を 開始 し た < ref name =" dj 145 - 31 "/>。 当初 は 10両編成 が 2 編成 で 、 本 形式 の 特徴 を 生かし た 「 [[ はこね ( 列車 )| はこね ]]」 と 「 [[ えのしま ( 列車 )| えのしま ]]」 の 分割 ・ 併合 が ある 運用 に 投入 さ れ た < ref name =" rf 422 - 23 "/>。 また 、 検査 時 は HiSE 車 で 代走 する 箱根 特急 「 スーパーはこね 」 に も 運用 さ れ < ref name =" rf 422 - 23 "/>、 運用 初日 は 箱根湯本駅 で 到着 式 も 行なわ れ た < ref name =" dj 145 - 31 "/>。 また 、 平日 の 夕方 に 新宿 を 発車 する 通勤 向け の 特急 で ある 「 [[ ホームウェイ ( 列車 )| あしがら ]]」（ 当時 ）< ref group =" 注釈 "> 1999年 7月16日 から は 、 新宿 を 18時 以降 に 発車 する 特急 は 通勤 向け として 、 愛称 が 「 ホームウェイ 」 に 変更 さ れ た 。 </ ref > にも 投入 さ れ < ref name =" dj 145 - 34 "/>、 LSE 車 と 比較 し て 130人 以上 の 定員 増加 と なっ た < ref name =" rp 829 - 281 "/> EXE 車 は 、 輸送力 増強 に 貢献 し た 。 
しかし 、 運行 開始 直後 から [[ 鉄道ファン ]] から は 外装 デザイン に対して 否定 的 な 意見 が 多かっ た < ref name =" 2005 - u - 59 "/>。 運行 開始 翌年 と なる 1997年 ブルーリボン賞 について は 候補 車両 に さ れ た ものの 、 この 年 の ブルーリボン賞 は 「 該当 車 なし 」 と さ れ た < ref ></ ref >< ref group =" 注釈 "> 選考 対象 と なっ た 1997年 の 同 賞 で は 本 形式 の 得票数 が 最多 だっ た が 、 「 該当 なし 」 票 が それ を 上回っ た ため で ある 。 </ ref >。 小田急電鉄 OB の [[ 生方 良雄 ]] は 、 「 EXE 車 が 1997年 の ブルーリボン賞 を 受賞 でき なかっ た 大きな 要因 の 一つ が 、 その 外装 デザイン による 」 と し て いる < ref name =" 2005 - u - 61 "/>。 また 、 運用 上 の 問題 として 「 途中駅 利用 に 対応 する ため の 車両 である に も かかわら ず 、 新宿 から 小田原 まで 無 停車 の 『 スーパーはこね 』 に 運用 する など 、 製作 趣旨 の 徹底 が 不十分 で あっ た 」 と も し て いる < ref name =" 2005 - u - 61 "/>。 
1999年 まで に 4 両 固定 編成 ・ 6 両 固定 編成 とも 7 編成 が 製造 さ れ < ref name =" rp 679 - 239 "/>、 これ によって NSE 車 は 「 ゆめ 70 」 に 改装 さ れ た 車両 を 除い て 淘汰 さ れ た < ref name =" rp 829 - 282 "/>。 1999年 に 増 備 さ れ た 編成 で は 、 座席 の 表地 が 4 両 固定 編成 ・ 6 両 固定 編成 とも 同じ もの と なり 、 その後 他 の 車両 も 同一 の 表地 に 交換 さ れ た 。 EXE 車 の 投入 と 、 途中駅 を 重視 し た 特急 施策 によって 、 年間 利用者 数 は 1987年 に 1 , 100万人 だっ た もの が 2003年 に は 1 , 400万人 に 増加 し た < ref name =" rj 464 - 33 "/>。 
EXE 車 は 登場 直後 から 小田急 の 広告 ポスター など で イメージ リーダー として 起用 さ れ て い た < ref name =" rj 464 - 33 "/> が 、 箱根 特急 の 利用者 数 は 1987年 の 550万人 から 、 2003年 に は 300万人 程度 に 減少 し て い た < ref name =" rj 464 - 33 "/>。 箱根 を 訪れる 観光客 の 減少 も 理由 で は あっ た が 、 観光客 全体 の 減少 率 が 15 [[ パーセント |%]] 程度 で ある の に対し < ref name =" rj 464 - 33 "/>、 箱根 特急 の 利用者 数 は 45% も 減少 し て い た の で ある < ref name =" rj 464 - 33 "/>。 この 要因 を 調べる と 、 EXE 車 に は 「 小田急ロマンスカー の イメージ 」 と さ れ た 展望 席 が 存在 し なかっ た ため に 他 の 交通手段 に 転移 し た と み られ た < ref name =" rj 464 - 33 "/>。 2002年 から は イメージ リーダー として 起用 さ れる 車両 は HiSE 車 に 変更 さ れ た < ref name =" rj 464 - 34 "/>。 
EXE 車 は 登場 以来 、 新宿駅 へ は [[ 臨時列車 ]] や 突発 的 な 運用 変更 が ない 限り 10両編成 で 乗り入れ て い た < ref name =" rp 829 - 210 "/> が 、 2003年 3月29日 の ダイヤ改正 から は 平日 の 「はこね 」 2 往復 が 全 区間 6両編成 で 運行 さ れる こと に なっ た < ref name =" rp 829 - 210 "/>。 6両編成 で 新宿駅 に 乗り入れる 運用 は 初めて で あっ た < ref name =" rp 829 - 210 "/> が 、 この 運用 は 2004年 12月11日 の ダイヤ改正 で 見 られ なく なっ た < ref name =" rp 829 - 212 "/> が 、 2009年 3月14日 の ダイヤ改正 で は 、 平日 の 「はこね 」 1 往復 が 全 区間 6両編成 で 運行 さ れる こと に なっ た < ref name =" rp 829 - 217 "/>。 
2002年 2月1日 から 3月31日 まで 、 各 編成 の 1号 車 で [[ IPv6 ]] を 用い た [[ 無線LAN ]][[ インターネット ]] 接続 実験 が 行わ れ 、 < ref ></ ref > 2012年 から は WiMAX を バック ホール と する 「 au Wi-Fi SPOT 」 と 「 Wi 2 300 」 を 民鉄 の 有料特急 として は 初めて 導入 し た < ref >[ http:// www . odakyu .jp / program / info / data . info / 7713 _ 4317860 _. pd f# search =% 27% E 5% B 0% 8 F % E 7% 94% B 0% E 6% 80% A5 ex e+ % E 7% 84% A1 % E 7% B7 % 9 Alan % 27 民鉄 有料特急 初 の 公衆 無線ＬＡＮ サービス 登場 ！ ロマンスカー ・ ＥＸＥ に 「 au Wi-Fi SPOT 」 を 導入 － 今後 、 小田急 外国人 旅行 センター など 、 サービス を 駅 に 拡充 し て いき ます － ]</ ref >。（ 登場 し て から 10年 余り 経過 し た 2007年 に は 、 日本 デザイン 振興 会 より ロングライフデザイン 賞 を 受賞 し た < ref ></ ref >。 </MECAB>
  <ID>85992</ID><LATESTID>58892203</LATESTID><NAMESPACE>0</NAMESPACE><RESTRICTIONS>move=:edit=</RESTRICTIONS><ISREDIRECT>0</ISREDIRECT><ISNEW>0</ISNEW><RANDOM>1</RANDOM><TOUCHED>0.40609801257960498</TOUCHED><LINKSUPDATED>20160309045415</LINKSUPDATED><LEN>38789</LEN><CONTENTMODEL></CONTENTMODEL><LANG></LANG></ITEM>
