<ITEM>
  <TITEL>Suisui/Sandbox</TITLE>
  <META></META>
  <DESCRIPTION>	このページは[[ウィキペディア]]に関するさまざまな目的での連絡先をまとめたものです。\n\n[[画像:Contactus-wmcolors.png|right|]]\n\n== 質問 ==\n* 一般的な質問をしたいとき、たとえば一番近い銀河はどれなのか、ロシアの国旗はどれなのか、などの場合は[[Wikipedia:ヘルプデスク|ヘルプデスク]]へ質問してください。\n* ウィキペディア内で進行中の話題や技術的な質問については[[Wikipedia:井戸端|井戸端]]を訪れてみてください。\n* ウィキペディアの使い方についての質問は[[Wikipedia:井戸端]]で尋ねてみてください。\n\n== 記事に関して ==\n* 記事の編集方法などを知りたい場合には[[Wikipedia:ガイドブック|ガイドブック]]をご覧ください。\n* 記事編集のマークアップについて知りたいときには[[Wikipedia:編集の仕方|編集の仕方]]をご覧ください。\n* 記事の削除を希望される場合は[[Wikipedia:削除依頼|削除依頼]]に説明があります。\n* 削除された記事について復帰を希望される場合[[Wikipedia:復帰依頼|復帰依頼]]をご覧ください。\n* まだない記事の執筆を希望されるときには[[Wikipedia:執筆依頼|執筆依頼]]をご覧ください。	</DESCRIPTION>
  <BODY>3359893	このページは[[ウィキペディア]]に関するさまざまな目的での連絡先をまとめたものです。\n\n[[画像:Contactus-wmcolors.png|right|]]\n\n== 質問 ==\n* 一般的な質問をしたいとき、たとえば一番近い銀河はどれなのか、ロシアの国旗はどれなのか、などの場合は[[Wikipedia:ヘルプデスク|ヘルプデスク]]へ質問してください。\n* ウィキペディア内で進行中の話題や技術的な質問については[[Wikipedia:井戸端|井戸端]]を訪れてみてください。\n* ウィキペディアの使い方についての質問は[[Wikipedia:井戸端]]で尋ねてみてください。\n\n== 記事に関して ==\n* 記事の編集方法などを知りたい場合には[[Wikipedia:ガイドブック|ガイドブック]]をご覧ください。\n* 記事編集のマークアップについて知りたいときには[[Wikipedia:編集の仕方|編集の仕方]]をご覧ください。\n* 記事の削除を希望される場合は[[Wikipedia:削除依頼|削除依頼]]に説明があります。\n* 削除された記事について復帰を希望される場合[[Wikipedia:復帰依頼|復帰依頼]]をご覧ください。\n* まだない記事の執筆を希望されるときには[[Wikipedia:執筆依頼|執筆依頼]]をご覧ください。	</BODY>
  <MECAB>Suisui / Sandbox  この ページ は [[ ウィキペディア ]] に関する さまざま な 目的 で の 連絡先 を まとめ た もの です 。 
* 一般 的 な 質問 を し たい とき 、 たとえば 一番 近い 銀河 は どれ な の か 、 ロシア の 国旗 は どれ な の か 、 など の 場合 は [[ Wikipedia : ヘルプ デスク | ヘルプ デスク ]] へ 質問 し て ください 。 
* ウィキペディア 内 で 進行 中 の 話題 や 技術 的 な 質問 について は [[ Wikipedia : 井戸端 | 井戸端 ]] を 訪れ て み て ください 。 
* ウィキペディア の 使い方 について の 質問 は [[ Wikipedia : 井戸端 ]] で 尋ね て み て ください 。 
* 記事 の 編集 方法 など を 知り たい 場合 に は [[ Wikipedia : ガイドブック | ガイドブック ]] を ご覧 ください 。 
* 記事 編集 の マークアップ について 知り たい とき に は [[ Wikipedia : 編集 の 仕方 | 編集 の 仕方 ]] を ご覧 ください 。 
* 記事 の 削除 を 希望 さ れる 場合 は [[ Wikipedia : 削除依頼 | 削除依頼 ]] に 説明 が あり ます 。 
* 削除 さ れ た 記事 について 復帰 を 希望 さ れる 場合 [[ Wikipedia : 復帰依頼 | 復帰依頼 ]] を ご覧 ください 。 
* まだ ない 記事 の 執筆 を 希望 さ れる とき に は [[ Wikipedia : 執筆 依頼 | 執筆 依頼 ]] を ご覧 ください 。 </MECAB>
  <ID>55599</ID><LATESTID>3359893</LATESTID><NAMESPACE>2</NAMESPACE><RESTRICTIONS>move=:edit=</RESTRICTIONS><ISREDIRECT>0</ISREDIRECT><ISNEW>0</ISNEW><RANDOM>1</RANDOM><TOUCHED>0.071847170824185014</TOUCHED><LINKSUPDATED>20051030041330</LINKSUPDATED><LEN>1336</LEN><CONTENTMODEL></CONTENTMODEL><LANG></LANG></ITEM>
